Workbook

Sheet Gifts
A1: BIRTHDAYS | P1: EVENTS
A2: Birthdays / Card 2021 | B2: Birth Date | D2: Death | E2: Current Age | F2: Gift Value | G2: Ideas | H2: Done? | I2: Spent | J2: Remaining | K2: Total spend | L2: Target | M2: Actual | N2: Time | P2: Month | Q2: Date | R2: Amount | S2: Ideas | T2: Spent | U2: Remaining
A3: JAN | B3: =SUM(F4:F12) -> 30 | J3: =SUM(J4:J12) -> -5 | K3: =SUM(B3,R3) -> 140 | L3: =($F$105/12)-K3 -> 95 | M3: =IF(N3<>"",N3,($F$105/12)-(B3-R3)+(J3+U3)) -> 275.43 | N3: 275.43 | P3: JAN | R3: =SUM(R4:R12) -> 110 | U3: =SUM(U4:U12) -> 110
A4: Ruby | B4: 43102 | E4: =DATEDIF(B4,NOW(),"y") -> 8 | F4: 20
A5: Sam | B5: 39453 | C5: =TEXT(B5,"MMDD") -> 0106 | E5: =DATEDIF(B5,NOW(),"y") -> 18 | F5: 10 | G5: Cash | H5: Y | I5: 10 | J5: =IF(N5="MISSED",F5,F5-I5) -> 0 | N5: =IF(TEXT(TODAY(),"YYYY")=RIGHT(A$2,4), IF(ISERROR(DATEDIF(TEXT(TODAY(),"dd/mm/yyyy"),TEXT(B5,"dd/mm/")&RIGHT(A$2,4),"d")),IF(H5="Y","DONE","MISSED"), IF(DATEDIF(TEXT(TODAY(),"dd/mm/yyyy"),TEXT(B5,"dd/mm/")&RIGHT(A$2,4),"d") = 0,"TODAY!!!", IF(DATEDIF(TEXT(TODAY(),"dd/mm/yyyy"),TEXT(B5,"dd/mm/")&RIGHT(A$2,4),"d") > 0, DATEDIF(TEXT(TODAY(),"dd/mm/yyyy"), TEXT(B5,"dd/mm/")&RIGHT(A$2,4),"d")&" Days to go!",""))),"") | P5: NY Gifts | Q5: 1 | R5: 110 | U5: =R5-T5 -> 110
A6: Jamie | B6: =DATE(1990,1,6) -> 32879 | C6: =TEXT(B6,"MMDD") -> 0106 | E6: =DATEDIF(B6,NOW(),"y") -> 36 | F6: 0 | J6: =IF(N6="MISSED",F6,F6-I6) -> 0 | N6: =IF(TEXT(TODAY(),"YYYY")=RIGHT(A$2,4), IF(ISERROR(DATEDIF(TEXT(TODAY(),"dd/mm/yyyy"),TEXT(B6,"dd/mm/")&RIGHT(A$2,4),"d")),IF(H6="Y","DONE","MISSED"), IF(DATEDIF(TEXT(TODAY(),"dd/mm/yyyy"),TEXT(B6,"dd/mm/")&RIGHT(A$2,4),"d") = 0,"TODAY!!!", IF(DATEDIF(TEXT(TODAY(),"dd/mm/yyyy"),TEXT(B6,"dd/mm/")&RIGHT(A$2,4),"d") > 0, DATEDIF(TEXT(TODAY(),"dd/mm/yyyy"), TEXT(B6,"dd/mm/")&RIGHT(A$2,4),"d")&" Days to go!",""))),"")
A7: Amanda | B7: 42376 | C7: =TEXT(B7,"MMDD") -> 0107 | E7: =DATEDIF(B7,NOW(),"y") -> 10 | F7: 0 | J7: =IF(N7="MISSED",F7,F7-I7) -> 0 | N7: =IF(TEXT(TODAY(),"YYYY")=RIGHT(A$2,4), IF(ISERROR(DATEDIF(TEXT(TODAY(),"dd/mm/yyyy"),TEXT(B7,"dd/mm/")&RIGHT(A$2,4),"d")),IF(H7="Y","DONE","MISSED"), IF(DATEDIF(TEXT(TODAY(),"dd/mm/yyyy"),TEXT(B7,"dd/mm/")&RIGHT(A$2,4),"d") = 0,"TODAY!!!", IF(DATEDIF(TEXT(TODAY(),"dd/mm/yyyy"),TEXT(B7,"dd/mm/")&RIGHT(A$2,4),"d") > 0, DATEDIF(TEXT(TODAY(),"dd/mm/yyyy"), TEXT(B7,"dd/mm/")&RIGHT(A$2,4),"d")&" Days to go!",""))),"")
A8: Uncle Andrew (Auntie Julie) | B8: 42378 | C8: =TEXT(B8,"MMDD") -> 0109 | E8: =DATEDIF(B8,NOW(),"y") -> 10 | F8: 0 | H8: Y | I8: 5 | J8: =IF(N8="MISSED",F8,F8-I8) -> -5 | N8: =IF(TEXT(TODAY(),"YYYY")=RIGHT(A$2,4), IF(ISERROR(DATEDIF(TEXT(TODAY(),"dd/mm/yyyy"),TEXT(B8,"dd/mm/")&RIGHT(A$2,4),"d")),IF(H8="Y","DONE","MISSED"), IF(DATEDIF(TEXT(TODAY(),"dd/mm/yyyy"),TEXT(B8,"dd/mm/")&RIGHT(A$2,4),"d") = 0,"TODAY!!!", IF(DATEDIF(TEXT(TODAY(),"dd/mm/yyyy"),TEXT(B8,"dd/mm/")&RIGHT(A$2,4),"d") > 0, DATEDIF(TEXT(TODAY(),"dd/mm/yyyy"), TEXT(B8,"dd/mm/")&RIGHT(A$2,4),"d")&" Days to go!",""))),"")
A9: Uncle Andrew (JJ) (RIP) | B9: 42382 | C9: =TEXT(B9,"MMDD") -> 0113 | E9: =DATEDIF(B9,NOW(),"y") -> 10 | F9: 0 | J9: =IF(N9="MISSED",F9,F9-I9) -> 0 | N9: =IF(TEXT(TODAY(),"YYYY")=RIGHT(A$2,4), IF(ISERROR(DATEDIF(TEXT(TODAY(),"dd/mm/yyyy"),TEXT(B9,"dd/mm/")&RIGHT(A$2,4),"d")),IF(H9="Y","DONE","MISSED"), IF(DATEDIF(TEXT(TODAY(),"dd/mm/yyyy"),TEXT(B9,"dd/mm/")&RIGHT(A$2,4),"d") = 0,"TODAY!!!", IF(DATEDIF(TEXT(TODAY(),"dd/mm/yyyy"),TEXT(B9,"dd/mm/")&RIGHT(A$2,4),"d") > 0, DATEDIF(TEXT(TODAY(),"dd/mm/yyyy"), TEXT(B9,"dd/mm/")&RIGHT(A$2,4),"d")&" Days to go!",""))),"")
A10: Rachel | B10: 42383 | C10: =TEXT(B10,"MMDD") -> 0114 | E10: =DATEDIF(B10,NOW(),"y") -> 10 | F10: 0 | J10: =IF(N10="MISSED",F10,F10-I10) -> 0 | N10: =IF(TEXT(TODAY(),"YYYY")=RIGHT(A$2,4), IF(ISERROR(DATEDIF(TEXT(TODAY(),"dd/mm/yyyy"),TEXT(B10,"dd/mm/")&RIGHT(A$2,4),"d")),IF(H10="Y","DONE","MISSED"), IF(DATEDIF(TEXT(TODAY(),"dd/mm/yyyy"),TEXT(B10,"dd/mm/")&RIGHT(A$2,4),"d") = 0,"TODAY!!!", IF(DATEDIF(TEXT(TODAY(),"dd/mm/yyyy"),TEXT(B10,"dd/mm/")&RIGHT(A$2,4),"d") > 0, DATEDIF(TEXT(TODAY(),"dd/mm/yyyy"), TEXT(B10,"dd/mm/")&RIGHT(A$2,4),"d")&" Days to go!",""))),"")
A11: Auntie Susan | B11: 20115 | C11: =TEXT(B11,"MMDD") -> 0126 | E11: =DATEDIF(B11,NOW(),"y") -> 71 | F11: 0 | J11: =IF(N11="MISSED",F11,F11-I11) -> 0 | N11: =IF(TEXT(TODAY(),"YYYY")=RIGHT(A$2,4), IF(ISERROR(DATEDIF(TEXT(TODAY(),"dd/mm/yyyy"),TEXT(B11,"dd/mm/")&RIGHT(A$2,4),"d")),IF(H11="Y","DONE","MISSED"), IF(DATEDIF(TEXT(TODAY(),"dd/mm/yyyy"),TEXT(B11,"dd/mm/")&RIGHT(A$2,4),"d") = 0,"TODAY!!!", IF(DATEDIF(TEXT(TODAY(),"dd/mm/yyyy"),TEXT(B11,"dd/mm/")&RIGHT(A$2,4),"d") > 0, DATEDIF(TEXT(TODAY(),"dd/mm/yyyy"), TEXT(B11,"dd/mm/")&RIGHT(A$2,4),"d")&" Days to go!",""))),"")
A12: Malcolm | B12: 42396 | C12: =TEXT(B12,"MMDD") -> 0127 | E12: =DATEDIF(B12,NOW(),"y") -> 10 | F12: 0 | J12: =IF(N12="MISSED",F12,F12-I12) -> 0 | N12: =IF(TEXT(TODAY(),"YYYY")=RIGHT(A$2,4), IF(ISERROR(DATEDIF(TEXT(TODAY(),"dd/mm/yyyy"),TEXT(B12,"dd/mm/")&RIGHT(A$2,4),"d")),IF(H12="Y","DONE","MISSED"), IF(DATEDIF(TEXT(TODAY(),"dd/mm/yyyy"),TEXT(B12,"dd/mm/")&RIGHT(A$2,4),"d") = 0,"TODAY!!!", IF(DATEDIF(TEXT(TODAY(),"dd/mm/yyyy"),TEXT(B12,"dd/mm/")&RIGHT(A$2,4),"d") > 0, DATEDIF(TEXT(TODAY(),"dd/mm/yyyy"), TEXT(B12,"dd/mm/")&RIGHT(A$2,4),"d")&" Days to go!",""))),"")
A14: FEB | B14: =SUM(F15:F19) -> 30 | J14: =SUM(J15:J19) -> -25.99 | K14: =SUM(B14,R14) -> 80 | L14: =L3+($F$105/12)-B14-R14 -> 250 | M14: =IF(N14<>"",N14,(M3+($F$105/12))-B14-R14+(J14+U14)) -> 454.44 | P14: FEB | R14: =SUM(R15:R19) -> 50 | U14: =SUM(U15:U19) -> 50
A15: Uncle Keith | B15: 42401 | C15: =TEXT(B15,"MMDD") -> 0201 | E15: =DATEDIF(B15,NOW(),"y") -> 10 | F15: 0 | G15: Beer | J15: =IF(N15="MISSED",F15,F15-I15) -> 0 | N15: =IF(TEXT(TODAY(),"YYYY")=RIGHT(A$2,4), IF(ISERROR(DATEDIF(TEXT(TODAY(),"dd/mm/yyyy"),TEXT(B15,"dd/mm/")&RIGHT(A$2,4),"d")),IF(H15="Y","DONE","MISSED"), IF(DATEDIF(TEXT(TODAY(),"dd/mm/yyyy"),TEXT(B15,"dd/mm/")&RIGHT(A$2,4),"d") = 0,"TODAY!!!", IF(DATEDIF(TEXT(TODAY(),"dd/mm/yyyy"),TEXT(B15,"dd/mm/")&RIGHT(A$2,4),"d") > 0, DATEDIF(TEXT(TODAY(),"dd/mm/yyyy"), TEXT(B15,"dd/mm/")&RIGHT(A$2,4),"d")&" Days to go!",""))),"") | P15: Valentines | Q15: 14th | R15: 50 | U15: =R15-T15 -> 50
A16: Alfie | B16: 45691 | E16: =DATEDIF(B16,NOW(),"y") -> 1 | F16: 20
A17: Jordan | B17: 34368 | C17: =TEXT(B17,"MMDD") -> 0203 | E17: =DATEDIF(B17,NOW(),"y") -> 32 | F17: 0 | H17: Y | I17: 25.99 | J17: =IF(N17="MISSED",F17,F17-I17) -> -25.99 | N17: =IF(TEXT(TODAY(),"YYYY")=RIGHT(A$2,4), IF(ISERROR(DATEDIF(TEXT(TODAY(),"dd/mm/yyyy"),TEXT(B17,"dd/mm/")&RIGHT(A$2,4),"d")),IF(H17="Y","DONE","MISSED"), IF(DATEDIF(TEXT(TODAY(),"dd/mm/yyyy"),TEXT(B17,"dd/mm/")&RIGHT(A$2,4),"d") = 0,"TODAY!!!", IF(DATEDIF(TEXT(TODAY(),"dd/mm/yyyy"),TEXT(B17,"dd/mm/")&RIGHT(A$2,4),"d") > 0, DATEDIF(TEXT(TODAY(),"dd/mm/yyyy"), TEXT(B17,"dd/mm/")&RIGHT(A$2,4),"d")&" Days to go!",""))),"")
A18: Auntie Jo | B18: 42404 | C18: =TEXT(B18,"MMDD") -> 0204 | E18: =DATEDIF(B18,NOW(),"y") -> 10 | F18: 0 | J18: =IF(N18="MISSED",F18,F18-I18) -> 0 | N18: =IF(TEXT(TODAY(),"YYYY")=RIGHT(A$2,4), IF(ISERROR(DATEDIF(TEXT(TODAY(),"dd/mm/yyyy"),TEXT(B18,"dd/mm/")&RIGHT(A$2,4),"d")),IF(H18="Y","DONE","MISSED"), IF(DATEDIF(TEXT(TODAY(),"dd/mm/yyyy"),TEXT(B18,"dd/mm/")&RIGHT(A$2,4),"d") = 0,"TODAY!!!", IF(DATEDIF(TEXT(TODAY(),"dd/mm/yyyy"),TEXT(B18,"dd/mm/")&RIGHT(A$2,4),"d") > 0, DATEDIF(TEXT(TODAY(),"dd/mm/yyyy"), TEXT(B18,"dd/mm/")&RIGHT(A$2,4),"d")&" Days to go!",""))),"")
A19: William | B19: 40215 | C19: =TEXT(B19,"MMDD") -> 0206 | E19: =DATEDIF(B19,NOW(),"y") -> 16 | F19: 10 | G19: Cash | H19: Y | I19: 10 | J19: =IF(N19="MISSED",F19,F19-I19) -> 0 | N19: =IF(TEXT(TODAY(),"YYYY")=RIGHT(A$2,4), IF(ISERROR(DATEDIF(TEXT(TODAY(),"dd/mm/yyyy"),TEXT(B19,"dd/mm/")&RIGHT(A$2,4),"d")),IF(H19="Y","DONE","MISSED"), IF(DATEDIF(TEXT(TODAY(),"dd/mm/yyyy"),TEXT(B19,"dd/mm/")&RIGHT(A$2,4),"d") = 0,"TODAY!!!", IF(DATEDIF(TEXT(TODAY(),"dd/mm/yyyy"),TEXT(B19,"dd/mm/")&RIGHT(A$2,4),"d") > 0, DATEDIF(TEXT(TODAY(),"dd/mm/yyyy"), TEXT(B19,"dd/mm/")&RIGHT(A$2,4),"d")&" Days to go!",""))),"")
P20: =275+250 -> 525
A21: MAR | B21: =SUM(F22:F30) -> 105 | J21: =SUM(J22:J30) -> 80 | K21: =SUM(B21,R21) -> 305 | L21: =L14+(($F$105/12)-B21-R21) -> 180 | M21: =IF(N21<>"",N21,(M14+($F$105/12))-B21-R21+(J21+U21)) -> 664.44 | P21: MAR | R21: =SUM(R24:R28) -> 200 | U21: =SUM(U24:U28) -> 200
A22: Inesa | B22: 27829 | E22: =DATEDIF(B22,NOW(),"y") -> 50 | F22: 0 | H22: Y | J22: =IF(N22="MISSED",F22,F22-I22) -> 0 | N22: =IF(TEXT(TODAY(),"YYYY")=RIGHT(A$2,4), IF(ISERROR(DATEDIF(TEXT(TODAY(),"dd/mm/yyyy"),TEXT(B22,"dd/mm/")&RIGHT(A$2,4),"d")),IF(H22="Y","DONE","MISSED"), IF(DATEDIF(TEXT(TODAY(),"dd/mm/yyyy"),TEXT(B22,"dd/mm/")&RIGHT(A$2,4),"d") = 0,"TODAY!!!", IF(DATEDIF(TEXT(TODAY(),"dd/mm/yyyy"),TEXT(B22,"dd/mm/")&RIGHT(A$2,4),"d") > 0, DATEDIF(TEXT(TODAY(),"dd/mm/yyyy"), TEXT(B22,"dd/mm/")&RIGHT(A$2,4),"d")&" Days to go!",""))),"")
A23: Babu | F23: 40 | H23: Y | J23: =IF(N23="MISSED",F23,F23-I23) -> 40
A24: Lea | B24: 37694 | C24: =TEXT(B24,"MMDD") -> 0314 | E24: =DATEDIF(B24,NOW(),"y") -> 23 | F24: 0 | G24: Cash | H24: Y | J24: =IF(N24="MISSED",F24,F24-I24) -> 0 | N24: =IF(TEXT(TODAY(),"YYYY")=RIGHT(A$2,4), IF(ISERROR(DATEDIF(TEXT(TODAY(),"dd/mm/yyyy"),TEXT(B24,"dd/mm/")&RIGHT(A$2,4),"d")),IF(H24="Y","DONE","MISSED"), IF(DATEDIF(TEXT(TODAY(),"dd/mm/yyyy"),TEXT(B24,"dd/mm/")&RIGHT(A$2,4),"d") = 0,"TODAY!!!", IF(DATEDIF(TEXT(TODAY(),"dd/mm/yyyy"),TEXT(B24,"dd/mm/")&RIGHT(A$2,4),"d") > 0, DATEDIF(TEXT(TODAY(),"dd/mm/yyyy"), TEXT(B24,"dd/mm/")&RIGHT(A$2,4),"d")&" Days to go!",""))),"") | P24: Womens Day | Q24: 8th | R24: 100 | S24: Flowers (kris, mum, inessa) | U24: =R24-T24 -> 100
A25: Morgan | B25: 37694 | C25: =TEXT(B25,"MMDD") -> 0314 | E25: =DATEDIF(B25,NOW(),"y") -> 23 | F25: 0 | G25: Cash | H25: Y | J25: =IF(N25="MISSED",F25,F25-I25) -> 0 | N25: =IF(TEXT(TODAY(),"YYYY")=RIGHT(A$2,4), IF(ISERROR(DATEDIF(TEXT(TODAY(),"dd/mm/yyyy"),TEXT(B25,"dd/mm/")&RIGHT(A$2,4),"d")),IF(H25="Y","DONE","MISSED"), IF(DATEDIF(TEXT(TODAY(),"dd/mm/yyyy"),TEXT(B25,"dd/mm/")&RIGHT(A$2,4),"d") = 0,"TODAY!!!", IF(DATEDIF(TEXT(TODAY(),"dd/mm/yyyy"),TEXT(B25,"dd/mm/")&RIGHT(A$2,4),"d") > 0, DATEDIF(TEXT(TODAY(),"dd/mm/yyyy"), TEXT(B25,"dd/mm/")&RIGHT(A$2,4),"d")&" Days to go!",""))),"") | P25: Mothers Day | Q25: 27th | R25: 100 | S25: Day out | U25: =R25-T25 -> 100
A26: Dave | B26: 35145 | C26: =TEXT(B26,"MMDD") -> 0321 | E26: =DATEDIF(B26,NOW(),"y") -> 30 | F26: 0 | J26: =IF(N26="MISSED",F26,F26-I26) -> 0 | N26: =IF(TEXT(TODAY(),"YYYY")=RIGHT(A$2,4), IF(ISERROR(DATEDIF(TEXT(TODAY(),"dd/mm/yyyy"),TEXT(B26,"dd/mm/")&RIGHT(A$2,4),"d")),IF(H26="Y","DONE","MISSED"), IF(DATEDIF(TEXT(TODAY(),"dd/mm/yyyy"),TEXT(B26,"dd/mm/")&RIGHT(A$2,4),"d") = 0,"TODAY!!!", IF(DATEDIF(TEXT(TODAY(),"dd/mm/yyyy"),TEXT(B26,"dd/mm/")&RIGHT(A$2,4),"d") > 0, DATEDIF(TEXT(TODAY(),"dd/mm/yyyy"), TEXT(B26,"dd/mm/")&RIGHT(A$2,4),"d")&" Days to go!",""))),"")
A27: Auntie Jean (RIP) | B27: 42453 | C27: =TEXT(B27,"MMDD") -> 0324 | D27: ?? | E27: =DATEDIF(B27,NOW(),"y") -> 10 | F27: 0 | J27: =IF(N27="MISSED",F27,F27-I27) -> 0 | N27: =IF(TEXT(TODAY(),"YYYY")=RIGHT(A$2,4), IF(ISERROR(DATEDIF(TEXT(TODAY(),"dd/mm/yyyy"),TEXT(B27,"dd/mm/")&RIGHT(A$2,4),"d")),IF(H27="Y","DONE","MISSED"), IF(DATEDIF(TEXT(TODAY(),"dd/mm/yyyy"),TEXT(B27,"dd/mm/")&RIGHT(A$2,4),"d") = 0,"TODAY!!!", IF(DATEDIF(TEXT(TODAY(),"dd/mm/yyyy"),TEXT(B27,"dd/mm/")&RIGHT(A$2,4),"d") > 0, DATEDIF(TEXT(TODAY(),"dd/mm/yyyy"), TEXT(B27,"dd/mm/")&RIGHT(A$2,4),"d")&" Days to go!",""))),"")
A28: Uncle Chris | B28: 42458 | C28: =TEXT(B28,"MMDD") -> 0329 | E28: =DATEDIF(B28,NOW(),"y") -> 10 | F28: 0 | J28: =IF(N28="MISSED",F28,F28-I28) -> 0 | N28: =IF(TEXT(TODAY(),"YYYY")=RIGHT(A$2,4), IF(ISERROR(DATEDIF(TEXT(TODAY(),"dd/mm/yyyy"),TEXT(B28,"dd/mm/")&RIGHT(A$2,4),"d")),IF(H28="Y","DONE","MISSED"), IF(DATEDIF(TEXT(TODAY(),"dd/mm/yyyy"),TEXT(B28,"dd/mm/")&RIGHT(A$2,4),"d") = 0,"TODAY!!!", IF(DATEDIF(TEXT(TODAY(),"dd/mm/yyyy"),TEXT(B28,"dd/mm/")&RIGHT(A$2,4),"d") > 0, DATEDIF(TEXT(TODAY(),"dd/mm/yyyy"), TEXT(B28,"dd/mm/")&RIGHT(A$2,4),"d")&" Days to go!",""))),"")
A29: Hugo | B29: 42823 | E29: =DATEDIF(B29,NOW(),"y") -> 9 | F29: 25
A30: Tania | B30: 20545 | C30: =TEXT(B30,"MMDD") -> 0331 | E30: =DATEDIF(B30,NOW(),"y") -> 70 | F30: 40 | H30: Y | J30: =IF(N30="MISSED",F30,F30-I30) -> 40 | N30: =IF(TEXT(TODAY(),"YYYY")=RIGHT(A$2,4), IF(ISERROR(DATEDIF(TEXT(TODAY(),"dd/mm/yyyy"),TEXT(B30,"dd/mm/")&RIGHT(A$2,4),"d")),IF(H30="Y","DONE","MISSED"), IF(DATEDIF(TEXT(TODAY(),"dd/mm/yyyy"),TEXT(B30,"dd/mm/")&RIGHT(A$2,4),"d") = 0,"TODAY!!!", IF(DATEDIF(TEXT(TODAY(),"dd/mm/yyyy"),TEXT(B30,"dd/mm/")&RIGHT(A$2,4),"d") > 0, DATEDIF(TEXT(TODAY(),"dd/mm/yyyy"), TEXT(B30,"dd/mm/")&RIGHT(A$2,4),"d")&" Days to go!",""))),"")
A32: APR | B32: =SUM(F33:F35) -> 50 | J32: =SUM(J33:J35) -> 50 | K32: =SUM(B32,R32) -> 100 | L32: =L21+(($F$105/12))-B32-R32 -> 315 | M32: =IF(N32<>"",N32,(M21+($F$105/12))-B32-R32+(J32+U32)) -> 79 | N32: 79 | P32: APR | R32: =SUM(R33:R35) -> 50 | U32: =SUM(U33:U35) -> 50
A33: Dad | B33: 18733 | C33: =TEXT(B33,"MMDD") -> 0415 | E33: =DATEDIF(B33,NOW(),"y") -> 75 | F33: 50 | H33: Y | J33: =IF(N33="MISSED",F33,F33-I33) -> 50 | N33: =IF(TEXT(TODAY(),"YYYY")=RIGHT(A$2,4), IF(ISERROR(DATEDIF(TEXT(TODAY(),"dd/mm/yyyy"),TEXT(B33,"dd/mm/")&RIGHT(A$2,4),"d")),IF(H33="Y","DONE","MISSED"), IF(DATEDIF(TEXT(TODAY(),"dd/mm/yyyy"),TEXT(B33,"dd/mm/")&RIGHT(A$2,4),"d") = 0,"TODAY!!!", IF(DATEDIF(TEXT(TODAY(),"dd/mm/yyyy"),TEXT(B33,"dd/mm/")&RIGHT(A$2,4),"d") > 0, DATEDIF(TEXT(TODAY(),"dd/mm/yyyy"), TEXT(B33,"dd/mm/")&RIGHT(A$2,4),"d")&" Days to go!",""))),"") | P33: Mum + Dad Anv | Q33: 1st | R33: 50 | S33: Dinner | U33: =R33-T33 -> 50
A34: Sarah | B34: 34074 | E34: =DATEDIF(B34,NOW(),"y") -> 33 | F34: 0 | J34: =IF(N34="MISSED",F34,F34-I34) -> 0
A35: Grandad (RIP) | B35: 12162 | C35: =TEXT(B35,"MMDD") -> 0418 | D35: ?? | E35: =DATEDIF(B35,NOW(),"y") -> 93 | F35: 0 | J35: =IF(N35="MISSED",F35,F35-I35) -> 0 | N35: =IF(TEXT(TODAY(),"YYYY")=RIGHT(A$2,4), IF(ISERROR(DATEDIF(TEXT(TODAY(),"dd/mm/yyyy"),TEXT(B35,"dd/mm/")&RIGHT(A$2,4),"d")),IF(H35="Y","DONE","MISSED"), IF(DATEDIF(TEXT(TODAY(),"dd/mm/yyyy"),TEXT(B35,"dd/mm/")&RIGHT(A$2,4),"d") = 0,"TODAY!!!", IF(DATEDIF(TEXT(TODAY(),"dd/mm/yyyy"),TEXT(B35,"dd/mm/")&RIGHT(A$2,4),"d") > 0, DATEDIF(TEXT(TODAY(),"dd/mm/yyyy"), TEXT(B35,"dd/mm/")&RIGHT(A$2,4),"d")&" Days to go!",""))),"")
A37: MAY | B37: =SUM(F38:F45) -> 25 | J37: =SUM(J38:J45) -> 0 | K37: =SUM(B37,R37) -> 125 | L37: =L32+($F$105/12)-B37-R37 -> 425 | M37: =IF(N37<>"",N37,(M32+($F$105/12))-B37-R37+(J37+U37)+13) -> 202 | P37: MAY | R37: =SUM(R38:R45) -> 100 | U37: =SUM(U38:U45) -> 0
A38: Brother Andrew | B38: 42495 | C38: =TEXT(B38,"MMDD") -> 0505 | E38: =DATEDIF(B38,NOW(),"y") -> 10 | F38: 0 | J38: =IF(N38="MISSED",F38,F38-I38) -> 0 | N38: =IF(TEXT(TODAY(),"YYYY")=RIGHT(A$2,4), IF(ISERROR(DATEDIF(TEXT(TODAY(),"dd/mm/yyyy"),TEXT(B38,"dd/mm/")&RIGHT(A$2,4),"d")),IF(H38="Y","DONE","MISSED"), IF(DATEDIF(TEXT(TODAY(),"dd/mm/yyyy"),TEXT(B38,"dd/mm/")&RIGHT(A$2,4),"d") = 0,"TODAY!!!", IF(DATEDIF(TEXT(TODAY(),"dd/mm/yyyy"),TEXT(B38,"dd/mm/")&RIGHT(A$2,4),"d") > 0, DATEDIF(TEXT(TODAY(),"dd/mm/yyyy"), TEXT(B38,"dd/mm/")&RIGHT(A$2,4),"d")&" Days to go!",""))),"") | P38: Anniversary | Q38: 17 | R38: 100 | S38: Dinner
A39: Christian | B39: 33730 | C39: =TEXT(B39,"MMDD") -> 0506 | E39: =DATEDIF(B39,NOW(),"y") -> 34 | F39: 0 | J39: =IF(N39="MISSED",F39,F39-I39) -> 0 | N39: =IF(TEXT(TODAY(),"YYYY")=RIGHT(A$2,4), IF(ISERROR(DATEDIF(TEXT(TODAY(),"dd/mm/yyyy"),TEXT(B39,"dd/mm/")&RIGHT(A$2,4),"d")),IF(H39="Y","DONE","MISSED"), IF(DATEDIF(TEXT(TODAY(),"dd/mm/yyyy"),TEXT(B39,"dd/mm/")&RIGHT(A$2,4),"d") = 0,"TODAY!!!", IF(DATEDIF(TEXT(TODAY(),"dd/mm/yyyy"),TEXT(B39,"dd/mm/")&RIGHT(A$2,4),"d") > 0, DATEDIF(TEXT(TODAY(),"dd/mm/yyyy"), TEXT(B39,"dd/mm/")&RIGHT(A$2,4),"d")&" Days to go!",""))),"")
A40: Brother Lee | B40: 27895 | C40: =TEXT(B40,"MMDD") -> 0515 | E40: =DATEDIF(B40,NOW(),"y") -> 50 | F40: 0 | J40: =IF(N40="MISSED",F40,F40-I40) -> 0 | N40: =IF(TEXT(TODAY(),"YYYY")=RIGHT(A$2,4), IF(ISERROR(DATEDIF(TEXT(TODAY(),"dd/mm/yyyy"),TEXT(B40,"dd/mm/")&RIGHT(A$2,4),"d")),IF(H40="Y","DONE","MISSED"), IF(DATEDIF(TEXT(TODAY(),"dd/mm/yyyy"),TEXT(B40,"dd/mm/")&RIGHT(A$2,4),"d") = 0,"TODAY!!!", IF(DATEDIF(TEXT(TODAY(),"dd/mm/yyyy"),TEXT(B40,"dd/mm/")&RIGHT(A$2,4),"d") > 0, DATEDIF(TEXT(TODAY(),"dd/mm/yyyy"), TEXT(B40,"dd/mm/")&RIGHT(A$2,4),"d")&" Days to go!",""))),"")
A41: Brother Craig | B41: 27895 | C41: =TEXT(B41,"MMDD") -> 0515 | E41: =DATEDIF(B41,NOW(),"y") -> 50 | F41: 0 | J41: =IF(N41="MISSED",F41,F41-I41) -> 0 | N41: =IF(TEXT(TODAY(),"YYYY")=RIGHT(A$2,4), IF(ISERROR(DATEDIF(TEXT(TODAY(),"dd/mm/yyyy"),TEXT(B41,"dd/mm/")&RIGHT(A$2,4),"d")),IF(H41="Y","DONE","MISSED"), IF(DATEDIF(TEXT(TODAY(),"dd/mm/yyyy"),TEXT(B41,"dd/mm/")&RIGHT(A$2,4),"d") = 0,"TODAY!!!", IF(DATEDIF(TEXT(TODAY(),"dd/mm/yyyy"),TEXT(B41,"dd/mm/")&RIGHT(A$2,4),"d") > 0, DATEDIF(TEXT(TODAY(),"dd/mm/yyyy"), TEXT(B41,"dd/mm/")&RIGHT(A$2,4),"d")&" Days to go!",""))),"")
A42: Dax | B42: 43236 | E42: =DATEDIF(B42,NOW(),"y") -> 8 | F42: 25
A43: Uncle Mick (RIP) | B43: 16942 | C43: =TEXT(B43,"MMDD") -> 0520 | E43: =DATEDIF(B43,NOW(),"y") -> 80 | F43: 0 | J43: =IF(N43="MISSED",F43,F43-I43) -> 0 | N43: =IF(TEXT(TODAY(),"YYYY")=RIGHT(A$2,4), IF(ISERROR(DATEDIF(TEXT(TODAY(),"dd/mm/yyyy"),TEXT(B43,"dd/mm/")&RIGHT(A$2,4),"d")),IF(H43="Y","DONE","MISSED"), IF(DATEDIF(TEXT(TODAY(),"dd/mm/yyyy"),TEXT(B43,"dd/mm/")&RIGHT(A$2,4),"d") = 0,"TODAY!!!", IF(DATEDIF(TEXT(TODAY(),"dd/mm/yyyy"),TEXT(B43,"dd/mm/")&RIGHT(A$2,4),"d") > 0, DATEDIF(TEXT(TODAY(),"dd/mm/yyyy"), TEXT(B43,"dd/mm/")&RIGHT(A$2,4),"d")&" Days to go!",""))),"")
A44: Adam | B44: 42512 | C44: =TEXT(B44,"MMDD") -> 0522 | E44: =DATEDIF(B44,NOW(),"y") -> 10 | F44: 0 | G44: Xbox card | J44: =IF(N44="MISSED",F44,F44-I44) -> 0 | N44: =IF(TEXT(TODAY(),"YYYY")=RIGHT(A$2,4), IF(ISERROR(DATEDIF(TEXT(TODAY(),"dd/mm/yyyy"),TEXT(B44,"dd/mm/")&RIGHT(A$2,4),"d")),IF(H44="Y","DONE","MISSED"), IF(DATEDIF(TEXT(TODAY(),"dd/mm/yyyy"),TEXT(B44,"dd/mm/")&RIGHT(A$2,4),"d") = 0,"TODAY!!!", IF(DATEDIF(TEXT(TODAY(),"dd/mm/yyyy"),TEXT(B44,"dd/mm/")&RIGHT(A$2,4),"d") > 0, DATEDIF(TEXT(TODAY(),"dd/mm/yyyy"), TEXT(B44,"dd/mm/")&RIGHT(A$2,4),"d")&" Days to go!",""))),"")
A45: Alex | B45: 42513 | C45: =TEXT(B45,"MMDD") -> 0523 | E45: =DATEDIF(B45,NOW(),"y") -> 10 | F45: 0 | G45: Flowers | J45: =IF(N45="MISSED",F45,F45-I45) -> 0 | N45: =IF(TEXT(TODAY(),"YYYY")=RIGHT(A$2,4), IF(ISERROR(DATEDIF(TEXT(TODAY(),"dd/mm/yyyy"),TEXT(B45,"dd/mm/")&RIGHT(A$2,4),"d")),IF(H45="Y","DONE","MISSED"), IF(DATEDIF(TEXT(TODAY(),"dd/mm/yyyy"),TEXT(B45,"dd/mm/")&RIGHT(A$2,4),"d") = 0,"TODAY!!!", IF(DATEDIF(TEXT(TODAY(),"dd/mm/yyyy"),TEXT(B45,"dd/mm/")&RIGHT(A$2,4),"d") > 0, DATEDIF(TEXT(TODAY(),"dd/mm/yyyy"), TEXT(B45,"dd/mm/")&RIGHT(A$2,4),"d")&" Days to go!",""))),"")
A47: JUN | B47: =SUM(F48:F54) -> 60 | J47: =SUM(J48:J54) -> 40 | K47: =SUM(B47,R47) -> 160 | L47: =L37+($F$105/12)-B47-R47 -> 500 | M47: =IF(N47<>"",N47,(M37+($F$105/12))-B47-R47+(J47+U47)) -> 417 | P47: JUN | R47: =SUM(R48:R54) -> 100 | U47: =SUM(U48:U54) -> 100
A48: Steve | B48: 26451 | C48: =TEXT(B48,"MMDD") -> 0601 | E48: =DATEDIF(B48,NOW(),"y") -> 54 | F48: 0 | J48: =IF(N48="MISSED",F48,F48-I48) -> 0 | N48: =IF(TEXT(TODAY(),"YYYY")=RIGHT(A$2,4), IF(ISERROR(DATEDIF(TEXT(TODAY(),"dd/mm/yyyy"),TEXT(B48,"dd/mm/")&RIGHT(A$2,4),"d")),IF(H48="Y","DONE","MISSED"), IF(DATEDIF(TEXT(TODAY(),"dd/mm/yyyy"),TEXT(B48,"dd/mm/")&RIGHT(A$2,4),"d") = 0,"TODAY!!!", IF(DATEDIF(TEXT(TODAY(),"dd/mm/yyyy"),TEXT(B48,"dd/mm/")&RIGHT(A$2,4),"d") > 0, DATEDIF(TEXT(TODAY(),"dd/mm/yyyy"), TEXT(B48,"dd/mm/")&RIGHT(A$2,4),"d")&" Days to go!",""))),"") | P48: Fathers Day | Q48: 21st | R48: 50 | U48: =R48-T48 -> 50
A49: Kat | B49: 29376 | C49: =TEXT(B49,"MMDD") -> 0604 | E49: =DATEDIF(B49,NOW(),"y") -> 46 | F49: 0 | J49: =IF(N49="MISSED",F49,F49-I49) -> 0 | N49: =IF(TEXT(TODAY(),"YYYY")=RIGHT(A$2,4), IF(ISERROR(DATEDIF(TEXT(TODAY(),"dd/mm/yyyy"),TEXT(B49,"dd/mm/")&RIGHT(A$2,4),"d")),IF(H49="Y","DONE","MISSED"), IF(DATEDIF(TEXT(TODAY(),"dd/mm/yyyy"),TEXT(B49,"dd/mm/")&RIGHT(A$2,4),"d") = 0,"TODAY!!!", IF(DATEDIF(TEXT(TODAY(),"dd/mm/yyyy"),TEXT(B49,"dd/mm/")&RIGHT(A$2,4),"d") > 0, DATEDIF(TEXT(TODAY(),"dd/mm/yyyy"), TEXT(B49,"dd/mm/")&RIGHT(A$2,4),"d")&" Days to go!",""))),"") | P49: Citizenship | Q49: 28th | R49: 50 | S49: Aft tea | U49: =R49-T49 -> 50
A50: Cooper | B50: 42160 | E50: =DATEDIF(B50,NOW(),"y") -> 11 | F50: 20
A51: Leo | B51: 39607 | C51: =TEXT(B51,"MMDD") -> 0608 | E51: =DATEDIF(B51,NOW(),"y") -> 18 | F51: 20 | H51: Y | J51: =IF(N51="MISSED",F51,F51-I51) -> 20 | N51: =IF(TEXT(TODAY(),"YYYY")=RIGHT(A$2,4), IF(ISERROR(DATEDIF(TEXT(TODAY(),"dd/mm/yyyy"),TEXT(B51,"dd/mm/")&RIGHT(A$2,4),"d")),IF(H51="Y","DONE","MISSED"), IF(DATEDIF(TEXT(TODAY(),"dd/mm/yyyy"),TEXT(B51,"dd/mm/")&RIGHT(A$2,4),"d") = 0,"TODAY!!!", IF(DATEDIF(TEXT(TODAY(),"dd/mm/yyyy"),TEXT(B51,"dd/mm/")&RIGHT(A$2,4),"d") > 0, DATEDIF(TEXT(TODAY(),"dd/mm/yyyy"), TEXT(B51,"dd/mm/")&RIGHT(A$2,4),"d")&" Days to go!",""))),"")
A52: Jasmine | B52: 38876 | C52: =TEXT(B52,"MMDD") -> 0608 | E52: =DATEDIF(B52,NOW(),"y") -> 20 | F52: 20 | H52: Y | J52: =IF(N52="MISSED",F52,F52-I52) -> 20 | N52: =IF(TEXT(TODAY(),"YYYY")=RIGHT(A$2,4), IF(ISERROR(DATEDIF(TEXT(TODAY(),"dd/mm/yyyy"),TEXT(B52,"dd/mm/")&RIGHT(A$2,4),"d")),IF(H52="Y","DONE","MISSED"), IF(DATEDIF(TEXT(TODAY(),"dd/mm/yyyy"),TEXT(B52,"dd/mm/")&RIGHT(A$2,4),"d") = 0,"TODAY!!!", IF(DATEDIF(TEXT(TODAY(),"dd/mm/yyyy"),TEXT(B52,"dd/mm/")&RIGHT(A$2,4),"d") > 0, DATEDIF(TEXT(TODAY(),"dd/mm/yyyy"), TEXT(B52,"dd/mm/")&RIGHT(A$2,4),"d")&" Days to go!",""))),"")
A53: Charlotte (Niece) | B53: 35953 | C53: =TEXT(B53,"MMDD") -> 0607 | E53: =DATEDIF(B53,NOW(),"y") -> 28 | F53: 0 | J53: 0 | N53: =IF(TEXT(TODAY(),"YYYY")=RIGHT(A$2,4), IF(ISERROR(DATEDIF(TEXT(TODAY(),"dd/mm/yyyy"),TEXT(B53,"dd/mm/")&RIGHT(A$2,4),"d")),IF(H53="Y","DONE","MISSED"), IF(DATEDIF(TEXT(TODAY(),"dd/mm/yyyy"),TEXT(B53,"dd/mm/")&RIGHT(A$2,4),"d") = 0,"TODAY!!!", IF(DATEDIF(TEXT(TODAY(),"dd/mm/yyyy"),TEXT(B53,"dd/mm/")&RIGHT(A$2,4),"d") > 0, DATEDIF(TEXT(TODAY(),"dd/mm/yyyy"), TEXT(B53,"dd/mm/")&RIGHT(A$2,4),"d")&" Days to go!",""))),"")
A54: Emma | B54: 27928 | C54: =TEXT(B54,"MMDD") -> 0617 | E54: =DATEDIF(B54,NOW(),"y") -> 50 | F54: 0 | J54: =IF(N54="MISSED",F54,F54-I54) -> 0 | N54: =IF(TEXT(TODAY(),"YYYY")=RIGHT(A$2,4), IF(ISERROR(DATEDIF(TEXT(TODAY(),"dd/mm/yyyy"),TEXT(B54,"dd/mm/")&RIGHT(A$2,4),"d")),IF(H54="Y","DONE","MISSED"), IF(DATEDIF(TEXT(TODAY(),"dd/mm/yyyy"),TEXT(B54,"dd/mm/")&RIGHT(A$2,4),"d") = 0,"TODAY!!!", IF(DATEDIF(TEXT(TODAY(),"dd/mm/yyyy"),TEXT(B54,"dd/mm/")&RIGHT(A$2,4),"d") > 0, DATEDIF(TEXT(TODAY(),"dd/mm/yyyy"), TEXT(B54,"dd/mm/")&RIGHT(A$2,4),"d")&" Days to go!",""))),"")
A56: JUL | B56: =SUM(F57:F61) -> 70 | J56: =SUM(J57:J60) -> 20 | K56: =SUM(B56,R56) -> 120 | L56: =L47+($F$105/12)-B56-R56 -> 615 | M56: =IF(N56<>"",N56,(M47+($F$105/12))-B56-R56+(J56+U56)) -> 602 | P56: JUL | R56: =SUM(R57:R60) -> 50 | U56: =SUM(U57:U60) -> 50
A57: Alex (Ola) | B57: 33789 | C57: =TEXT(B57,"MMDD") -> 0704 | E57: =DATEDIF(B57,NOW(),"y") -> 34 | F57: 0 | H57: Y | J57: =IF(N57="MISSED",F57,F57-I57) -> 0 | N57: =IF(TEXT(TODAY(),"YYYY")=RIGHT(A$2,4), IF(ISERROR(DATEDIF(TEXT(TODAY(),"dd/mm/yyyy"),TEXT(B57,"dd/mm/")&RIGHT(A$2,4),"d")),IF(H57="Y","DONE","MISSED"), IF(DATEDIF(TEXT(TODAY(),"dd/mm/yyyy"),TEXT(B57,"dd/mm/")&RIGHT(A$2,4),"d") = 0,"TODAY!!!", IF(DATEDIF(TEXT(TODAY(),"dd/mm/yyyy"),TEXT(B57,"dd/mm/")&RIGHT(A$2,4),"d") > 0, DATEDIF(TEXT(TODAY(),"dd/mm/yyyy"), TEXT(B57,"dd/mm/")&RIGHT(A$2,4),"d")&" Days to go!",""))),"") | P57: Name day | Q57: 24th | R57: 50 | S57: Necklace | U57: =R57-T57 -> 50
A58: Hanna | B58: 44028 | E58: =DATEDIF(B58,NOW(),"y") -> 6 | F58: 20 | H58: Y | J58: =IF(N58="MISSED",F58,F58-I58) -> 20 | N58: =IF(TEXT(TODAY(),"YYYY")=RIGHT(A$2,4), IF(ISERROR(DATEDIF(TEXT(TODAY(),"dd/mm/yyyy"),TEXT(B58,"dd/mm/")&RIGHT(A$2,4),"d")),IF(H58="Y","DONE","MISSED"), IF(DATEDIF(TEXT(TODAY(),"dd/mm/yyyy"),TEXT(B58,"dd/mm/")&RIGHT(A$2,4),"d") = 0,"TODAY!!!", IF(DATEDIF(TEXT(TODAY(),"dd/mm/yyyy"),TEXT(B58,"dd/mm/")&RIGHT(A$2,4),"d") > 0, DATEDIF(TEXT(TODAY(),"dd/mm/yyyy"), TEXT(B58,"dd/mm/")&RIGHT(A$2,4),"d")&" Days to go!",""))),"")
A59: Louise | B59: 42562 | C59: =TEXT(B59,"MMDD") -> 0711 | E59: =DATEDIF(B59,NOW(),"y") -> 10 | F59: 0 | J59: =IF(N59="MISSED",F59,F59-I59) -> 0 | N59: =IF(TEXT(TODAY(),"YYYY")=RIGHT(A$2,4), IF(ISERROR(DATEDIF(TEXT(TODAY(),"dd/mm/yyyy"),TEXT(B59,"dd/mm/")&RIGHT(A$2,4),"d")),IF(H59="Y","DONE","MISSED"), IF(DATEDIF(TEXT(TODAY(),"dd/mm/yyyy"),TEXT(B59,"dd/mm/")&RIGHT(A$2,4),"d") = 0,"TODAY!!!", IF(DATEDIF(TEXT(TODAY(),"dd/mm/yyyy"),TEXT(B59,"dd/mm/")&RIGHT(A$2,4),"d") > 0, DATEDIF(TEXT(TODAY(),"dd/mm/yyyy"), TEXT(B59,"dd/mm/")&RIGHT(A$2,4),"d")&" Days to go!",""))),"")
A60: Keiran | B60: 39641 | C60: =TEXT(B60,"MMDD") -> 0712 | E60: =DATEDIF(B60,NOW(),"y") -> 18 | F60: 0 | J60: =IF(N60="MISSED",F60,F60-I60) -> 0 | N60: =IF(TEXT(TODAY(),"YYYY")=RIGHT(A$2,4), IF(ISERROR(DATEDIF(TEXT(TODAY(),"dd/mm/yyyy"),TEXT(B60,"dd/mm/")&RIGHT(A$2,4),"d")),IF(H60="Y","DONE","MISSED"), IF(DATEDIF(TEXT(TODAY(),"dd/mm/yyyy"),TEXT(B60,"dd/mm/")&RIGHT(A$2,4),"d") = 0,"TODAY!!!", IF(DATEDIF(TEXT(TODAY(),"dd/mm/yyyy"),TEXT(B60,"dd/mm/")&RIGHT(A$2,4),"d") > 0, DATEDIF(TEXT(TODAY(),"dd/mm/yyyy"), TEXT(B60,"dd/mm/")&RIGHT(A$2,4),"d")&" Days to go!",""))),"")
A61: Katie | B61: 34902 | E61: =DATEDIF(B61,NOW(),"y") -> 31 | F61: 50
A63: AUG | B63: =SUM(F64:F68) -> 20 | J63: =SUM(J65:J68) -> 20 | K63: =SUM(B63,R63) -> 20 | L63: =L56+($F$105/12)-B63-R63 -> 830 | M63: =IF(N63<>"",N63,(M56+($F$105/12))-B63-R63+(J63+U63)) -> 837 | P63: AUG | R63: =SUM(R65:R68) -> 0 | U63: =SUM(U65:U68) -> 0
A64: Glen | F64: 0 | J64: =IF(N64="MISSED",F64,F64-I64) -> 0
A65: Charlotte | B65: 31995 | C65: =TEXT(B65,"MMDD") -> 0806 | E65: =DATEDIF(B65,NOW(),"y") -> 39 | F65: 0 | J65: =IF(N65="MISSED",F65,F65-I65) -> 0 | N65: =IF(TEXT(TODAY(),"YYYY")=RIGHT(A$2,4), IF(ISERROR(DATEDIF(TEXT(TODAY(),"dd/mm/yyyy"),TEXT(B65,"dd/mm/")&RIGHT(A$2,4),"d")),IF(H65="Y","DONE","MISSED"), IF(DATEDIF(TEXT(TODAY(),"dd/mm/yyyy"),TEXT(B65,"dd/mm/")&RIGHT(A$2,4),"d") = 0,"TODAY!!!", IF(DATEDIF(TEXT(TODAY(),"dd/mm/yyyy"),TEXT(B65,"dd/mm/")&RIGHT(A$2,4),"d") > 0, DATEDIF(TEXT(TODAY(),"dd/mm/yyyy"), TEXT(B65,"dd/mm/")&RIGHT(A$2,4),"d")&" Days to go!",""))),"")
A66: Jack | B66: 44788 | E66: =DATEDIF(B66,NOW(),"y") -> 4 | F66: 20 | J66: =IF(N66="MISSED",F66,F66-I66) -> 20
A67: Cheryl | B67: 31651 | E67: =DATEDIF(B67,NOW(),"y") -> 39 | F67: 0 | J67: =IF(N67="MISSED",F67,F67-I67) -> 0
A68: Dylan | B68: 36766 | C68: =TEXT(B68,"MMDD") -> 0828 | E68: =DATEDIF(B68,NOW(),"y") -> 25 | F68: 0 | J68: =IF(N68="MISSED",F68,F68-I68) -> 0 | N68: =IF(TEXT(TODAY(),"YYYY")=RIGHT(A$2,4), IF(ISERROR(DATEDIF(TEXT(TODAY(),"dd/mm/yyyy"),TEXT(B68,"dd/mm/")&RIGHT(A$2,4),"d")),IF(H68="Y","DONE","MISSED"), IF(DATEDIF(TEXT(TODAY(),"dd/mm/yyyy"),TEXT(B68,"dd/mm/")&RIGHT(A$2,4),"d") = 0,"TODAY!!!", IF(DATEDIF(TEXT(TODAY(),"dd/mm/yyyy"),TEXT(B68,"dd/mm/")&RIGHT(A$2,4),"d") > 0, DATEDIF(TEXT(TODAY(),"dd/mm/yyyy"), TEXT(B68,"dd/mm/")&RIGHT(A$2,4),"d")&" Days to go!",""))),"")
A70: SEP | B70: =SUM(F71:F77) -> 220 | J70: =SUM(J71:J77) -> 200 | K70: =SUM(B70,R70) -> 220 | L70: =L63+($F$105/12)-B70-R70-300 -> 545 | M70: =IF(N70<>"",N70,(M63+($F$105/12))-B70-R70+(J70+U70)) -> 1052 | P70: SEP | R70: =SUM(R71:R77) -> 0 | U70: =SUM(U71:U77) -> 0
A71: Beverley | B71: 42620 | C71: =TEXT(B71,"MMDD") -> 0907 | E71: =DATEDIF(B71,NOW(),"y") -> 9 | F71: 0 | J71: =IF(N71="MISSED",F71,F71-I71) -> 0 | N71: =IF(TEXT(TODAY(),"YYYY")=RIGHT(A$2,4), IF(ISERROR(DATEDIF(TEXT(TODAY(),"dd/mm/yyyy"),TEXT(B71,"dd/mm/")&RIGHT(A$2,4),"d")),IF(H71="Y","DONE","MISSED"), IF(DATEDIF(TEXT(TODAY(),"dd/mm/yyyy"),TEXT(B71,"dd/mm/")&RIGHT(A$2,4),"d") = 0,"TODAY!!!", IF(DATEDIF(TEXT(TODAY(),"dd/mm/yyyy"),TEXT(B71,"dd/mm/")&RIGHT(A$2,4),"d") > 0, DATEDIF(TEXT(TODAY(),"dd/mm/yyyy"), TEXT(B71,"dd/mm/")&RIGHT(A$2,4),"d")&" Days to go!",""))),"")
A72: Amelia | B72: 45176 | E72: =DATEDIF(B72,NOW(),"y") -> 2 | F72: 20
A73: Ben | B73: 38606 | C73: =TEXT(B73,"MMDD") -> 0911 | E73: =DATEDIF(B73,NOW(),"y") -> 20 | F73: 0 | H73: Y | I73: 0 | J73: =IF(N73="MISSED",F73,F73-I73) -> 0 | N73: =IF(TEXT(TODAY(),"YYYY")=RIGHT(A$2,4), IF(ISERROR(DATEDIF(TEXT(TODAY(),"dd/mm/yyyy"),TEXT(B73,"dd/mm/")&RIGHT(A$2,4),"d")),IF(H73="Y","DONE","MISSED"), IF(DATEDIF(TEXT(TODAY(),"dd/mm/yyyy"),TEXT(B73,"dd/mm/")&RIGHT(A$2,4),"d") = 0,"TODAY!!!", IF(DATEDIF(TEXT(TODAY(),"dd/mm/yyyy"),TEXT(B73,"dd/mm/")&RIGHT(A$2,4),"d") > 0, DATEDIF(TEXT(TODAY(),"dd/mm/yyyy"), TEXT(B73,"dd/mm/")&RIGHT(A$2,4),"d")&" Days to go!",""))),"")
A74: Rebecca | B74: 37511 | C74: =TEXT(B74,"MMDD") -> 0912 | E74: =DATEDIF(B74,NOW(),"y") -> 23 | F74: 0 | J74: =IF(N74="MISSED",F74,F74-I74) -> 0 | N74: =IF(TEXT(TODAY(),"YYYY")=RIGHT(A$2,4), IF(ISERROR(DATEDIF(TEXT(TODAY(),"dd/mm/yyyy"),TEXT(B74,"dd/mm/")&RIGHT(A$2,4),"d")),IF(H74="Y","DONE","MISSED"), IF(DATEDIF(TEXT(TODAY(),"dd/mm/yyyy"),TEXT(B74,"dd/mm/")&RIGHT(A$2,4),"d") = 0,"TODAY!!!", IF(DATEDIF(TEXT(TODAY(),"dd/mm/yyyy"),TEXT(B74,"dd/mm/")&RIGHT(A$2,4),"d") > 0, DATEDIF(TEXT(TODAY(),"dd/mm/yyyy"), TEXT(B74,"dd/mm/")&RIGHT(A$2,4),"d")&" Days to go!",""))),"")
A75: Mum | B75: 21076 | C75: =TEXT(B75,"MMDD") -> 0913 | E75: =DATEDIF(B75,NOW(),"y") -> 68 | F75: 50 | J75: =IF(N75="MISSED",F75,F75-I75) -> 50 | N75: =IF(TEXT(TODAY(),"YYYY")=RIGHT(A$2,4), IF(ISERROR(DATEDIF(TEXT(TODAY(),"dd/mm/yyyy"),TEXT(B75,"dd/mm/")&RIGHT(A$2,4),"d")),IF(H75="Y","DONE","MISSED"), IF(DATEDIF(TEXT(TODAY(),"dd/mm/yyyy"),TEXT(B75,"dd/mm/")&RIGHT(A$2,4),"d") = 0,"TODAY!!!", IF(DATEDIF(TEXT(TODAY(),"dd/mm/yyyy"),TEXT(B75,"dd/mm/")&RIGHT(A$2,4),"d") > 0, DATEDIF(TEXT(TODAY(),"dd/mm/yyyy"), TEXT(B75,"dd/mm/")&RIGHT(A$2,4),"d")&" Days to go!",""))),"")
A76: Me | B76: 34230 | E76: =DATEDIF(B76,NOW(),"y") -> 32 | F76: 150 | J76: =IF(N76="MISSED",F76,F76-I76) -> 150 | N76: =IF(TEXT(TODAY(),"YYYY")=RIGHT(A$2,4), IF(ISERROR(DATEDIF(TEXT(TODAY(),"dd/mm/yyyy"),TEXT(B76,"dd/mm/")&RIGHT(A$2,4),"d")),IF(H76="Y","DONE","MISSED"), IF(DATEDIF(TEXT(TODAY(),"dd/mm/yyyy"),TEXT(B76,"dd/mm/")&RIGHT(A$2,4),"d") = 0,"TODAY!!!", IF(DATEDIF(TEXT(TODAY(),"dd/mm/yyyy"),TEXT(B76,"dd/mm/")&RIGHT(A$2,4),"d") > 0, DATEDIF(TEXT(TODAY(),"dd/mm/yyyy"), TEXT(B76,"dd/mm/")&RIGHT(A$2,4),"d")&" Days to go!",""))),"")
A77: Auntie Linda (RIP) | B77: 19262 | C77: =TEXT(B77,"MMDD") -> 0925 | E77: =DATEDIF(B77,NOW(),"y") -> 73 | F77: 0 | J77: =IF(N77="MISSED",F77,F77-I77) -> 0 | N77: =IF(TEXT(TODAY(),"YYYY")=RIGHT(A$2,4), IF(ISERROR(DATEDIF(TEXT(TODAY(),"dd/mm/yyyy"),TEXT(B77,"dd/mm/")&RIGHT(A$2,4),"d")),IF(H77="Y","DONE","MISSED"), IF(DATEDIF(TEXT(TODAY(),"dd/mm/yyyy"),TEXT(B77,"dd/mm/")&RIGHT(A$2,4),"d") = 0,"TODAY!!!", IF(DATEDIF(TEXT(TODAY(),"dd/mm/yyyy"),TEXT(B77,"dd/mm/")&RIGHT(A$2,4),"d") > 0, DATEDIF(TEXT(TODAY(),"dd/mm/yyyy"), TEXT(B77,"dd/mm/")&RIGHT(A$2,4),"d")&" Days to go!",""))),"")
A79: OCT | B79: =SUM(F80:F86) -> 50 | J79: =SUM(J80:J86) -> 50 | K79: =SUM(B79,R79) -> 150 | L79: =L70+($F$105/12)-B79-R79 -> 630 | M79: =IF(N79<>"",N79,(M70+($F$105/12))-B79-R79+(J79+U79)) -> 1287 | P79: OCT | R79: =SUM(R80:R86) -> 100 | U79: =SUM(U80:U86) -> 100
A80: Thomas | B80: 35342 | C80: =TEXT(B80,"MMDD") -> 1004 | E80: =DATEDIF(B80,NOW(),"y") -> 29 | F80: 0 | J80: =IF(N80="MISSED",F80,F80-I80) -> 0 | N80: =IF(TEXT(TODAY(),"YYYY")=RIGHT(A$2,4), IF(ISERROR(DATEDIF(TEXT(TODAY(),"dd/mm/yyyy"),TEXT(B80,"dd/mm/")&RIGHT(A$2,4),"d")),IF(H80="Y","DONE","MISSED"), IF(DATEDIF(TEXT(TODAY(),"dd/mm/yyyy"),TEXT(B80,"dd/mm/")&RIGHT(A$2,4),"d") = 0,"TODAY!!!", IF(DATEDIF(TEXT(TODAY(),"dd/mm/yyyy"),TEXT(B80,"dd/mm/")&RIGHT(A$2,4),"d") > 0, DATEDIF(TEXT(TODAY(),"dd/mm/yyyy"), TEXT(B80,"dd/mm/")&RIGHT(A$2,4),"d")&" Days to go!",""))),"") | P80: Anniversary | Q80: 13th | R80: 100 | U80: =R80-T80 -> 100
A81: Michelle | B81: 42654 | C81: =TEXT(B81,"MMDD") -> 1011 | E81: =DATEDIF(B81,NOW(),"y") -> 9 | F81: 0 | J81: =IF(N81="MISSED",F81,F81-I81) -> 0 | N81: =IF(TEXT(TODAY(),"YYYY")=RIGHT(A$2,4), IF(ISERROR(DATEDIF(TEXT(TODAY(),"dd/mm/yyyy"),TEXT(B81,"dd/mm/")&RIGHT(A$2,4),"d")),IF(H81="Y","DONE","MISSED"), IF(DATEDIF(TEXT(TODAY(),"dd/mm/yyyy"),TEXT(B81,"dd/mm/")&RIGHT(A$2,4),"d") = 0,"TODAY!!!", IF(DATEDIF(TEXT(TODAY(),"dd/mm/yyyy"),TEXT(B81,"dd/mm/")&RIGHT(A$2,4),"d") > 0, DATEDIF(TEXT(TODAY(),"dd/mm/yyyy"), TEXT(B81,"dd/mm/")&RIGHT(A$2,4),"d")&" Days to go!",""))),"")
A82: Lena | B82: 42655 | C82: =TEXT(B82,"MMDD") -> 1012 | E82: =DATEDIF(B82,NOW(),"y") -> 9 | F82: 25 | J82: =IF(N82="MISSED",F82,F82-I82) -> 25 | N82: =IF(TEXT(TODAY(),"YYYY")=RIGHT(A$2,4), IF(ISERROR(DATEDIF(TEXT(TODAY(),"dd/mm/yyyy"),TEXT(B82,"dd/mm/")&RIGHT(A$2,4),"d")),IF(H82="Y","DONE","MISSED"), IF(DATEDIF(TEXT(TODAY(),"dd/mm/yyyy"),TEXT(B82,"dd/mm/")&RIGHT(A$2,4),"d") = 0,"TODAY!!!", IF(DATEDIF(TEXT(TODAY(),"dd/mm/yyyy"),TEXT(B82,"dd/mm/")&RIGHT(A$2,4),"d") > 0, DATEDIF(TEXT(TODAY(),"dd/mm/yyyy"), TEXT(B82,"dd/mm/")&RIGHT(A$2,4),"d")&" Days to go!",""))),"")
A83: Oscar | B83: 43025 | E83: =DATEDIF(B83,NOW(),"y") -> 8 | F83: 25 | J83: =IF(N83="MISSED",F83,F83-I83) -> 25 | N83: =IF(TEXT(TODAY(),"YYYY")=RIGHT(A$2,4), IF(ISERROR(DATEDIF(TEXT(TODAY(),"dd/mm/yyyy"),TEXT(B83,"dd/mm/")&RIGHT(A$2,4),"d")),IF(H83="Y","DONE","MISSED"), IF(DATEDIF(TEXT(TODAY(),"dd/mm/yyyy"),TEXT(B83,"dd/mm/")&RIGHT(A$2,4),"d") = 0,"TODAY!!!", IF(DATEDIF(TEXT(TODAY(),"dd/mm/yyyy"),TEXT(B83,"dd/mm/")&RIGHT(A$2,4),"d") > 0, DATEDIF(TEXT(TODAY(),"dd/mm/yyyy"), TEXT(B83,"dd/mm/")&RIGHT(A$2,4),"d")&" Days to go!",""))),"")
A84: Auntie Helen | B84: 22573 | C84: =TEXT(B84,"MMDD") -> 1019 | E84: =DATEDIF(B84,NOW(),"y") -> 64 | F84: 0 | J84: =IF(N84="MISSED",F84,F84-I84) -> 0 | N84: =IF(TEXT(TODAY(),"YYYY")=RIGHT(A$2,4), IF(ISERROR(DATEDIF(TEXT(TODAY(),"dd/mm/yyyy"),TEXT(B84,"dd/mm/")&RIGHT(A$2,4),"d")),IF(H84="Y","DONE","MISSED"), IF(DATEDIF(TEXT(TODAY(),"dd/mm/yyyy"),TEXT(B84,"dd/mm/")&RIGHT(A$2,4),"d") = 0,"TODAY!!!", IF(DATEDIF(TEXT(TODAY(),"dd/mm/yyyy"),TEXT(B84,"dd/mm/")&RIGHT(A$2,4),"d") > 0, DATEDIF(TEXT(TODAY(),"dd/mm/yyyy"), TEXT(B84,"dd/mm/")&RIGHT(A$2,4),"d")&" Days to go!",""))),"")
A85: Grandma (RIP) | B85: 11252 | C85: =TEXT(B85,"MMDD") -> 1021 | D85: 44386 | E85: =DATEDIF(B85,NOW(),"y") -> 95 | F85: 0 | J85: =IF(N85="MISSED",F85,F85-I85) -> 0 | N85: =IF(TEXT(TODAY(),"YYYY")=RIGHT(A$2,4), IF(ISERROR(DATEDIF(TEXT(TODAY(),"dd/mm/yyyy"),TEXT(B85,"dd/mm/")&RIGHT(A$2,4),"d")),IF(H85="Y","DONE","MISSED"), IF(DATEDIF(TEXT(TODAY(),"dd/mm/yyyy"),TEXT(B85,"dd/mm/")&RIGHT(A$2,4),"d") = 0,"TODAY!!!", IF(DATEDIF(TEXT(TODAY(),"dd/mm/yyyy"),TEXT(B85,"dd/mm/")&RIGHT(A$2,4),"d") > 0, DATEDIF(TEXT(TODAY(),"dd/mm/yyyy"), TEXT(B85,"dd/mm/")&RIGHT(A$2,4),"d")&" Days to go!",""))),"")
A86: Daniel | B86: 33172 | C86: =TEXT(B86,"MMDD") -> 1026 | E86: =DATEDIF(B86,NOW(),"y") -> 35 | F86: 0 | J86: =IF(N86="MISSED",F86,F86-I86) -> 0 | N86: =IF(TEXT(TODAY(),"YYYY")=RIGHT(A$2,4), IF(ISERROR(DATEDIF(TEXT(TODAY(),"dd/mm/yyyy"),TEXT(B86,"dd/mm/")&RIGHT(A$2,4),"d")),IF(H86="Y","DONE","MISSED"), IF(DATEDIF(TEXT(TODAY(),"dd/mm/yyyy"),TEXT(B86,"dd/mm/")&RIGHT(A$2,4),"d") = 0,"TODAY!!!", IF(DATEDIF(TEXT(TODAY(),"dd/mm/yyyy"),TEXT(B86,"dd/mm/")&RIGHT(A$2,4),"d") > 0, DATEDIF(TEXT(TODAY(),"dd/mm/yyyy"), TEXT(B86,"dd/mm/")&RIGHT(A$2,4),"d")&" Days to go!",""))),"")
A88: NOV | B88: =SUM(F89:F90) -> 25 | J88: =SUM(J89:J90) -> 25 | K88: =SUM(B88,R88) -> 25 | L88: =L79+($F$105/12)-B88-R88 -> 840 | M88: =IF(N88<>"",N88,(M79+($F$105/12))-B88-R88+(J88+U88)) -> 1522 | P88: NOV | R88: =SUM(R89:R90) -> 0 | U88: =SUM(U89:U90) -> 0
A89: Philippa | B89: 34280 | C89: =TEXT(B89,"MMDD") -> 1107 | E89: =DATEDIF(B89,NOW(),"y") -> 32 | F89: 25 | J89: =IF(N89="MISSED",F89,F89-I89) -> 25 | N89: =IF(TEXT(TODAY(),"YYYY")=RIGHT(A$2,4), IF(ISERROR(DATEDIF(TEXT(TODAY(),"dd/mm/yyyy"),TEXT(B89,"dd/mm/")&RIGHT(A$2,4),"d")),IF(H89="Y","DONE","MISSED"), IF(DATEDIF(TEXT(TODAY(),"dd/mm/yyyy"),TEXT(B89,"dd/mm/")&RIGHT(A$2,4),"d") = 0,"TODAY!!!", IF(DATEDIF(TEXT(TODAY(),"dd/mm/yyyy"),TEXT(B89,"dd/mm/")&RIGHT(A$2,4),"d") > 0, DATEDIF(TEXT(TODAY(),"dd/mm/yyyy"), TEXT(B89,"dd/mm/")&RIGHT(A$2,4),"d")&" Days to go!",""))),"") | P89: Bonfire | Q89: 5th | R89: 0 | S89: Fireworks | U89: =R89-T89 -> 0
A90: Harry | B90: 40139 | C90: =TEXT(B90,"MMDD") -> 1122 | E90: =DATEDIF(B90,NOW(),"y") -> 16 | F90: 0 | J90: =IF(N90="MISSED",F90,F90-I90) -> 0 | N90: =IF(TEXT(TODAY(),"YYYY")=RIGHT(A$2,4), IF(ISERROR(DATEDIF(TEXT(TODAY(),"dd/mm/yyyy"),TEXT(B90,"dd/mm/")&RIGHT(A$2,4),"d")),IF(H90="Y","DONE","MISSED"), IF(DATEDIF(TEXT(TODAY(),"dd/mm/yyyy"),TEXT(B90,"dd/mm/")&RIGHT(A$2,4),"d") = 0,"TODAY!!!", IF(DATEDIF(TEXT(TODAY(),"dd/mm/yyyy"),TEXT(B90,"dd/mm/")&RIGHT(A$2,4),"d") > 0, DATEDIF(TEXT(TODAY(),"dd/mm/yyyy"), TEXT(B90,"dd/mm/")&RIGHT(A$2,4),"d")&" Days to go!",""))),"")
A92: DEC | B92: =SUM(F93:F98) -> 190 | J92: =SUM(J93:J98) -> -30 | K92: =SUM(B92,R92) -> 190 | L92: =L88+($F$105/12)-B92-F103-R92 -> -300 | M92: =IF(N92<>"",N92,((M88+($F$105/12))-(B92-J92)-(R92-U92))-J99) -> 1537 | P92: DEC | R92: =SUM(R93:R98) -> 0 | U92: =SUM(U93:U98) -> 0
A93: Robert | B93: 34317 | C93: =TEXT(B93,"MMDD") -> 1214 | E93: =DATEDIF(B93,NOW(),"y") -> 32 | F93: 25 | G93: John bishop? | H93: Y | J93: =IF(N93="MISSED",F93,F93-I93) -> 25 | N93: =IF(TEXT(TODAY(),"YYYY")=RIGHT(A$2,4), IF(ISERROR(DATEDIF(TEXT(TODAY(),"dd/mm/yyyy"),TEXT(B93,"dd/mm/")&RIGHT(A$2,4),"d")),IF(H93="Y","DONE","MISSED"), IF(DATEDIF(TEXT(TODAY(),"dd/mm/yyyy"),TEXT(B93,"dd/mm/")&RIGHT(A$2,4),"d") = 0,"TODAY!!!", IF(DATEDIF(TEXT(TODAY(),"dd/mm/yyyy"),TEXT(B93,"dd/mm/")&RIGHT(A$2,4),"d") > 0, DATEDIF(TEXT(TODAY(),"dd/mm/yyyy"), TEXT(B93,"dd/mm/")&RIGHT(A$2,4),"d")&" Days to go!",""))),"") | P93: Markets | Q93: ? | R93: 0 | S93: Markets | U93: =R93-T93 -> 0
A94: JJ | B94: 33221 | C94: =TEXT(B94,"MMDD") -> 1214 | E94: =DATEDIF(B94,NOW(),"y") -> 35 | F94: 0 | J94: =IF(N94="MISSED",F94,F94-I94) -> 0 | N94: =IF(TEXT(TODAY(),"YYYY")=RIGHT(A$2,4), IF(ISERROR(DATEDIF(TEXT(TODAY(),"dd/mm/yyyy"),TEXT(B94,"dd/mm/")&RIGHT(A$2,4),"d")),IF(H94="Y","DONE","MISSED"), IF(DATEDIF(TEXT(TODAY(),"dd/mm/yyyy"),TEXT(B94,"dd/mm/")&RIGHT(A$2,4),"d") = 0,"TODAY!!!", IF(DATEDIF(TEXT(TODAY(),"dd/mm/yyyy"),TEXT(B94,"dd/mm/")&RIGHT(A$2,4),"d") > 0, DATEDIF(TEXT(TODAY(),"dd/mm/yyyy"), TEXT(B94,"dd/mm/")&RIGHT(A$2,4),"d")&" Days to go!",""))),"") | P94: Dini day | R94: 0
A95: Andrew | B95: 42720 | C95: =TEXT(B95,"MMDD") -> 1216 | E95: =DATEDIF(B95,NOW(),"y") -> 9 | F95: 0 | J95: =IF(N95="MISSED",F95,F95-I95) -> 0 | N95: =IF(TEXT(TODAY(),"YYYY")=RIGHT(A$2,4), IF(ISERROR(DATEDIF(TEXT(TODAY(),"dd/mm/yyyy"),TEXT(B95,"dd/mm/")&RIGHT(A$2,4),"d")),IF(H95="Y","DONE","MISSED"), IF(DATEDIF(TEXT(TODAY(),"dd/mm/yyyy"),TEXT(B95,"dd/mm/")&RIGHT(A$2,4),"d") = 0,"TODAY!!!", IF(DATEDIF(TEXT(TODAY(),"dd/mm/yyyy"),TEXT(B95,"dd/mm/")&RIGHT(A$2,4),"d") > 0, DATEDIF(TEXT(TODAY(),"dd/mm/yyyy"), TEXT(B95,"dd/mm/")&RIGHT(A$2,4),"d")&" Days to go!",""))),"")
A96: Kristine | B96: 34327 | C96: =TEXT(B96,"MMDD") -> 1224 | E96: =DATEDIF(B96,NOW(),"y") -> 32 | F96: 150 | G96: Lulus | I96: 220 | J96: =IF(N96="MISSED",F96,F96-I96) -> -70 | N96: =IF(TEXT(TODAY(),"YYYY")=RIGHT(A$2,4), IF(ISERROR(DATEDIF(TEXT(TODAY(),"dd/mm/yyyy"),TEXT(B96,"dd/mm/")&RIGHT(A$2,4),"d")),IF(H96="Y","DONE","MISSED"), IF(DATEDIF(TEXT(TODAY(),"dd/mm/yyyy"),TEXT(B96,"dd/mm/")&RIGHT(A$2,4),"d") = 0,"TODAY!!!", IF(DATEDIF(TEXT(TODAY(),"dd/mm/yyyy"),TEXT(B96,"dd/mm/")&RIGHT(A$2,4),"d") > 0, DATEDIF(TEXT(TODAY(),"dd/mm/yyyy"), TEXT(B96,"dd/mm/")&RIGHT(A$2,4),"d")&" Days to go!",""))),"")
A97: Mark | B97: 32138 | C97: =TEXT(B97,"MMDD") -> 1227 | E97: =DATEDIF(B97,NOW(),"y") -> 38 | F97: 0 | J97: =IF(N97="MISSED",F97,F97-I97) -> 0 | N97: =IF(TEXT(TODAY(),"YYYY")=RIGHT(A$2,4), IF(ISERROR(DATEDIF(TEXT(TODAY(),"dd/mm/yyyy"),TEXT(B97,"dd/mm/")&RIGHT(A$2,4),"d")),IF(H97="Y","DONE","MISSED"), IF(DATEDIF(TEXT(TODAY(),"dd/mm/yyyy"),TEXT(B97,"dd/mm/")&RIGHT(A$2,4),"d") = 0,"TODAY!!!", IF(DATEDIF(TEXT(TODAY(),"dd/mm/yyyy"),TEXT(B97,"dd/mm/")&RIGHT(A$2,4),"d") > 0, DATEDIF(TEXT(TODAY(),"dd/mm/yyyy"), TEXT(B97,"dd/mm/")&RIGHT(A$2,4),"d")&" Days to go!",""))),"")
A98: Auntie Julie | B98: 23740 | C98: =TEXT(B98,"MMDD") -> 1229 | E98: =DATEDIF(B98,NOW(),"y") -> 61 | F98: 15 | G98: Tea towel | H98: Y | J98: =IF(N98="MISSED",F98,F98-I98) -> 15 | N98: =IF(TEXT(TODAY(),"YYYY")=RIGHT(A$2,4), IF(ISERROR(DATEDIF(TEXT(TODAY(),"dd/mm/yyyy"),TEXT(B98,"dd/mm/")&RIGHT(A$2,4),"d")),IF(H98="Y","DONE","MISSED"), IF(DATEDIF(TEXT(TODAY(),"dd/mm/yyyy"),TEXT(B98,"dd/mm/")&RIGHT(A$2,4),"d") = 0,"TODAY!!!", IF(DATEDIF(TEXT(TODAY(),"dd/mm/yyyy"),TEXT(B98,"dd/mm/")&RIGHT(A$2,4),"d") > 0, DATEDIF(TEXT(TODAY(),"dd/mm/yyyy"), TEXT(B98,"dd/mm/")&RIGHT(A$2,4),"d")&" Days to go!",""))),"")
A99: Christmas total | J99: 0
A101: ="Total birthday gifts: "&COUNTIF(F4:F98,"<>0") -> Total birthday gifts: 46 | F101: =SUMIF(F4:F98,">0") -> 875 | I101: =SUM(I4:I98) -> 270.99 | J101: =SUM(J92,J88,J79,J70,J63,J56,J47,J37,J32,J21,J14,J3) -> 424.01 | K101: =SUM(K3:K95)-R101 -> 875 | R101: =SUM(R3,R14,R21,R32,R37,R47,R56,R63,R70,R79,R88,R92) -> 760 | U101: =SUM(U3,U14,U21,U32,U37,U47,U56,U63,U70,U79,U88,U92) -> 660
A102: ="Total birthday cards: "&COUNTA(A4:A98) -> Total birthday cards: 84
A103: Christmas | F103: =G186 -> 1185 | M103: =J92+R92+F104 -> 730
A104: Other | F104: =R101 -> 760
A105: Total | F105: =SUM(F101:F104) -> 2820 | M105: =R92+F103+B92 -> 1375 | N105: =M105-450 -> 925
A106: Monthly | F106: =F105/12 -> 235 | G106: =250*12 -> 3000
A108: Christmas Ideas
A109: Person(s) | B109: Card | E109: Idea | G109: Budget | H109: Spent | I109: Remaining
A110: Mum + Dad | B110: Y | E110: Theatre + meal | G110: 100 | H110: 70 | I110: =G110-H110 -> 30
A111: Inesa + Glen | G111: 100 | I111: =G111-H111 -> 100
I112: =G112-H112 -> 0
...

Sheet 5 week template
A1: MONTH | B1: Monthly Allowance | C1: ="22/02/17" & " - " & "28/02/17" -> 22/02/17 - 28/02/17 | D1: =TEXT(DATEVALUE(RIGHT(C1,8))+1,"dd/mm/yy")& " - "& TEXT(DATEVALUE(RIGHT(C1,8))+7,"dd/mm/yy") -> 01/03/17 - 07/03/17 | E1: =TEXT(DATEVALUE(RIGHT(D1,8))+1,"dd/mm/yy")& " - "& TEXT(DATEVALUE(RIGHT(D1,8))+7,"dd/mm/yy") -> 08/03/17 - 14/03/17 | F1: =TEXT(DATEVALUE(RIGHT(E1,8))+1,"dd/mm/yy")& " - "& TEXT(DATEVALUE(RIGHT(E1,8))+7,"dd/mm/yy") -> 15/03/17 - 21/03/17 | G1: =TEXT(DATEVALUE(RIGHT(F1,8))+1,"dd/mm/yy")& " - "& TEXT(DATEVALUE(RIGHT(F1,8))+7,"dd/mm/yy") -> 22/03/17 - 28/03/17 | H1: Remaining
A2: Outgoings | C2: =SUM(C5:C20) -> 0 | D2: =SUM(D5:D20) -> 0 | E2: =SUM(E5:E20) -> 0 | F2: =SUM(F5:F20) -> 0 | G2: =SUM(G5:G20) -> 0
A4: General | B4: =SUM(B5:B9) -> 460 | H4: ="Remaining: £" & SUM(H5:H9) -> Remaining: £460
A5: Car Petrol | B5: =IF(G1="Remaining",17.5*4,17.5*5) -> 87.5 | H5: =IF(B5<>"",B5-C5-D5-E5-F5-G5,"") -> 87.5 | I5: =A5 -> Car Petrol
A6: Bike petrol | B6: =IF(G1="Remaining",4.5*4,4.5*5) -> 22.5 | H6: =IF(B6<>"",B6-C6-D6-E6-F6-G6,"") -> 22.5 | I6: =A6 -> Bike petrol
A7: Food | B7: =IF(G1="Remaining",30*4,IF(H1= "Remaining",30* 5,"")) -> 150 | H7: =IF(B7<>"",B7-C7-D7-E7-F7-G7,"") -> 150 | I7: =A7 -> Food
A8: Gift Fund | B8: 100 | H8: =IF(B8<>"",B8-C8-D8-E8-F8-G8,"") -> 100 | I8: =A8 -> Gift Fund
A9: Holiday Fund | B9: =IF(G1="Remaining",20*4,IF(H1= "Remaining",20* 5,"")) -> 100 | H9: =IF(B9<>"",B9-C9-D9-E9-F9-G9,"") -> 100 | I9: =A9 -> Holiday Fund
A10: Misc | B10: =IF(B26 <> 0,B26-SUM(B5:B9)-B12-B24,0) -> -16.26 | H10: =IF(B10<>"",B10-C10-D10-E10-F10-G10,"") -> -16.26 | I10: Misc
A12: Direct Debits | B12: =SUM(B13:B21) -> 859.87 | H12: ="Remaining: £" & SUM(H13:H21) -> Remaining: £859.87
A13: House | B13: 500 | H13: =IF(B13<>"",B13-C13-D13-E13-F13-G13,"") -> 500 | I13: =A13 -> House
A14: Ring | B14: 104.92 | H14: =IF(B14<>"",B14-C14-D14-E14-F14-G14,"") -> 104.92 | I14: =A14 -> Ring
A15: Phone | B15: ='Joint Outgoings'!C29 -> 16.99 | H15: =IF(B15<>"",B15-C15-D15-E15-F15-G15,"") -> 16.99 | I15: =A15 -> Phone
A16: Gym | B16: 17.99 | H16: =IF(B16<>"",B16-C16-D16-E16-F16-G16,"") -> 17.99 | I16: =A16 -> Gym
A17: Car v.tax | B17: ='Joint Outgoings'!C25 -> 200 | H17: =IF(B17<>"",B17-C17-D17-E17-F17-G17,"") -> 200 | I17: =A17 -> Car v.tax
A18: Sky Movies | B18: 3.99 | H18: =IF(B18<>"",B18-C18-D18-E18-F18-G18,"") -> 3.99 | I18: =A18 -> Sky Movies
A19: Spotify | B19: 0 | H19: =IF(B19<>"",B19-C19-D19-E19-F19-G19,"") -> 0 | I19: =A19 -> Spotify
A20: Onedrive | B20: 7.99 | H20: =IF(B20<>"",B20-C20-D20-E20-F20-G20,"") -> 7.99 | I20: =A20 -> Onedrive
A21: Amazon Prime | B21: 7.99 | H21: =IF(B21<>"",B21-C21-D21-E21-F21-G21,"") -> 7.99 | I21: =A21 -> Amazon Prime
A23: Savings
A24: Savings In | B24: =IF(SUM(C24:G24)<>0,SUM(C24:G24),0) -> 0
A25: Savings Out | B25: =IF(SUM(C25:G25)<>0,SUM(C25:G25),0) -> 0
A26: Income | B26: =SUM(C26:G26) -> 1303.61 | C26: 1303.61 | H26: =SUM(H5:H25) & " / " & B26 -> 1303.61 / 1303.61
A27: Reminders: | B27: =IF(MONTH(TODAY()) = 11, IF(MONTH(A1(RIGHT,3)) = 11, "Bike insurance due",""),"")
B28: =IF(MONTH(TODAY()) = 6, IF(MONTH(A1(RIGHT,3)) = 6, "Bike insurance due",""),"") | H28: =SUM(H5:H25)*12 -> 15643.32
A31: Pay after del:

Sheet 4 week template
A1: MONTH | B1: Monthly Allowance | C1: ="29/06/16" & " - " & "05/7/16" -> 29/06/16 - 05/7/16 | D1: =TEXT(DATEVALUE(RIGHT(C1,8))+1,"dd/mm/yy")& " - "& TEXT(DATEVALUE(RIGHT(C1,8))+7,"dd/mm/yy") -> 06/07/16 - 12/07/16 | E1: =TEXT(DATEVALUE(RIGHT(D1,8))+1,"dd/mm/yy")& " - "& TEXT(DATEVALUE(RIGHT(D1,8))+7,"dd/mm/yy") -> 13/07/16 - 19/07/16 | F1: =TEXT(DATEVALUE(RIGHT(E1,8))+1,"dd/mm/yy")& " - "& TEXT(DATEVALUE(RIGHT(E1,8))+7,"dd/mm/yy") -> 20/07/16 - 26/07/16 | G1: Remaining
A2: Outgoings | C2: =SUM(C5:C20) -> 0 | D2: =SUM(D5:D20) -> 0 | E2: =SUM(E5:E20) -> 0 | F2: =SUM(F5:F20) -> 0
A4: General | B4: =SUM(B5:B9) -> 368 | G4: ="Remaining: £" & ROUND(SUM(G5:G10),2) -> Remaining: £443.74
A5: Car Petrol | B5: =IF(G1="Remaining",17.5*4,17.5*5) -> 70 | G5: =IF(B5<>"",B5-C5-D5-E5-F5,"") -> 70 | H5: =A5 -> Car Petrol
A6: Bike petrol | B6: =IF(G1="Remaining",4.5*4,4.5*5) -> 18 | G6: =IF(B6<>"",B6-C6-D6-E6-F6,"") -> 18 | H6: =A6 -> Bike petrol
A7: Food | B7: =IF(G1="Remaining",30*4,IF(H1= "Remaining",30* 5,"")) -> 120 | G7: =IF(B7<>"",B7-C7-D7-E7-F7,"") -> 120 | H7: =A7 -> Food
A8: Gift Fund | B8: =IF(G1="Remaining",20*4,IF(H1= "Remaining",20* 5,"")) -> 80 | G8: =IF(B8<>"",B8-C8-D8-E8-F8,"") -> 80 | H8: =A8 -> Gift Fund
A9: Holiday Fund | B9: =IF(G1="Remaining",20*4,IF(H1= "Remaining",20* 5,"")) -> 80 | G9: =IF(B9<>"",B9-C9-D9-E9-F9,"") -> 80 | H9: =A9 -> Holiday Fund
A10: Misc | B10: =IF(B26 <> 0,B26-B4-B12-B24,0) -> 75.74 | G10: =IF(B10<>"",B10-C10-D10-E10-F10,"") -> 75.74 | H10: Misc
A12: Direct debits | B12: =SUM(B13:B21) -> 859.87 | G12: ="Remaining: £" & ROUND(SUM(G13:G21),2) -> Remaining: £859.87
A13: House | B13: 500 | G13: =IF(B13<>"",B13-C13-D13-E13-F13,"") -> 500 | H13: =A13 -> House
A14: Ring | B14: 104.92 | G14: =IF(B14<>"",B14-C14-D14-E14-F14,"") -> 104.92 | H14: =A14 -> Ring
A15: Phone | B15: ='Joint Outgoings'!C29 -> 16.99 | G15: =IF(B15<>"",B15-C15-D15-E15-F15,"") -> 16.99 | H15: =A15 -> Phone
A16: Gym | B16: 17.99 | G16: =IF(B16<>"",B16-C16-D16-E16-F16,"") -> 17.99 | H16: =A16 -> Gym
A17: Car v.tax | B17: ='Joint Outgoings'!C25 -> 200 | G17: =IF(B17<>"",B17-C17-D17-E17-F17,"") -> 200 | H17: =A17 -> Car v.tax
A18: Sky Movies | B18: 3.99 | G18: =IF(B18<>"",B18-C18-D18-E18-F18,"") -> 3.99 | H18: =A18 -> Sky Movies
A19: Spotify | B19: 0 | G19: =IF(B19<>"",B19-C19-D19-E19-F19,"") -> 0 | H19: =A19 -> Spotify
A20: Onedrive | B20: 7.99 | G20: =IF(B20<>"",B20-C20-D20-E20-F20,"") -> 7.99 | H20: =A20 -> Onedrive
A21: Amazon Prime | B21: 7.99 | G21: =IF(B21<>"",B21-C21-D21-E21-F21,"") -> 7.99 | H21: =A21 -> Amazon Prime
A23: Savings
A24: Savings In | B24: =SUM(C24:F24) -> 0
A25: Savings Out | B25: =SUM(C25:F25) -> 0
A26: Income | B26: =SUM(C26:F26) -> 1303.61 | C26: 1303.61 | G26: =SUM(G5:G20) & " / " & B26 -> 1295.62 / 1303.61
G27: =IF(ROUND(SUM(G5:G20),2)>0,IF(ROUND(SUM(G5:G20),2)<ROUND(SUMIF(G5:G20,">0"),2),"NOT ENOUGH MONEY",""),"NO MONEY")
A28: Reminders: | B28: =IF(MONTH(TODAY()) = 11, IF(MONTH(A1(RIGHT,3)) = 11, "Bike insurance due",""),"")
B29: =IF(MONTH(TODAY()) = 6, IF(MONTH(A1(RIGHT,3)) = 6, "Bike insurance due",""),"")
A31: Pay after del:

Sheet Wages 2014
A1: 2014/Month | B1: Dates worked | C1: Days | D1: Hours | E1: Total Earned | F1: Total Bonus | G1: Pay + Bonus | H1: NI (12%) | I1: Pension (5%) | J1: Income Tax (%20) | K1: Expected | L1: Payday | M1: Total Paid (on date) | N1: Difference | O1: Total Late Payments | P1: Missing Paid On
A2: JAN | C2: =IF(B2<>"",((LEN(B2)-LEN(SUBSTITUTE(B2,",","")))/LEN(",")+1)+((LEN(B2)-LEN(SUBSTITUTE(B2,"/","")))/LEN("/")/2)- ((LEN(B2)-LEN(SUBSTITUTE(B2,"/","")))/LEN("/")),0) -> 0 | D2: =ROUND((((C2*7.5)/9)+(C2*7.5)), 2) -> 0 | E2: =D2*B15 -> 0 | F2: =IF(B$16<>0,B$16*D2-E2,0) -> 0 | G2: =IF(B16<>0,IF(ISREF(INDIRECT("'"&"Wages "&LEFT(A1,4)-1&"'!A1"))=TRUE,INDIRECT(CONCATENATE("'Wages ",LEFT(A1,4)-1,"'!F11")) + INDIRECT(CONCATENATE("'Wages ",LEFT(A1,4)-1,"'!F12")) + INDIRECT(CONCATENATE("'Wages ",LEFT(A1,4)-1,"'!F13")),""),0) -> 0 | H2: =IF(G2="",IF((((E2-I2)/4)-155)>0,((((E2-I2)/4)-155)*0.12)*4,0),IF((((G2-I2)/4)-155)>0,((((G2-I2)/4)-155)*0.12)*4,0)) -> 0 | I2: =IF(B$17<>"N",IF(G2="",E2*0.05,G2*0.05),0) -> 0 | J2: =IF(E2>11000,E2-11000*0.2,0) -> 0 | K2: =IF(G2="",E2-H2-I2-J2,G2-H2-I2-J2) -> 0 | L2: =TEXT(DATE(LEFT(A$1,4),IF(MONTH(DATEVALUE(A2&" 1"))+1>12,1,MONTH(DATEVALUE(A2&" 1"))+1),1),"mmm")&" " &DAY(EOMONTH((DATE(LEFT(A$1,4),MONTH(DATEVALUE(A2&" 1"))+1,1)),0)+1-WEEKDAY(EOMONTH((DATE(LEFT(A$1,4),MONTH(DATEVALUE(A2&" 1"))+1,1)),0)+1-4)) -> Feb 26
A3: FEB | C3: =IF(B3<>"",((LEN(B3)-LEN(SUBSTITUTE(B3,",","")))/LEN(",")+1)+((LEN(B3)-LEN(SUBSTITUTE(B3,"/","")))/LEN("/")/2)- ((LEN(B3)-LEN(SUBSTITUTE(B3,"/","")))/LEN("/")),0) -> 0 | D3: =ROUND((((C3*7.5)/9)+(C3*7.5)), 2) -> 0 | E3: =D3*B15 -> 0 | F3: =IF(B$16<>0,B$16*D3-E3,0) -> 0 | H3: =IF(G3="",IF((((E3-I3)/4)-155)>0,((((E3-I3)/4)-155)*0.12)*4,0),IF((((G3-I3)/4)-155)>0,((((G3-I3)/4)-155)*0.12)*4,0)) -> 0 | I3: =IF(B$17<>"N",IF(G3="",E3*0.05,G3*0.05),0) -> 0 | J3: =IF(SUM(E$2:E3)>11000,E3-11000*0.2,0) -> 0 | K3: =IF(G3="",E3-H3-I3-J3,G3-H3-I3-J3) -> 0 | L3: =TEXT(DATE(LEFT(A$1,4),IF(MONTH(DATEVALUE(A3&" 1"))+1>12,1,MONTH(DATEVALUE(A3&" 1"))+1),1),"mmm")&" " &DAY(EOMONTH((DATE(LEFT(A$1,4),MONTH(DATEVALUE(A3&" 1"))+1,1)),0)+1-WEEKDAY(EOMONTH((DATE(LEFT(A$1,4),MONTH(DATEVALUE(A3&" 1"))+1,1)),0)+1-4)) -> Mar 26
A4: MAR | C4: =IF(B4<>"",((LEN(B4)-LEN(SUBSTITUTE(B4,",","")))/LEN(",")+1)+((LEN(B4)-LEN(SUBSTITUTE(B4,"/","")))/LEN("/")/2)- ((LEN(B4)-LEN(SUBSTITUTE(B4,"/","")))/LEN("/")),0) -> 0 | D4: =ROUND((((C4*7.5)/9)+(C4*7.5)), 2) -> 0 | E4: =D4*B15 -> 0 | F4: =IF(B$16<>0,B$16*D4-E4,0) -> 0 | H4: =IF(G4="",IF((((E4-I4)/4)-155)>0,((((E4-I4)/4)-155)*0.12)*4,0),IF((((G4-I4)/4)-155)>0,((((G4-I4)/4)-155)*0.12)*4,0)) -> 0 | I4: =IF(B$17<>"N",IF(G4="",E4*0.05,G4*0.05),0) -> 0 | J4: =IF(SUM(E$2:E4)>11000,E4-11000*0.2,0) -> 0 | K4: =IF(G4="",E4-H4-I4-J4,G4-H4-I4-J4) -> 0 | L4: =TEXT(DATE(LEFT(A$1,4),IF(MONTH(DATEVALUE(A4&" 1"))+1>12,1,MONTH(DATEVALUE(A4&" 1"))+1),1),"mmm")&" " &DAY(EOMONTH((DATE(LEFT(A$1,4),MONTH(DATEVALUE(A4&" 1"))+1,1)),0)+1-WEEKDAY(EOMONTH((DATE(LEFT(A$1,4),MONTH(DATEVALUE(A4&" 1"))+1,1)),0)+1-4)) -> Apr 30
A5: APR | C5: =IF(B5<>"",((LEN(B5)-LEN(SUBSTITUTE(B5,",","")))/LEN(",")+1)+((LEN(B5)-LEN(SUBSTITUTE(B5,"/","")))/LEN("/")/2)- ((LEN(B5)-LEN(SUBSTITUTE(B5,"/","")))/LEN("/")),0) -> 0 | D5: =ROUND((((C5*7.5)/9)+(C5*7.5)), 2) -> 0 | E5: =D5*B15 -> 0 | F5: =IF(B$16<>0,B$16*D5-E5,0) -> 0 | G5: =IF(B16<>0,E5+SUM(F2:F4),0) -> 0 | H5: =IF(G5="",IF((((E5-I5)/4)-155)>0,((((E5-I5)/4)-155)*0.12)*4,0),IF((((G5-I5)/4)-155)>0,((((G5-I5)/4)-155)*0.12)*4,0)) -> 0 | I5: =IF(B$17<>"N",IF(G5="",E5*0.05,G5*0.05),0) -> 0 | J5: =IF(SUM(E$2:E5)>11000,E5-11000*0.2,0) -> 0 | K5: =IF(G5="",E5-H5-I5-J5,G5-H5-I5-J5) -> 0 | L5: =TEXT(DATE(LEFT(A$1,4),IF(MONTH(DATEVALUE(A5&" 1"))+1>12,1,MONTH(DATEVALUE(A5&" 1"))+1),1),"mmm")&" " &DAY(EOMONTH((DATE(LEFT(A$1,4),MONTH(DATEVALUE(A5&" 1"))+1,1)),0)+1-WEEKDAY(EOMONTH((DATE(LEFT(A$1,4),MONTH(DATEVALUE(A5&" 1"))+1,1)),0)+1-4)) -> May 28
A6: MAY | B6: 12,13,14,15,16,19,20,21,22,23,27,28,29,30 | C6: =IF(B6<>"",((LEN(B6)-LEN(SUBSTITUTE(B6,",","")))/LEN(",")+1)+((LEN(B6)-LEN(SUBSTITUTE(B6,"/","")))/LEN("/")/2)- ((LEN(B6)-LEN(SUBSTITUTE(B6,"/","")))/LEN("/")),0) -> 14 | D6: =ROUND((((C6*7.5)/9)+(C6*7.5)), 2)+6.33+0.89 -> 123.89 | E6: =D6*B15 -> 905.66068 | F6: =IF(B$16<>0,B$16*D6-E6,0) -> 0 | H6: =IF(G6="",IF((((E6-I6)/4)-155)>0,((((E6-I6)/4)-155)*0.12)*4,0),IF((((G6-I6)/4)-155)>0,((((G6-I6)/4)-155)*0.12)*4,0)) -> 34.279281 | I6: =IF(B$17<>"N",IF(G6="",E6*0.05,G6*0.05),0) -> 0 | J6: =IF(SUM(E$2:E6)>11000,E6-11000*0.2,0) -> 0 | K6: =IF(G6="",E6-H6-I6-J6,G6-H6-I6-J6) -> 871.3814 | L6: =TEXT(DATE(LEFT(A$1,4),IF(MONTH(DATEVALUE(A6&" 1"))+1>12,1,MONTH(DATEVALUE(A6&" 1"))+1),1),"mmm")&" " &DAY(EOMONTH((DATE(LEFT(A$1,4),MONTH(DATEVALUE(A6&" 1"))+1,1)),0)+1-WEEKDAY(EOMONTH((DATE(LEFT(A$1,4),MONTH(DATEVALUE(A6&" 1"))+1,1)),0)+1-4)) -> Jun 25 | M6: 630 | N6: =K6-M6 -> 241.3814
A7: JUN | B7: 2,3,4,5,6,9,10,11,12,13,16,17,18,19,20,23,24,25,26,27 | C7: =IF(B7<>"",((LEN(B7)-LEN(SUBSTITUTE(B7,",","")))/LEN(",")+1)+((LEN(B7)-LEN(SUBSTITUTE(B7,"/","")))/LEN("/")/2)- ((LEN(B7)-LEN(SUBSTITUTE(B7,"/","")))/LEN("/")),0) -> 20 | D7: =ROUND((((C7*7.5)/9)+(C7*7.5)), 2) -> 166.67 | E7: =D7*B15 -> 1218.391 | F7: =IF(B$16<>0,B$16*D7-E7,0) -> 0 | H7: =IF(G7="",IF((((E7-I7)/4)-155)>0,((((E7-I7)/4)-155)*0.12)*4,0),IF((((G7-I7)/4)-155)>0,((((G7-I7)/4)-155)*0.12)*4,0)) -> 71.806924 | I7: =IF(B$17<>"N",IF(G7="",E7*0.05,G7*0.05),0) -> 0 | J7: =IF(SUM(E$2:E7)>11000,E7-11000*0.2,0) -> 0 | K7: =IF(G7="",E7-H7-I7-J7,G7-H7-I7-J7) -> 1146.5841 | L7: =TEXT(DATE(LEFT(A$1,4),IF(MONTH(DATEVALUE(A7&" 1"))+1>12,1,MONTH(DATEVALUE(A7&" 1"))+1),1),"mmm")&" " &DAY(EOMONTH((DATE(LEFT(A$1,4),MONTH(DATEVALUE(A7&" 1"))+1,1)),0)+1-WEEKDAY(EOMONTH((DATE(LEFT(A$1,4),MONTH(DATEVALUE(A7&" 1"))+1,1)),0)+1-4)) -> Jul 30 | M7: 915.53 | N7: =K7-M7 -> 231.05411 | O7: 400 | P7: 42671
A8: JUL | B8: 14,15,16,17,18,21,22,23,24,25,28,29,30,31,1 | C8: =IF(B8<>"",((LEN(B8)-LEN(SUBSTITUTE(B8,",","")))/LEN(",")+1)+((LEN(B8)-LEN(SUBSTITUTE(B8,"/","")))/LEN("/")/2)- ((LEN(B8)-LEN(SUBSTITUTE(B8,"/","")))/LEN("/")),0) -> 15 | D8: =ROUND((((C8*7.5)/9)+(C8*7.5)), 2)-0.83 -> 124.17 | E8: =D8*B15 -> 907.70753 | F8: =IF(B$16<>0,B$16*D8-E8,0) -> 0 | G8: =IF(B16<>0,E8+SUM(F5:F7),0) -> 0 | H8: =IF(G8="",IF((((E8-I8)/4)-155)>0,((((E8-I8)/4)-155)*0.12)*4,0),IF((((G8-I8)/4)-155)>0,((((G8-I8)/4)-155)*0.12)*4,0)) -> 0 | I8: =IF(B$17<>"N",IF(G8="",E8*0.05,G8*0.05),0) -> 0 | J8: =IF(SUM(E$2:E8)>11000,E8-11000*0.2,0) -> 0 | K8: =IF(G8="",E8-H8-I8-J8,G8-H8-I8-J8) -> 0 | L8: =TEXT(DATE(LEFT(A$1,4),IF(MONTH(DATEVALUE(A8&" 1"))+1>12,1,MONTH(DATEVALUE(A8&" 1"))+1),1),"mmm")&" " &DAY(EOMONTH((DATE(LEFT(A$1,4),MONTH(DATEVALUE(A8&" 1"))+1,1)),0)+1-WEEKDAY(EOMONTH((DATE(LEFT(A$1,4),MONTH(DATEVALUE(A8&" 1"))+1,1)),0)+1-4)) -> Aug 27 | M8: 714.26 | N8: =K8-M8 -> -714.26 | O8: 106.02 | P8: 42672
A9: AUG | B9: 5,6,7 | C9: =IF(B9<>"",((LEN(B9)-LEN(SUBSTITUTE(B9,",","")))/LEN(",")+1)+((LEN(B9)-LEN(SUBSTITUTE(B9,"/","")))/LEN("/")/2)- ((LEN(B9)-LEN(SUBSTITUTE(B9,"/","")))/LEN("/")),0) -> 3 | D9: =ROUND((((C9*7.5)/9)+(C9*7.5)), 2) -> 25 | E9: =D9*B15 -> 182.755 | F9: =IF(B$16<>0,B$16*D9-E9,0) -> 0 | H9: =IF(G9="",IF((((E9-I9)/4)-155)>0,((((E9-I9)/4)-155)*0.12)*4,0),IF((((G9-I9)/4)-155)>0,((((G9-I9)/4)-155)*0.12)*4,0)) -> 0 | I9: =IF(B$17<>"N",IF(G9="",E9*0.05,G9*0.05),0) -> 0 | J9: =IF(SUM(E$2:E9)>11000,E9-11000*0.2,0) -> 0 | K9: =IF(G9="",E9-H9-I9-J9,G9-H9-I9-J9) -> 182.755 | L9: =TEXT(DATE(LEFT(A$1,4),IF(MONTH(DATEVALUE(A9&" 1"))+1>12,1,MONTH(DATEVALUE(A9&" 1"))+1),1),"mmm")&" " &DAY(EOMONTH((DATE(LEFT(A$1,4),MONTH(DATEVALUE(A9&" 1"))+1,1)),0)+1-WEEKDAY(EOMONTH((DATE(LEFT(A$1,4),MONTH(DATEVALUE(A9&" 1"))+1,1)),0)+1-4)) -> Sep 24 | M9: 225.71 | O9: 170.96 | P9: 42700
A10: SEP | C10: =IF(B10<>"",((LEN(B10)-LEN(SUBSTITUTE(B10,",","")))/LEN(",")+1)+((LEN(B10)-LEN(SUBSTITUTE(B10,"/","")))/LEN("/")/2)- ((LEN(B10)-LEN(SUBSTITUTE(B10,"/","")))/LEN("/")),0) -> 0 | D10: =ROUND((((C10*7.5)/9)+(C10*7.5)), 2) -> 0 | E10: =D10*B15 -> 0 | F10: =IF(B$16<>0,B$16*D10-E10,0) -> 0 | H10: =IF(G10="",IF((((E10-I10)/4)-155)>0,((((E10-I10)/4)-155)*0.12)*4,0),IF((((G10-I10)/4)-155)>0,((((G10-I10)/4)-155)*0.12)*4,0)) -> 0 | I10: =IF(B$17<>"N",IF(G10="",E10*0.05,G10*0.05),0) -> 0 | J10: =IF(SUM(E$2:E10)>11000,E10-11000*0.2,0) -> 0 | K10: =IF(G10="",E10-H10-I10-J10,G10-H10-I10-J10) -> 0 | L10: =TEXT(DATE(LEFT(A$1,4),IF(MONTH(DATEVALUE(A10&" 1"))+1>12,1,MONTH(DATEVALUE(A10&" 1"))+1),1),"mmm")&" " &DAY(EOMONTH((DATE(LEFT(A$1,4),MONTH(DATEVALUE(A10&" 1"))+1,1)),0)+1-WEEKDAY(EOMONTH((DATE(LEFT(A$1,4),MONTH(DATEVALUE(A10&" 1"))+1,1)),0)+1-4)) -> Oct 29
A11: OCT | C11: =IF(B11<>"",((LEN(B11)-LEN(SUBSTITUTE(B11,",","")))/LEN(",")+1)+((LEN(B11)-LEN(SUBSTITUTE(B11,"/","")))/LEN("/")/2)- ((LEN(B11)-LEN(SUBSTITUTE(B11,"/","")))/LEN("/")),0) -> 0 | D11: =ROUND((((C11*7.5)/9)+(C11*7.5)), 2) -> 0 | E11: =D11*B15 -> 0 | F11: =IF(B$16<>0,B$16*D11-E11,0) -> 0 | G11: =IF(B16<>0,E11+SUM(F8:F10),0) -> 0 | H11: =IF(G11="",IF((((E11-I11)/4)-155)>0,((((E11-I11)/4)-155)*0.12)*4,0),IF((((G11-I11)/4)-155)>0,((((G11-I11)/4)-155)*0.12)*4,0)) -> 0 | I11: =IF(B$17<>"N",IF(G11="",E11*0.05,G11*0.05),0) -> 0 | J11: =IF(SUM(E$2:E11)>11000,E11-11000*0.2,0) -> 0 | K11: =IF(G11="",E11-H11-I11-J11,G11-H11-I11-J11) -> 0 | L11: =TEXT(DATE(LEFT(A$1,4),IF(MONTH(DATEVALUE(A11&" 1"))+1>12,1,MONTH(DATEVALUE(A11&" 1"))+1),1),"mmm")&" " &DAY(EOMONTH((DATE(LEFT(A$1,4),MONTH(DATEVALUE(A11&" 1"))+1,1)),0)+1-WEEKDAY(EOMONTH((DATE(LEFT(A$1,4),MONTH(DATEVALUE(A11&" 1"))+1,1)),0)+1-4)) -> Nov 26
A12: NOV | C12: =IF(B12<>"",((LEN(B12)-LEN(SUBSTITUTE(B12,",","")))/LEN(",")+1)+((LEN(B12)-LEN(SUBSTITUTE(B12,"/","")))/LEN("/")/2)- ((LEN(B12)-LEN(SUBSTITUTE(B12,"/","")))/LEN("/")),0) -> 0 | D12: =ROUND((((C12*7.5)/9)+(C12*7.5)), 2) -> 0 | E12: =D12*B15 -> 0 | F12: =IF(B$16<>0,B$16*D12-E12,0) -> 0 | H12: =IF(G12="",IF((((E12-I12)/4)-155)>0,((((E12-I12)/4)-155)*0.12)*4,0),IF((((G12-I12)/4)-155)>0,((((G12-I12)/4)-155)*0.12)*4,0)) -> 0 | I12: =IF(B$17<>"N",IF(G12="",E12*0.05,G12*0.05),0) -> 0 | J12: =IF(SUM(E$2:E12)>11000,E12-11000*0.2,0) -> 0 | K12: =IF(G12="",E12-H12-I12-J12,G12-H12-I12-J12) -> 0 | L12: ="Dec 24" -> Dec 24
A13: DEC | C13: =IF(B13<>"",((LEN(B13)-LEN(SUBSTITUTE(B13,",","")))/LEN(",")+1)+((LEN(B13)-LEN(SUBSTITUTE(B13,"/","")))/LEN("/")/2)- ((LEN(B13)-LEN(SUBSTITUTE(B13,"/","")))/LEN("/")),0) -> 0 | D13: =ROUND((((C13*7.5)/9)+(C13*7.5)), 2) -> 0 | E13: =D13*B15 -> 0 | F13: =IF(B$16<>0,B$16*D13-E13,0) -> 0 | H13: =IF(G13="",IF((((E13-I13)/4)-155)>0,((((E13-I13)/4)-155)*0.12)*4,0),IF((((G13-I13)/4)-155)>0,((((G13-I13)/4)-155)*0.12)*4,0)) -> 0 | I13: =IF(B$17<>"N",IF(G13="",E13*0.05,G13*0.05),0) -> 0 | J13: =IF(SUM(E$2:E13)>11000,E13-11000*0.2,0) -> 0 | K13: =IF(G13="",E13-H13-I13-J13,G13-H13-I13-J13) -> 0 | L13: =TEXT(DATE(LEFT(A$1,4),IF(MONTH(DATEVALUE(A13&" 1"))+1>12,1,MONTH(DATEVALUE(A13&" 1"))+1),1),"mmm")&" " &DAY(EOMONTH((DATE(LEFT(A$1,4),MONTH(DATEVALUE(A13&" 1"))+1,1)),0)+1-WEEKDAY(EOMONTH((DATE(LEFT(A$1,4),MONTH(DATEVALUE(A13&" 1"))+1,1)),0)+1-4)) -> Jan 28
I14: ="SUM: " & ROUND(SUM(I8:I13),2) -> SUM: 0 | K14: ="SUM: "& ROUND(SUM(K2:K13),2) -> SUM: 2200.72 | M14: ="SUM: " & SUM(M2:M13) -> SUM: 2485.5 | N14: ="SUM: "& ROUND(SUM(N2:N13),2) -> SUM: -241.82 | O14: ="SUM: "& ROUND(SUM(O2:O13),2) -> SUM: 676.98
A15: Hourly Rate: | B15: 7.3102
A16: Bonus Rate | B16: 0
A17: Pension | B17: N
A19: Missing Hours
A21: 41820 | B21: 07.30-15.30 | C21: 7.5
A22: 41821 | B22: 07.30-15.30 | C22: 7.5
A23: 41822 | B23: 07.30-15.30 | C23: 7.5
A24: 41823 | B24: 07.30-15.30 | C24: 7.5
A25: 41824 | B25: 07.30-15.30 | C25: 7.5
A26: 41827 | B26: 07.30-15.30 | C26: 7.5
A27: 41828 | B27: 07.30-15.30 | C27: 7.5
A28: 41829 | B28: 07.30-15.30 | C28: 7.5
A29: 41830 | B29: 07.30-15.30 | C29: 7.5
A30: 41831 | B30: 07.30-15.30 | C30: 7.5
A31: Additional Holiday hours | C31: =SUM(C21:C30)/9 -> 8.3333333
A32: Additional Total | D32: =SUM(C21:C31) -> 83.333333 | E32: =SUM(D32*7.3102) -> 609.18333
A34: Revised Total | D34: =SUM(D32+D15) -> 83.333333 | E34: =SUM(E32+E15) -> 609.18333

Sheet Wages 2015
A1: 2015/Month | B1: Dates worked | C1: Days | D1: Hours | E1: Total Earned | F1: Total Bonus | G1: Pay + Bonus | H1: NI (12%) | I1: Pension (5%) | J1: Income Tax (%20) | K1: Expected | L1: Payday | M1: Total Paid (on date) | N1: Total Missing | O1: Missing Paid On
A2: JAN | C2: =IF(B2<>"",((LEN(B2)-LEN(SUBSTITUTE(B2,",","")))/LEN(",")+1)+((LEN(B2)-LEN(SUBSTITUTE(B2,"/","")))/LEN("/")/2)- ((LEN(B2)-LEN(SUBSTITUTE(B2,"/","")))/LEN("/")),0) -> 0 | D2: =ROUND((((C2*7.5)/9)+(C2*7.5)), 2) -> 0 | E2: =D2*B15 -> 0 | F2: =B$16*D2-E2 -> 0 | G2: =IF(B16<>0,IF(ISREF(INDIRECT("'"&"Wages "&LEFT(A1,4)-1&"'!A1"))=TRUE,INDIRECT(CONCATENATE("'Wages ",LEFT(A1,4)-1,"'!F11")) + INDIRECT(CONCATENATE("'Wages ",LEFT(A1,4)-1,"'!F12")) + INDIRECT(CONCATENATE("'Wages ",LEFT(A1,4)-1,"'!F13")),""),0) -> 0 | H2: =IF(G2="",IF((((E2-I2)/4)-155)>0,((((E2-I2)/4)-155)*0.12)*4,0),IF((((G2-I2)/4)-155)>0,((((G2-I2)/4)-155)*0.12)*4,0)) -> 0 | I2: =IF(G2="",E2*0.05,G2*0.05) -> 0 | J2: =IF(E2>11000,E2-11000*0.2,0) -> 0 | K2: =IF(G2="",E2-H2-I2-J2,G2-H2-I2-J2) -> 0 | L2: =TEXT(DATE(LEFT(A$1,4),IF(MONTH(DATEVALUE(A2&" 1"))+1>12,1,MONTH(DATEVALUE(A2&" 1"))+1),1),"mmm")&" " &DAY(EOMONTH((DATE(LEFT(A$1,4),MONTH(DATEVALUE(A2&" 1"))+1,1)),0)+1-WEEKDAY(EOMONTH((DATE(LEFT(A$1,4),MONTH(DATEVALUE(A2&" 1"))+1,1)),0)+1-4)) -> Feb 25
A3: FEB | C3: =IF(B3<>"",((LEN(B3)-LEN(SUBSTITUTE(B3,",","")))/LEN(",")+1)+((LEN(B3)-LEN(SUBSTITUTE(B3,"/","")))/LEN("/")/2)- ((LEN(B3)-LEN(SUBSTITUTE(B3,"/","")))/LEN("/")),0) -> 0 | D3: =ROUND((((C3*7.5)/9)+(C3*7.5)), 2) -> 0 | E3: =D3*B15 -> 0 | F3: =B$16*D3-E3 -> 0 | H3: =IF(G3="",IF((((E3-I3)/4)-155)>0,((((E3-I3)/4)-155)*0.12)*4,0),IF((((G3-I3)/4)-155)>0,((((G3-I3)/4)-155)*0.12)*4,0)) -> 0 | I3: =IF(G3="",E3*0.05,G3*0.05) -> 0 | J3: =IF(SUM(E$2:E3)>11000,E3-11000*0.2,0) -> 0 | K3: =IF(G3="",E3-H3-I3-J3,G3-H3-I3-J3) -> 0 | L3: =TEXT(DATE(LEFT(A$1,4),IF(MONTH(DATEVALUE(A3&" 1"))+1>12,1,MONTH(DATEVALUE(A3&" 1"))+1),1),"mmm")&" " &DAY(EOMONTH((DATE(LEFT(A$1,4),MONTH(DATEVALUE(A3&" 1"))+1,1)),0)+1-WEEKDAY(EOMONTH((DATE(LEFT(A$1,4),MONTH(DATEVALUE(A3&" 1"))+1,1)),0)+1-4)) -> Mar 25
A4: MAR | C4: =IF(B4<>"",((LEN(B4)-LEN(SUBSTITUTE(B4,",","")))/LEN(",")+1)+((LEN(B4)-LEN(SUBSTITUTE(B4,"/","")))/LEN("/")/2)- ((LEN(B4)-LEN(SUBSTITUTE(B4,"/","")))/LEN("/")),0) -> 0 | D4: =ROUND((((C4*7.5)/9)+(C4*7.5)), 2) -> 0 | E4: =D4*B15 -> 0 | F4: =B$16*D4-E4 -> 0 | H4: =IF(G4="",IF((((E4-I4)/4)-155)>0,((((E4-I4)/4)-155)*0.12)*4,0),IF((((G4-I4)/4)-155)>0,((((G4-I4)/4)-155)*0.12)*4,0)) -> 0 | I4: =IF(G4="",E4*0.05,G4*0.05) -> 0 | J4: =IF(SUM(E$2:E4)>11000,E4-11000*0.2,0) -> 0 | K4: =IF(G4="",E4-H4-I4-J4,G4-H4-I4-J4) -> 0 | L4: =TEXT(DATE(LEFT(A$1,4),IF(MONTH(DATEVALUE(A4&" 1"))+1>12,1,MONTH(DATEVALUE(A4&" 1"))+1),1),"mmm")&" " &DAY(EOMONTH((DATE(LEFT(A$1,4),MONTH(DATEVALUE(A4&" 1"))+1,1)),0)+1-WEEKDAY(EOMONTH((DATE(LEFT(A$1,4),MONTH(DATEVALUE(A4&" 1"))+1,1)),0)+1-4)) -> Apr 29
A5: APR | C5: =IF(B5<>"",((LEN(B5)-LEN(SUBSTITUTE(B5,",","")))/LEN(",")+1)+((LEN(B5)-LEN(SUBSTITUTE(B5,"/","")))/LEN("/")/2)- ((LEN(B5)-LEN(SUBSTITUTE(B5,"/","")))/LEN("/")),0) -> 0 | D5: =ROUND((((C5*7.5)/9)+(C5*7.5)), 2) -> 0 | E5: =D5*B15 -> 0 | F5: =B$16*D5-E5 -> 0 | G5: =IF(B16<>0,E5+SUM(F2:F4),0) -> 0 | H5: =IF(G5="",IF((((E5-I5)/4)-155)>0,((((E5-I5)/4)-155)*0.12)*4,0),IF((((G5-I5)/4)-155)>0,((((G5-I5)/4)-155)*0.12)*4,0)) -> 0 | I5: =IF(G5="",E5*0.05,G5*0.05) -> 0 | J5: =IF(SUM(E$2:E5)>11000,E5-11000*0.2,0) -> 0 | K5: =IF(G5="",E5-H5-I5-J5,G5-H5-I5-J5) -> 0 | L5: =TEXT(DATE(LEFT(A$1,4),IF(MONTH(DATEVALUE(A5&" 1"))+1>12,1,MONTH(DATEVALUE(A5&" 1"))+1),1),"mmm")&" " &DAY(EOMONTH((DATE(LEFT(A$1,4),MONTH(DATEVALUE(A5&" 1"))+1,1)),0)+1-WEEKDAY(EOMONTH((DATE(LEFT(A$1,4),MONTH(DATEVALUE(A5&" 1"))+1,1)),0)+1-4)) -> May 27 | M5: 317.47
A6: MAY | C6: =IF(B6<>"",((LEN(B6)-LEN(SUBSTITUTE(B6,",","")))/LEN(",")+1)+((LEN(B6)-LEN(SUBSTITUTE(B6,"/","")))/LEN("/")/2)- ((LEN(B6)-LEN(SUBSTITUTE(B6,"/","")))/LEN("/")),0) -> 0 | D6: =ROUND((((C6*7.5)/9)+(C6*7.5)), 2) -> 0 | E6: =D6*B15 -> 0 | F6: =B$16*D6-E6 -> 0 | H6: =IF(G6="",IF((((E6-I6)/4)-155)>0,((((E6-I6)/4)-155)*0.12)*4,0),IF((((G6-I6)/4)-155)>0,((((G6-I6)/4)-155)*0.12)*4,0)) -> 0 | I6: =IF(G6="",E6*0.05,G6*0.05) -> 0 | J6: =IF(SUM(E$2:E6)>11000,E6-11000*0.2,0) -> 0 | K6: =IF(G6="",E6-H6-I6-J6,G6-H6-I6-J6) -> 0 | L6: =TEXT(DATE(LEFT(A$1,4),IF(MONTH(DATEVALUE(A6&" 1"))+1>12,1,MONTH(DATEVALUE(A6&" 1"))+1),1),"mmm")&" " &DAY(EOMONTH((DATE(LEFT(A$1,4),MONTH(DATEVALUE(A6&" 1"))+1,1)),0)+1-WEEKDAY(EOMONTH((DATE(LEFT(A$1,4),MONTH(DATEVALUE(A6&" 1"))+1,1)),0)+1-4)) -> Jun 24 | M6: 816.81
A7: JUN | C7: =IF(B7<>"",((LEN(B7)-LEN(SUBSTITUTE(B7,",","")))/LEN(",")+1)+((LEN(B7)-LEN(SUBSTITUTE(B7,"/","")))/LEN("/")/2)- ((LEN(B7)-LEN(SUBSTITUTE(B7,"/","")))/LEN("/")),0) -> 0 | D7: =ROUND((((C7*7.5)/9)+(C7*7.5)), 2) -> 0 | E7: =D7*B15 -> 0 | F7: =B$16*D7-E7 -> 0 | H7: =IF(G7="",IF((((E7-I7)/4)-155)>0,((((E7-I7)/4)-155)*0.12)*4,0),IF((((G7-I7)/4)-155)>0,((((G7-I7)/4)-155)*0.12)*4,0)) -> 0 | I7: =IF(G7="",E7*0.05,G7*0.05) -> 0 | J7: =IF(SUM(E$2:E7)>11000,E7-11000*0.2,0) -> 0 | K7: =IF(G7="",E7-H7-I7-J7,G7-H7-I7-J7) -> 0 | L7: =TEXT(DATE(LEFT(A$1,4),IF(MONTH(DATEVALUE(A7&" 1"))+1>12,1,MONTH(DATEVALUE(A7&" 1"))+1),1),"mmm")&" " &DAY(EOMONTH((DATE(LEFT(A$1,4),MONTH(DATEVALUE(A7&" 1"))+1,1)),0)+1-WEEKDAY(EOMONTH((DATE(LEFT(A$1,4),MONTH(DATEVALUE(A7&" 1"))+1,1)),0)+1-4)) -> Jul 29 | M7: 760.21
A8: JUL | C8: =IF(B8<>"",((LEN(B8)-LEN(SUBSTITUTE(B8,",","")))/LEN(",")+1)+((LEN(B8)-LEN(SUBSTITUTE(B8,"/","")))/LEN("/")/2)- ((LEN(B8)-LEN(SUBSTITUTE(B8,"/","")))/LEN("/")),0) -> 0 | D8: =ROUND((((C8*7.5)/9)+(C8*7.5)), 2) -> 0 | E8: =D8*B15 -> 0 | F8: =B$16*D8-E8 -> 0 | G8: =IF(B16<>0,E8+SUM(F5:F7),0) -> 0 | H8: =IF(G8="",IF((((E8-I8)/4)-155)>0,((((E8-I8)/4)-155)*0.12)*4,0),IF((((G8-I8)/4)-155)>0,((((G8-I8)/4)-155)*0.12)*4,0)) -> 0 | I8: =IF(G8="",E8*0.05,G8*0.05) -> 0 | J8: =IF(SUM(E$2:E8)>11000,E8-11000*0.2,0) -> 0 | K8: =IF(G8="",E8-H8-I8-J8,G8-H8-I8-J8) -> 0 | L8: =TEXT(DATE(LEFT(A$1,4),IF(MONTH(DATEVALUE(A8&" 1"))+1>12,1,MONTH(DATEVALUE(A8&" 1"))+1),1),"mmm")&" " &DAY(EOMONTH((DATE(LEFT(A$1,4),MONTH(DATEVALUE(A8&" 1"))+1,1)),0)+1-WEEKDAY(EOMONTH((DATE(LEFT(A$1,4),MONTH(DATEVALUE(A8&" 1"))+1,1)),0)+1-4)) -> Aug 26 | M8: 788.55
A9: AUG | C9: =IF(B9<>"",((LEN(B9)-LEN(SUBSTITUTE(B9,",","")))/LEN(",")+1)+((LEN(B9)-LEN(SUBSTITUTE(B9,"/","")))/LEN("/")/2)- ((LEN(B9)-LEN(SUBSTITUTE(B9,"/","")))/LEN("/")),0) -> 0 | D9: =ROUND((((C9*7.5)/9)+(C9*7.5)), 2) -> 0 | E9: =D9*B15 -> 0 | F9: =B$16*D9-E9 -> 0 | H9: =IF(G9="",IF((((E9-I9)/4)-155)>0,((((E9-I9)/4)-155)*0.12)*4,0),IF((((G9-I9)/4)-155)>0,((((G9-I9)/4)-155)*0.12)*4,0)) -> 0 | I9: =IF(G9="",E9*0.05,G9*0.05) -> 0 | J9: =IF(SUM(E$2:E9)>11000,E9-11000*0.2,0) -> 0 | K9: =IF(G9="",E9-H9-I9-J9,G9-H9-I9-J9) -> 0 | L9: =TEXT(DATE(LEFT(A$1,4),IF(MONTH(DATEVALUE(A9&" 1"))+1>12,1,MONTH(DATEVALUE(A9&" 1"))+1),1),"mmm")&" " &DAY(EOMONTH((DATE(LEFT(A$1,4),MONTH(DATEVALUE(A9&" 1"))+1,1)),0)+1-WEEKDAY(EOMONTH((DATE(LEFT(A$1,4),MONTH(DATEVALUE(A9&" 1"))+1,1)),0)+1-4)) -> Sep 30 | M9: 257.39 | O9: Late
A10: SEP | C10: =IF(B10<>"",((LEN(B10)-LEN(SUBSTITUTE(B10,",","")))/LEN(",")+1)+((LEN(B10)-LEN(SUBSTITUTE(B10,"/","")))/LEN("/")/2)- ((LEN(B10)-LEN(SUBSTITUTE(B10,"/","")))/LEN("/")),0) -> 0 | D10: =ROUND((((C10*7.5)/9)+(C10*7.5)), 2) -> 0 | E10: =D10*B15 -> 0 | F10: =B$16*D10-E10 -> 0 | H10: =IF(G10="",IF((((E10-I10)/4)-155)>0,((((E10-I10)/4)-155)*0.12)*4,0),IF((((G10-I10)/4)-155)>0,((((G10-I10)/4)-155)*0.12)*4,0)) -> 0 | I10: =IF(G10="",E10*0.05,G10*0.05) -> 0 | J10: =IF(SUM(E$2:E10)>11000,E10-11000*0.2,0) -> 0 | K10: =IF(G10="",E10-H10-I10-J10,G10-H10-I10-J10) -> 0 | L10: =TEXT(DATE(LEFT(A$1,4),IF(MONTH(DATEVALUE(A10&" 1"))+1>12,1,MONTH(DATEVALUE(A10&" 1"))+1),1),"mmm")&" " &DAY(EOMONTH((DATE(LEFT(A$1,4),MONTH(DATEVALUE(A10&" 1"))+1,1)),0)+1-WEEKDAY(EOMONTH((DATE(LEFT(A$1,4),MONTH(DATEVALUE(A10&" 1"))+1,1)),0)+1-4)) -> Oct 28
A11: OCT | C11: =IF(B11<>"",((LEN(B11)-LEN(SUBSTITUTE(B11,",","")))/LEN(",")+1)+((LEN(B11)-LEN(SUBSTITUTE(B11,"/","")))/LEN("/")/2)- ((LEN(B11)-LEN(SUBSTITUTE(B11,"/","")))/LEN("/")),0) -> 0 | D11: =ROUND((((C11*7.5)/9)+(C11*7.5)), 2) -> 0 | E11: =D11*B15 -> 0 | F11: =B$16*D11-E11 -> 0 | G11: =IF(B16<>0,E11+SUM(F8:F10),0) -> 0 | H11: =IF(G11="",IF((((E11-I11)/4)-155)>0,((((E11-I11)/4)-155)*0.12)*4,0),IF((((G11-I11)/4)-155)>0,((((G11-I11)/4)-155)*0.12)*4,0)) -> 0 | I11: =IF(G11="",E11*0.05,G11*0.05) -> 0 | J11: =IF(SUM(E$2:E11)>11000,E11-11000*0.2,0) -> 0 | K11: =IF(G11="",E11-H11-I11-J11,G11-H11-I11-J11) -> 0 | L11: =TEXT(DATE(LEFT(A$1,4),IF(MONTH(DATEVALUE(A11&" 1"))+1>12,1,MONTH(DATEVALUE(A11&" 1"))+1),1),"mmm")&" " &DAY(EOMONTH((DATE(LEFT(A$1,4),MONTH(DATEVALUE(A11&" 1"))+1,1)),0)+1-WEEKDAY(EOMONTH((DATE(LEFT(A$1,4),MONTH(DATEVALUE(A11&" 1"))+1,1)),0)+1-4)) -> Nov 25 | M11: 321.79 | O11: Late
A12: NOV | C12: =IF(B12<>"",((LEN(B12)-LEN(SUBSTITUTE(B12,",","")))/LEN(",")+1)+((LEN(B12)-LEN(SUBSTITUTE(B12,"/","")))/LEN("/")/2)- ((LEN(B12)-LEN(SUBSTITUTE(B12,"/","")))/LEN("/")),0) -> 0 | D12: =ROUND((((C12*7.5)/9)+(C12*7.5)), 2) -> 0 | E12: =D12*B15 -> 0 | F12: =B$16*D12-E12 -> 0 | H12: =IF(G12="",IF((((E12-I12)/4)-155)>0,((((E12-I12)/4)-155)*0.12)*4,0),IF((((G12-I12)/4)-155)>0,((((G12-I12)/4)-155)*0.12)*4,0)) -> 0 | J12: =IF(SUM(E$2:E12)>11000,E12-11000*0.2,0) -> 0 | K12: =IF(G12="",E12-H12-I12-J12,G12-H12-I12-J12) -> 0 | L12: ="Dec 23" -> Dec 23 | M12: 333.27 | O12: Late
A13: DEC | C13: =IF(B13<>"",((LEN(B13)-LEN(SUBSTITUTE(B13,",","")))/LEN(",")+1)+((LEN(B13)-LEN(SUBSTITUTE(B13,"/","")))/LEN("/")/2)- ((LEN(B13)-LEN(SUBSTITUTE(B13,"/","")))/LEN("/")),0) -> 0 | D13: =ROUND((((C13*7.5)/9)+(C13*7.5)), 2) -> 0 | E13: =D13*B15 -> 0 | F13: =B$16*D13-E13 -> 0 | H13: =IF(G13="",IF((((E13-I13)/4)-155)>0,((((E13-I13)/4)-155)*0.12)*4,0),IF((((G13-I13)/4)-155)>0,((((G13-I13)/4)-155)*0.12)*4,0)) -> 0 | J13: =IF(SUM(E$2:E13)>11000,E13-11000*0.2,0) -> 0 | K13: =IF(G13="",E13-H13-I13-J13,G13-H13-I13-J13) -> 0 | L13: =TEXT(DATE(LEFT(A$1,4),IF(MONTH(DATEVALUE(A13&" 1"))+1>12,1,MONTH(DATEVALUE(A13&" 1"))+1),1),"mmm")&" " &DAY(EOMONTH((DATE(LEFT(A$1,4),MONTH(DATEVALUE(A13&" 1"))+1,1)),0)+1-WEEKDAY(EOMONTH((DATE(LEFT(A$1,4),MONTH(DATEVALUE(A13&" 1"))+1,1)),0)+1-4)) -> Jan 27 | M13: 411.84
I14: ="SUM: " & ROUND(SUM(I8:I13),2) -> SUM: 0 | K14: ="SUM: "& ROUND(SUM(K2:K13),2) -> SUM: 0 | M14: ="SUM: " & SUM(M2:M13) -> SUM: 4007.33
A15: Hourly Rate: | B15: 7.7224
A16: Bonus Rate | B16: 0
A17: Pension | B17: N

Sheet Wages 2016
A1: 2016/Month | B1: Days worked | C1: Hours | D1: Total Days | E1: Total Hours | F1: Total Earned | G1: Total Bonus | H1: Pay + Bonus | I1: NI (12%) | J1: Pension (5%) | K1: Income Tax (%20) | L1: Expected | M1: Payday | N1: Total Paid (on date) | O1: Total Missing | P1: Missing Paid On | Q1: Sum to date (Tax year)
A2: JAN | B2: 19, 20, 26, 27 | D2: =IF(B2<>"",((LEN(B2)-LEN(SUBSTITUTE(B2,",","")))/LEN(",")+1)+((LEN(B2)-LEN(SUBSTITUTE(B2,"/","")))/LEN("/")/2)- ((LEN(B2)-LEN(SUBSTITUTE(B2,"/","")))/LEN("/")),0) -> 4 | E2: =ROUND((((D2*7.5)/9)+(D2*7.5)), 2) -> 33.33 | F2: =E2*B19 -> 259.96067 | G2: =8.25*E2-F2 -> 15.011832 | H2: =IF(B20<>0,IF(ISREF(INDIRECT("'"&"Wages "&LEFT(A1,4)-1&"'!A1"))=TRUE,INDIRECT(CONCATENATE("'Wages ",LEFT(A1,4)-1,"'!F11")) + INDIRECT(CONCATENATE("'Wages ",LEFT(A1,4)-1,"'!F12")) + INDIRECT(CONCATENATE("'Wages ",LEFT(A1,4)-1,"'!F13")),""),0) -> 0 | I2: =IF(H2="",IF((((F2-J2)/4)-155)>0,((((F2-J2)/4)-155)*0.12)*4,0),IF((((H2-J2)/4)-155)>0,((((H2-J2)/4)-155)*0.12)*4,0)) -> 0 | J2: =IF(H2="",F2*0.05,H2*0.05) -> 0 | K2: =IF(F2>11000,F2-11000*0.2,0) -> 0 | L2: =IF(H2="",F2-I2-J2-K2,H2-I2-J2-K2) -> 0 | M2: =TEXT(DATE(LEFT(A$1,4),IF(MONTH(DATEVALUE(A2&" 1"))+1>12,1,MONTH(DATEVALUE(A2&" 1"))+1),1),"mmm")&" " &DAY(EOMONTH((DATE(LEFT(A$1,4),MONTH(DATEVALUE(A2&" 1"))+1,1)),0)+1-WEEKDAY(EOMONTH((DATE(LEFT(A$1,4),MONTH(DATEVALUE(A2&" 1"))+1,1)),0)+1-4)) -> Feb 24 | N2: 321.79 | Q2: =F2 -> 259.96067
A3: FEB | B3: 2, 3, 9, 10, 17, 18, 19, 23, 24 | D3: =IF(B3<>"",((LEN(B3)-LEN(SUBSTITUTE(B3,",","")))/LEN(",")+1)+((LEN(B3)-LEN(SUBSTITUTE(B3,"/","")))/LEN("/")/2)- ((LEN(B3)-LEN(SUBSTITUTE(B3,"/","")))/LEN("/")),0) -> 9 | E3: =ROUND((((D3*7.5)/9)+(D3*7.5)), 2) -> 75 | F3: =E3*B19 -> 584.97 | G3: =8.25*E3-F3 -> 33.78 | I3: =IF(H3="",IF((((F3-J3)/4)-155)>0,((((F3-J3)/4)-155)*0.12)*4,0),IF((((H3-J3)/4)-155)>0,((((H3-J3)/4)-155)*0.12)*4,0)) -> 0 | J3: =IF(H3="",F3*0.05,H3*0.05) -> 29.2485 | K3: =IF(SUM(F$2:F3)>11000,F3-11000*0.2,0) -> 0 | L3: =IF(H3="",F3-I3-J3-K3,H3-I3-J3-K3) -> 555.7215 | M3: =TEXT(DATE(LEFT(A$1,4),IF(MONTH(DATEVALUE(A3&" 1"))+1>12,1,MONTH(DATEVALUE(A3&" 1"))+1),1),"mmm")&" " &DAY(EOMONTH((DATE(LEFT(A$1,4),MONTH(DATEVALUE(A3&" 1"))+1,1)),0)+1-WEEKDAY(EOMONTH((DATE(LEFT(A$1,4),MONTH(DATEVALUE(A3&" 1"))+1,1)),0)+1-4)) -> Mar 30 | N3: 643.51 | O3: =L3-N3 -> -87.7885 | Q3: =Q2+F3 -> 844.93067
A4: MAR | B4: 1, 2, 8, 9(1/2), 15, 16, 22, 23, 24 | D4: =IF(B4<>"",((LEN(B4)-LEN(SUBSTITUTE(B4,",","")))/LEN(",")+1)+((LEN(B4)-LEN(SUBSTITUTE(B4,"/","")))/LEN("/")/2)- ((LEN(B4)-LEN(SUBSTITUTE(B4,"/","")))/LEN("/")),0) -> 8.5 | E4: =ROUND((((D4*7.5)/9)+(D4*7.5)), 2) -> 70.83 | F4: =E4*B19 -> 552.44567 | G4: =8.25*E4-F4 -> 31.901832 | I4: =IF(H4="",IF((((F4-J4)/4)-155)>0,((((F4-J4)/4)-155)*0.12)*4,0),IF((((H4-J4)/4)-155)>0,((((H4-J4)/4)-155)*0.12)*4,0)) -> 0 | J4: =IF(H4="",F4*0.05,H4*0.05) -> 27.622283 | K4: =IF(SUM(F$2:F4)>11000,F4-11000*0.2,0) -> 0 | L4: =IF(H4="",F4-I4-J4-K4,H4-I4-J4-K4) -> 524.82338 | M4: =TEXT(DATE(LEFT(A$1,4),IF(MONTH(DATEVALUE(A4&" 1"))+1>12,1,MONTH(DATEVALUE(A4&" 1"))+1),1),"mmm")&" " &DAY(EOMONTH((DATE(LEFT(A$1,4),MONTH(DATEVALUE(A4&" 1"))+1,1)),0)+1-WEEKDAY(EOMONTH((DATE(LEFT(A$1,4),MONTH(DATEVALUE(A4&" 1"))+1,1)),0)+1-4)) -> Apr 27 | N4: 579.76 | O4: =L4-N4 -> -54.936615 | Q4: =Q3+F4 -> 1397.3763
A5: APR | B5: 12, 13, 19, 20 | D5: =IF(B5<>"",((LEN(B5)-LEN(SUBSTITUTE(B5,",","")))/LEN(",")+1)+((LEN(B5)-LEN(SUBSTITUTE(B5,"/","")))/LEN("/")/2)- ((LEN(B5)-LEN(SUBSTITUTE(B5,"/","")))/LEN("/")),0) -> 4 | E5: =ROUND((((D5*7.5)/9)+(D5*7.5)), 2) -> 33.33 | F5: =E5*B19 -> 259.96067 | G5: =8.25*E5-F5 -> 15.011832 | H5: =IF(B20<>0,F5+SUM(G2:G4),0) -> 340.65433 | I5: =IF(H5="",IF((((F5-J5)/4)-155)>0,((((F5-J5)/4)-155)*0.12)*4,0),IF((((H5-J5)/4)-155)>0,((((H5-J5)/4)-155)*0.12)*4,0)) -> 0 | J5: =IF(H5="",F5*0.05,H5*0.05) -> 17.032717 | K5: =IF(SUM(F$2:F5)>11000,F5-11000*0.2,0) -> 0 | L5: =IF(H5="",F5-I5-J5-K5,H5-I5-J5-K5) -> 323.62162 | M5: =TEXT(DATE(LEFT(A$1,4),IF(MONTH(DATEVALUE(A5&" 1"))+1>12,1,MONTH(DATEVALUE(A5&" 1"))+1),1),"mmm")&" " &DAY(EOMONTH((DATE(LEFT(A$1,4),MONTH(DATEVALUE(A5&" 1"))+1,1)),0)+1-WEEKDAY(EOMONTH((DATE(LEFT(A$1,4),MONTH(DATEVALUE(A5&" 1"))+1,1)),0)+1-4)) -> May 25 | N5: 259.96 | O5: =L5-N5 -> 63.661615 | Q5: =F5 -> 259.96067
A6: MAY | B6: 16, 17, 18, 19, 20, 23, 24, 25, 26, 27 | D6: =IF(B6<>"",((LEN(B6)-LEN(SUBSTITUTE(B6,",","")))/LEN(",")+1)+((LEN(B6)-LEN(SUBSTITUTE(B6,"/","")))/LEN("/")/2)- ((LEN(B6)-LEN(SUBSTITUTE(B6,"/","")))/LEN("/")),0) -> 10 | E6: =ROUND((((D6*7.5)/9)+(D6*7.5)), 2) -> 83.33 | F6: =E6*B19 -> 649.94067 | G6: =8.25*E6-F6 -> 37.531832 | I6: =IF(H6="",IF((((F6-J6)/4)-155)>0,((((F6-J6)/4)-155)*0.12)*4,0),IF((((H6-J6)/4)-155)>0,((((H6-J6)/4)-155)*0.12)*4,0)) -> 0 | J6: =IF(H6="",F6*0.05,H6*0.05) -> 32.497033 | K6: =IF(SUM(F$2:F6)>11000,F6-11000*0.2,0) -> 0 | L6: =IF(H6="",F6-I6-J6-K6,H6-I6-J6-K6) -> 617.44363 | M6: =TEXT(DATE(LEFT(A$1,4),IF(MONTH(DATEVALUE(A6&" 1"))+1>12,1,MONTH(DATEVALUE(A6&" 1"))+1),1),"mmm")&" " &DAY(EOMONTH((DATE(LEFT(A$1,4),MONTH(DATEVALUE(A6&" 1"))+1,1)),0)+1-WEEKDAY(EOMONTH((DATE(LEFT(A$1,4),MONTH(DATEVALUE(A6&" 1"))+1,1)),0)+1-4)) -> Jun 29 | N6: 325.01 | O6: 305 | P6: 11110 | Q6: =Q5+N6 -> 584.97067
A7: JUN | B7: 30(1/2), 31(1/2), 1, 2, 3, 8, 9, 10, 15, 16, 17, 20, 21, 22, 23, 24 | D7: =IF(B7<>"",((LEN(B7)-LEN(SUBSTITUTE(B7,",","")))/LEN(",")+1)+((LEN(B7)-LEN(SUBSTITUTE(B7,"/","")))/LEN("/")/2)- ((LEN(B7)-LEN(SUBSTITUTE(B7,"/","")))/LEN("/")),0) -> 15 | E7: =ROUND((((D7*7.5)/9)+(D7*7.5)), 2) -> 125 | F7: =E7*B19 -> 974.95 | G7: =8.25*E7-F7 -> 56.3 | I7: =IF(H7="",IF((((F7-J7)/4)-155)>0,((((F7-J7)/4)-155)*0.12)*4,0),IF((((H7-J7)/4)-155)>0,((((H7-J7)/4)-155)*0.12)*4,0)) -> 36.7443 | J7: =IF(H7="",F7*0.05,H7*0.05) -> 48.7475 | K7: =IF(SUM(F$2:F7)>11000,F7-11000*0.2,0) -> 0 | L7: =IF(H7="",F7-I7-J7-K7,H7-I7-J7-K7) -> 889.4582 | M7: =TEXT(DATE(LEFT(A$1,4),IF(MONTH(DATEVALUE(A7&" 1"))+1>12,1,MONTH(DATEVALUE(A7&" 1"))+1),1),"mmm")&" " &DAY(EOMONTH((DATE(LEFT(A$1,4),MONTH(DATEVALUE(A7&" 1"))+1,1)),0)+1-WEEKDAY(EOMONTH((DATE(LEFT(A$1,4),MONTH(DATEVALUE(A7&" 1"))+1,1)),0)+1-4)) -> Jul 27 | N7: 993.29 | O7: =L7-N7 -> -103.8318 | Q7: =Q6+F7 -> 1559.9207
A8: JUL | B8: 11, 13, 14, 15, 18, 19(1/2), 20, 21, 22(1/2), 25, 26, 27, 28, 29 | D8: =IF(B8<>"",((LEN(B8)-LEN(SUBSTITUTE(B8,",","")))/LEN(",")+1)+((LEN(B8)-LEN(SUBSTITUTE(B8,"/","")))/LEN("/")/2)- ((LEN(B8)-LEN(SUBSTITUTE(B8,"/","")))/LEN("/")),0) -> 13 | E8: =ROUND((((D8*7.5)/9)+(D8*7.5)), 2) -> 108.33 | F8: =E8*B19 -> 844.93067 | G8: =8.25*E8-F8 -> 48.791832 | H8: =IF(B20<>0,F8+SUM(G5:G7),0) -> 953.77433 | I8: =IF(H8="",IF((((F8-J8)/4)-155)>0,((((F8-J8)/4)-155)*0.12)*4,0),IF((((H8-J8)/4)-155)>0,((((H8-J8)/4)-155)*0.12)*4,0)) -> 34.330274 | J8: =IF(H8="",F8*0.05,H8*0.05) -> 47.688717 | K8: =IF(SUM(F$2:F8)>11000,F8-11000*0.2,0) -> 0 | L8: =IF(H8="",F8-I8-J8-K8,H8-I8-J8-K8) -> 871.75534 | M8: =TEXT(DATE(LEFT(A$1,4),IF(MONTH(DATEVALUE(A8&" 1"))+1>12,1,MONTH(DATEVALUE(A8&" 1"))+1),1),"mmm")&" " &DAY(EOMONTH((DATE(LEFT(A$1,4),MONTH(DATEVALUE(A8&" 1"))+1,1)),0)+1-WEEKDAY(EOMONTH((DATE(LEFT(A$1,4),MONTH(DATEVALUE(A8&" 1"))+1,1)),0)+1-4)) -> Aug 31 | N8: 905.12 | O8: =L8-N8 -> -33.364658 | Q8: =Q7+F8 -> 2404.8513
A9: AUG | B9: 1, 2, 3, 4, 5, 8, 9, 10, 11, 12, 15, 16, 17, 18, 19 | D9: =IF(B9<>"",((LEN(B9)-LEN(SUBSTITUTE(B9,",","")))/LEN(",")+1)+((LEN(B9)-LEN(SUBSTITUTE(B9,"/","")))/LEN("/")/2)- ((LEN(B9)-LEN(SUBSTITUTE(B9,"/","")))/LEN("/")),0) -> 15 | E9: =ROUND((((D9*7.5)/9)+(D9*7.5)), 2) -> 125 | F9: =E9*B19 -> 974.95 | G9: =8.25*E9-F9 -> 56.3 | I9: =IF(H9="",IF((((F9-J9)/4)-155)>0,((((F9-J9)/4)-155)*0.12)*4,0),IF((((H9-J9)/4)-155)>0,((((H9-J9)/4)-155)*0.12)*4,0)) -> 36.7443 | J9: =IF(H9="",F9*0.05,H9*0.05) -> 48.7475 | K9: =IF(SUM(F$2:F9)>11000,F9-11000*0.2,0) -> 0 | L9: =IF(H9="",F9-I9-J9-K9,H9-I9-J9-K9) -> 889.4582 | M9: =TEXT(DATE(LEFT(A$1,4),IF(MONTH(DATEVALUE(A9&" 1"))+1>12,1,MONTH(DATEVALUE(A9&" 1"))+1),1),"mmm")&" " &DAY(EOMONTH((DATE(LEFT(A$1,4),MONTH(DATEVALUE(A9&" 1"))+1,1)),0)+1-WEEKDAY(EOMONTH((DATE(LEFT(A$1,4),MONTH(DATEVALUE(A9&" 1"))+1,1)),0)+1-4)) -> Sep 28 | N9: 910.51 | O9: =L9-N9 -> -21.0518 | Q9: =Q8+F9 -> 3379.8013
A10: SEP | B10: 5, 6, 7, 8, 9, 12(1/2), 13, 14, 15, 16, 20, 21, 23, 24, 26, 27, 28 | D10: =IF(B10<>"",((LEN(B10)-LEN(SUBSTITUTE(B10,",","")))/LEN(",")+1)+((LEN(B10)-LEN(SUBSTITUTE(B10,"/","")))/LEN("/")/2)- ((LEN(B10)-LEN(SUBSTITUTE(B10,"/","")))/LEN("/")),0) -> 16.5 | E10: =ROUND((((D10*7.5)/9)+(D10*7.5)), 2)+1 -> 138.5 | F10: =E10*B19 -> 1080.2446 | G10: =8.25*E10-F10 -> 62.3804 | I10: =IF(H10="",IF((((F10-J10)/4)-155)>0,((((F10-J10)/4)-155)*0.12)*4,0),IF((((H10-J10)/4)-155)>0,((((H10-J10)/4)-155)*0.12)*4,0)) -> 48.747884 | J10: =IF(H10="",F10*0.05,H10*0.05) -> 54.01223 | K10: =IF(SUM(F$2:F10)>11000,F10-11000*0.2,0) -> 0 | L10: =IF(H10="",F10-I10-J10-K10,H10-I10-J10-K10) -> 977.48449 | M10: =TEXT(DATE(LEFT(A$1,4),IF(MONTH(DATEVALUE(A10&" 1"))+1>12,1,MONTH(DATEVALUE(A10&" 1"))+1),1),"mmm")&" " &DAY(EOMONTH((DATE(LEFT(A$1,4),MONTH(DATEVALUE(A10&" 1"))+1,1)),0)+1-WEEKDAY(EOMONTH((DATE(LEFT(A$1,4),MONTH(DATEVALUE(A10&" 1"))+1,1)),0)+1-4)) -> Oct 26 | N10: 979.78 | O10: =L10-N10 -> -2.2955144 | Q10: =Q9+F10 -> 4460.0459
A11: OCT | B11: 3+, 4(^6), 5(£3), 6+, 10+, 11(^6), 12(£3), 13+, 17+, 18(^6), 19(£3), 20+, 24+, 25(^6), 26(£3), 27+ | D11: =IF(B11<>"",((LEN(B11)-LEN(SUBSTITUTE(B11,",","")))+1)) -> 16 | E11: =(ROUND((((D11*7.5)/9)+(D11*7.5)), 2) + (LEN(B11)-LEN(SUBSTITUTE(B11,"+","")))) - ((((LEN(B11)-LEN(SUBSTITUTE(B11,"^","")))*7.5)-((LEN(B11)-LEN(SUBSTITUTE(B11,"^","")))*6))+(((LEN(B11)-LEN(SUBSTITUTE(B11,"£","")))*7.5)-((LEN(B11)-LEN(SUBSTITUTE(B11,"£","")))*3)))+1 -> 118.33 | F11: =E11*B19 -> 922.92667 | G11: =8.25*E11-F11 -> 53.295832 | H11: =IF(B20<>0,F11+SUM(G8:G10),0) -> 1090.3989 | I11: =IF(H11="",IF((((F11-J11)/4)-155)>0,((((F11-J11)/4)-155)*0.12)*4,0),IF((((H11-J11)/4)-155)>0,((((H11-J11)/4)-155)*0.12)*4,0)) -> 49.905475 | J11: =IF(H11="",F11*0.05,H11*0.05) -> 54.519945 | K11: =IF(SUM(F$2:F11)>11000,F11-11000*0.2,0) -> 0 | L11: =IF(H11="",F11-I11-J11-K11,H11-I11-J11-K11) -> 985.97348 | M11: =TEXT(DATE(LEFT(A$1,4),IF(MONTH(DATEVALUE(A11&" 1"))+1>12,1,MONTH(DATEVALUE(A11&" 1"))+1),1),"mmm")&" " &DAY(EOMONTH((DATE(LEFT(A$1,4),MONTH(DATEVALUE(A11&" 1"))+1,1)),0)+1-WEEKDAY(EOMONTH((DATE(LEFT(A$1,4),MONTH(DATEVALUE(A11&" 1"))+1,1)),0)+1-4)) -> Nov 30 | N11: 950.62 | O11: =L11-N11 -> 35.35348 | Q11: =Q10+F11 -> 5382.9726
A12: NOV | B12: 31+, 1(^6), 3+, 7+, 8(^6), 9(£3), 10+, 14+, 17+, 18+, 21+, 22+, 23+, 24+, 25/ | D12: =IF(B12<>"",((LEN(B12)-LEN(SUBSTITUTE(B12,",","")))+1)) -> 15 | E12: =ROUND((((D12*7.5)/9)+(D12*7.5)), 2) - ((((LEN(B12)-LEN(SUBSTITUTE(B12,"^","")))*7.5)-((LEN(B12)-LEN(SUBSTITUTE(B12,"^","")))*6))+(((LEN(B12)-LEN(SUBSTITUTE(B12,"£","")))*7.5)-((LEN(B12)-LEN(SUBSTITUTE(B12,"£","")))*3))) + (LEN(B12)-LEN(SUBSTITUTE(B12,"+",""))) -> 128.5 | F12: =E12*B19 -> 1002.2486 | G12: =8.25*E12-F12 -> 57.8764 | I12: =IF(H12="",IF((((F12-J12)/4)-155)>0,((((F12-J12)/4)-155)*0.12)*4,0),IF((((H12-J12)/4)-155)>0,((((H12-J12)/4)-155)*0.12)*4,0)) -> 39.85634 | J12: =IF(H12="",F12*0.05,H12*0.05) -> 50.11243 | K12: =IF(SUM(F$2:F12)>11000,F12-11000*0.2,0) -> 0 | L12: =IF(H12="",F12-I12-J12-K12,H12-I12-J12-K12) -> 912.27983 | M12: ="Dec 21" -> Dec 21 | N12: 866.48 | O12: =L12-N12 -> 45.79983 | Q12: =Q11+F12 -> 6385.2212
A13: DEC | B13: =(IF(B14<>"",((LEN(B14)-LEN(SUBSTITUTE(B14,",","")))+1)))+(IF(B15<>"",((LEN(B15)-LEN(SUBSTITUTE(B15,",","")))+1)))+(IF(B16<>"",((LEN(B16)-LEN(SUBSTITUTE(B16,",","")))+1)))+(IF(B17<>"",((LEN(B17)-LEN(SUBSTITUTE(B17,",","")))+1))) -> 14 | C13: =ROUND(SUM(C14:C16)/9,2)+SUM(C14:C16) -> 102.22 | D13: =IF(B13<>"",((LEN(B13)-LEN(SUBSTITUTE(B13,",","")))+1)) -> 1 | F13: =C13*B19 -> 797.27511 | G13: =8.25*C13-F13 -> 46.039888 | I13: =IF(H13="",IF((((F13-J13)/4)-155)>0,((((F13-J13)/4)-155)*0.12)*4,0),IF((((H13-J13)/4)-155)>0,((((H13-J13)/4)-155)*0.12)*4,0)) -> 21.273013 | K13: =IF(SUM(F$2:F13)>11000,F13-11000*0.2,0) -> 0 | L13: =IF(H13="",F13-I13-J13-K13,H13-I13-J13-K13) -> 776.0021 | M13: =TEXT(DATE(LEFT(A$1,4),IF(MONTH(DATEVALUE(A13&" 1"))+1>12,1,MONTH(DATEVALUE(A13&" 1"))+1),1),"mmm")&" " &DAY(EOMONTH((DATE(LEFT(A$1,4),MONTH(DATEVALUE(A13&" 1"))+1,1)),0)+1-WEEKDAY(EOMONTH((DATE(LEFT(A$1,4),MONTH(DATEVALUE(A13&" 1"))+1,1)),0)+1-4)) -> Jan 25 | N13: 798.12 | Q13: =Q12+F13 -> 7182.4963
A14: 42702 | B14: 28,29,1,2 | C14: =8+6+5+8 -> 27
A15: =A14+7 -> 42709 | B15: 5, 6, 7, 8, 9 | C15: =8+6+3+8+7 -> 32
A16: =A15+7 -> 42716 | B16: 12,13,14,15,16 | C16: =8+6+3+8+8 -> 33
A17: =A16+7 -> 42723 | J17: ="SUM: " & ROUND(SUM(J8:J13),2) -> SUM: 255.08 | L17: ="SUM: "& ROUND(SUM(L2:L13),2) -> SUM: 8324.02 | N17: ="SUM: " & SUM(N2:N13) -> SUM: 8533.95
A19: Hourly Rate: | B19: 7.7996
A20: Bonus Rate | B20: 8.25
A21: Pension | B21: N
A30: 8.5 * 5 | B30: =ROUND((8.5*5)+((8.5*5)/9),2)*52 -> 2455.44 | C30: =B30*8.25 -> 20257.38 | D30: =C30/12 -> 1688.115 | E30: =(D30/4-155)*0.12*4 -> 128.1738 | F30: =ROUND((C30-11000)*0.2,2) -> 1851.48 | G30: =C30-F30-E30 -> 18277.726
A31: 7.5 * 5 | B31: =ROUND((7.5*5)+((7.5*5)/9),2)*52 -> 2166.84 | C31: =B31*8.25 -> 17876.43 | D31: =C31/12 -> 1489.7025 | E31: =(D31/4-155)*0.12*4 -> 104.3643 | F31: =ROUND((C31-11000)*0.2,2) -> 1375.29 | G31: =C31-F31-E31 -> 16396.776
A32: 8.5 * 4 | B32: =37.78*52 -> 1964.56 | C32: =B32*8.25 -> 16207.62 | D32: =C32/12 -> 1350.635 | E32: =(D32/4-155)*0.12*4 -> 87.6762 | F32: =ROUND((C32-11000)*0.2,2) -> 1041.52 | G32: =C32-F32-E32 -> 15078.424
A33: 7.5 * 4 | B33: =ROUND((7.5*4)+((7.5*4)/9),2)*52 -> 1733.16 | C33: =B33*8.25 -> 14298.57 | D33: =C33/12 -> 1191.5475 | E33: =(D33/4-155)*0.12*4 -> 68.5857 | F33: =ROUND((C33-11000)*0.2,2) -> 659.71 | G33: =C33-F33-E33 -> 13570.274

Sheet BRI Wages 2017
A1: 2017/Month | B1: Days worked | C1: Hours | D1: Gross Pay | E1: Total Bonus | F1: Gross + Bonus | G1: NI (12%) | H1: Pension (5%) | I1: Income Tax (%20) | J1: Net Pay | K1: Payday | L1: Total Paid | M1: Total Missing | N1: Gross sum to date (Tax year)
A2: JAN | B2: =(IF(B3<>"",((LEN(B3)-LEN(SUBSTITUTE(B3,",","")))+1)))+(IF(B4<>"",((LEN(B4)-LEN(SUBSTITUTE(B4,",","")))+1)))+(IF(B5<>"",((LEN(B5)-LEN(SUBSTITUTE(B5,",","")))+1)))+(IF(B6<>"",((LEN(B6)-LEN(SUBSTITUTE(B6,",","")))+1))) -> 18 | C2: =ROUND(SUM(C3:C6)/9,2)+SUM(C3:C6) -> 150 | D2: =C2*B41 -> 1181.685 | E2: =8.25*C2-D2 -> 55.815 | F2: =IF(ISREF(INDIRECT("'"&"Wages "&LEFT(A1,4)-1&"'!A1"))=TRUE,INDIRECT(CONCATENATE("'Wages ",LEFT(A1,4)-1,"'!G11")) + INDIRECT(CONCATENATE("'Wages ",LEFT(A1,4)-1,"'!G12")) + INDIRECT(CONCATENATE("'Wages ",LEFT(A1,4)-1,"'!G13")) + D2,"") -> 1338.8971 | G2: =IF(F2="",IF((((D2-H2)/4)-155)>0,((((D2-H2)/4)-155)*0.12)*4,0),IF((((F2-H2)/4)-155)>0,((((F2-H2)/4)-155)*0.12)*4,0)) -> 78.234272 | H2: =IF(B$43<>"N",IF(F2="",D2*0.05,F2*0.05),0) -> 66.944856 | I2: =IF(N2>11000,IF(F2="",(D2-11000)*0.2,(F2-11000)*0.2),0) -> 0 | J2: =IF(F2="",D2-G2-H2,F2-G2-H2) -> 1193.718 | K2: =TEXT(DATE(LEFT(A$1,4),IF(MONTH(DATEVALUE(A2&" 1"))+1>12,1,MONTH(DATEVALUE(A2&" 1"))+1),1),"mmm")&" " &DAY(EOMONTH((DATE(LEFT(A$1,4),MONTH(DATEVALUE(A2&" 1"))+1,1)),0)+1-WEEKDAY(EOMONTH((DATE(LEFT(A$1,4),MONTH(DATEVALUE(A2&" 1"))+1,1)),0)+1-4)) -> Feb 22 | L2: 1110.39 | M2: =IF(L2<>"",J2-L2,"") -> 83.327992 | N2: =IF(ISREF(INDIRECT("'"&"Wages "&LEFT(A1,4)-1&"'!A1"))=TRUE,INDIRECT(CONCATENATE("'Wages ",LEFT(A1,4)-1,"'!Q13")))+(IF(F2="",D2,F2)) -> 8521.3934
A3: 42737 | B3: 3,4,5,6 | C3: =8.5+8.5+8.5+5 -> 30.5
A4: =A3+7 -> 42744 | B4: 9,10,11,12,13 | C4: =8.5+8.5+8.5+8+8.5 -> 42
A5: =A4+7 -> 42751 | B5: 16,17,18,19,20 | C5: =8.5+6+3+8.5+5 -> 31
A6: =A5+7 -> 42758 | B6: 23,24,26,27 | C6: =8.5+6+8.5+8.5 -> 31.5
A7: FEB | B7: =(IF(B8<>"",((LEN(B8)-LEN(SUBSTITUTE(B8,",","")))+1)))+(IF(B9<>"",((LEN(B9)-LEN(SUBSTITUTE(B9,",","")))+1)))+(IF(B10<>"",((LEN(B10)-LEN(SUBSTITUTE(B10,",","")))+1)))+(IF(B11<>"",((LEN(B11)-LEN(SUBSTITUTE(B11,",","")))+1)))+(IF(B12<>"",((LEN(B12)-LEN(SUBSTITUTE(B12,",","")))+1))) -> 20 | C7: =ROUND(SUM(C8:C12)/9,2)+SUM(C8:C12) -> 135.56 | D7: =C7*B41 -> 1067.9281 | E7: =8.25*C7-D7 -> 50.441876 | G7: =IF(F7="",IF((((D7-H7)/4)-155)>0,((((D7-H7)/4)-155)*0.12)*4,0),IF((((F7-H7)/4)-155)>0,((((F7-H7)/4)-155)*0.12)*4,0)) -> 47.343806 | H7: =IF(B$43<>"N",IF(F7="",D7*0.05,F7*0.05),0) -> 53.396406 | I7: =IF(N7>11000,(D7-(11000-N2))*0.2,0) -> 0 | J7: =IF(F7="",D7-G7-H7,F7-G7-H7) -> 967.18791 | K7: =TEXT(DATE(LEFT(A$1,4),IF(MONTH(DATEVALUE(A7&" 1"))+1>12,1,MONTH(DATEVALUE(A7&" 1"))+1),1),"mmm")&" " &DAY(EOMONTH((DATE(LEFT(A$1,4),MONTH(DATEVALUE(A7&" 1"))+1,1)),0)+1-WEEKDAY(EOMONTH((DATE(LEFT(A$1,4),MONTH(DATEVALUE(A7&" 1"))+1,1)),0)+1-4)) -> Mar 29 | L7: 945.16 | M7: =IF(L7<>"",J7-L7,"") -> 22.027912 | N7: =N2+D7 -> 9589.3216
A8: 42765 | B8: 30,31,2,3 | C8: =8.5+6+8.5 -> 23
A9: =A8+7 -> 42772 | B9: 6,7,8,9,10 | C9: =7.25+6+7.5+7.5 -> 28.25
A10: =A9+7 -> 42779 | C10: 9
A11: =A10+7 -> 42786 | B11: 20,21,22,23,24,25 | C11: =7.5+7.5+4.75+7.5+7.5+3 -> 37.75
A12: 42793 | B12: 27,28,1,2,3 | C12: =7.5+6+3+7.5 -> 24
A13: MAR | B13: =(IF(B14<>"",((LEN(B14)-LEN(SUBSTITUTE(B14,",","")))+1)))+(IF(B15<>"",((LEN(B15)-LEN(SUBSTITUTE(B15,",","")))+1)))+(IF(B16<>"",((LEN(B16)-LEN(SUBSTITUTE(B16,",","")))+1)))+(IF(B17<>"",((LEN(B17)-LEN(SUBSTITUTE(B17,",","")))+1))) -> 20 | C13: =ROUND(SUM(C14:C17)/9,2)+SUM(C14:C17) -> 131.67 | D13: =C13*B41 -> 1037.2831 | E13: =8.25*C13-D13 -> 48.994407 | G13: =IF(F13="",IF((((D13-H13)/4)-155)>0,((((D13-H13)/4)-155)*0.12)*4,0),IF((((F13-H13)/4)-155)>0,((((F13-H13)/4)-155)*0.12)*4,0)) -> 43.850273 | H13: =IF(B$43<>"N",IF(F13="",D13*0.05,F13*0.05),0) -> 51.864155 | I13: =IF(N13>11000,(D13-(11000-N7))*0.2,0) -> 0 | J13: =IF(F13="",D13-G13-H13,F13-G13-H13-I13) -> 941.56867 | K13: =TEXT(DATE(LEFT(A$1,4),IF(MONTH(DATEVALUE(A13&" 1"))+1>12,1,MONTH(DATEVALUE(A13&" 1"))+1),1),"mmm")&" " &DAY(EOMONTH((DATE(LEFT(A$1,4),MONTH(DATEVALUE(A13&" 1"))+1,1)),0)+1-WEEKDAY(EOMONTH((DATE(LEFT(A$1,4),MONTH(DATEVALUE(A13&" 1"))+1,1)),0)+1-4)) -> Apr 26 | L13: 973.15 | M13: =IF(L13<>"",J13-L13,"") -> -31.581334 | N13: =N7+D13 -> 10626.605
A14: =A12+7 -> 42800 | B14: 6,7,8,9,10,11 | C14: =7.5+7.5+3+7.5+5+3.5 -> 34
A15: =A14+7 -> 42807 | B15: 13,14,15,16,17,18 | C15: =7.5+7.5+3+5+7.5+4 -> 34.5
A16: =A15+7 -> 42814 | B16: 20,21,22,23,24 | C16: =7.5+7.5+7.5+5 -> 27.5
A17: =A16+7 -> 42821 | B17: 28,30,31 | C17: =7.5+7.5+7.5 -> 22.5
A18: APR | B18: =(IF(B19<>"",((LEN(B19)-LEN(SUBSTITUTE(B19,",","")))+1)))+(IF(B20<>"",((LEN(B20)-LEN(SUBSTITUTE(B20,",","")))+1)))+(IF(B21<>"",((LEN(B21)-LEN(SUBSTITUTE(B21,",","")))+1)))+(IF(B22<>"",((LEN(B22)-LEN(SUBSTITUTE(B22,",","")))+1))) -> 21 | C18: =ROUND(SUM(C19:C22)/9,2)+SUM(C19:C22) -> 145.28 | D18: =C18*B41 -> 1144.5013 | E18: =8.25*C18-D18 -> 54.058688 | F18: =IF(B42<>0,D18+SUM(E2:E13),0) -> 1299.7526 | G18: =IF(F18="",IF((((D18-H18)/4)-155)>0,((((D18-H18)/4)-155)*0.12)*4,0),IF((((F18-H18)/4)-155)>0,((((F18-H18)/4)-155)*0.12)*4,0)) -> 73.771796 | H18: =IF(B$43<>"N",IF(F18="",D18*0.05,F18*0.05),0) -> 64.98763 | I18: =IF(N18>11000,(D18-(11000-N13))*0.2,0) -> 0 | J18: =IF(F18="",D18-G18-H18-I18,F18-G18-H18-I18) -> 1160.9932 | K18: =TEXT(DATE(LEFT(A$1,4),IF(MONTH(DATEVALUE(A18&" 1"))+1>12,1,MONTH(DATEVALUE(A18&" 1"))+1),1),"mmm")&" " &DAY(EOMONTH((DATE(LEFT(A$1,4),MONTH(DATEVALUE(A18&" 1"))+1,1)),0)+1-WEEKDAY(EOMONTH((DATE(LEFT(A$1,4),MONTH(DATEVALUE(A18&" 1"))+1,1)),0)+1-4)) -> May 31 | L18: 1156.56 | M18: =IF(L18<>"",J18-L18,"") -> 4.4331694 | N18: =IF(F18="",D18,F18) -> 1299.7526 | O18: New tax year
A19: =A17+7 -> 42828 | B19: 3,4,5,6,7,8 | C19: =4+7.5+3+7.5+7.5+5 -> 34.5
A20: =A19+7 -> 42835 | B20: 10,11,12,13,15 | C20: =7.5+7.5+3.75+7.5+5 -> 31.25
A21: =A20+7 -> 42842 | B21: 17,18,19,20,21 | C21: =5+7.5+7.5+7.5 -> 27.5
A22: =A21+7 -> 42849 | B22: 24,25,26,27,28 | C22: =7.5+7.5+7.5+7.5+7.5 -> 37.5
A23: MAY | B23: =(IF(B24<>"",((LEN(B24)-LEN(SUBSTITUTE(B24,",","")))+1)))+(IF(B25<>"",((LEN(B25)-LEN(SUBSTITUTE(B25,",","")))+1)))+(IF(B26<>"",((LEN(B26)-LEN(SUBSTITUTE(B26,",","")))+1)))+(IF(B27<>"",((LEN(B27)-LEN(SUBSTITUTE(B27,",","")))+1)))+(IF(B28<>"",((LEN(B28)-LEN(SUBSTITUTE(B28,",","")))+1))) -> 6 | C23: =ROUND(SUM(C24:C28)/9,2)+SUM(C24:C28) -> 50 | D23: =C23*B41 -> 393.895 | E23: =8.25*C23-D23 -> 18.605 | G23: =IF(F23="",IF((((D23-H23)/4)-155)>0,((((D23-H23)/4)-155)*0.12)*4,0),IF((((F23-H23)/4)-155)>0,((((F23-H23)/4)-155)*0.12)*4,0)) -> 0 | H23: =IF(B$43<>"N",IF(F23="",D23*0.05,F23*0.05),0) -> 19.69475 | I23: =IF(N23>11000,(D23-(11000-N18))*0.2,0) -> 0 | J23: =IF(F23="",D23-G23-H23-I23,F23-G23-H23-I23) -> 374.20025 | K23: =TEXT(DATE(LEFT(A$1,4),IF(MONTH(DATEVALUE(A23&" 1"))+1>12,1,MONTH(DATEVALUE(A23&" 1"))+1),1),"mmm")&" " &DAY(EOMONTH((DATE(LEFT(A$1,4),MONTH(DATEVALUE(A23&" 1"))+1,1)),0)+1-WEEKDAY(EOMONTH((DATE(LEFT(A$1,4),MONTH(DATEVALUE(A23&" 1"))+1,1)),0)+1-4)) -> Jun 28 | L23: 368.55 | M23: =IF(L23<>"",J23-L23,"") -> 5.65025 | N23: =IF(F23="",D23,F23)+N18 -> 1693.6476
A24: =A22+7 -> 42856 | B24: 1,2,3,4,5 | C24: =7.5+7.5+7.5+7.5+7.5 -> 37.5
A25: =A24+7 -> 42863
A26: =A25+7 -> 42870
A27: =A26+7 -> 42877
A28: =A27+7 -> 42884 | B28: 31 | C28: 7.5
A29: JUN | B29: =(IF(B30<>"",((LEN(B30)-LEN(SUBSTITUTE(B30,",","")))+1)))+(IF(B31<>"",((LEN(B31)-LEN(SUBSTITUTE(B31,",","")))+1)))+(IF(B32<>"",((LEN(B32)-LEN(SUBSTITUTE(B32,",","")))+1)))+(IF(B33<>"",((LEN(B33)-LEN(SUBSTITUTE(B33,",","")))+1))) -> 5 | C29: =ROUND(SUM(C30:C33)/9,2)+SUM(C30:C33) -> 38.89 | D29: =C29*B41 -> 306.37153 | E29: =8.25*C29-D29 -> 14.470969 | G29: =IF(F29="",IF((((D29-H29)/4)-155)>0,((((D29-H29)/4)-155)*0.12)*4,0),IF((((F29-H29)/4)-155)>0,((((F29-H29)/4)-155)*0.12)*4,0)) -> 0 | H29: =IF(B$43<>"N",IF(F29="",D29*0.05,F29*0.05),0) -> 15.318577 | I29: =IF(N29>11000,(D29-(11000-N23))*0.2,0) -> 0 | J29: =IF(F29="",D29-G29-H29-I29,F29-G29-H29-I29) -> 291.05295 | K29: =TEXT(DATE(LEFT(A$1,4),IF(MONTH(DATEVALUE(A29&" 1"))+1>12,1,MONTH(DATEVALUE(A29&" 1"))+1),1),"mmm")&" " &DAY(EOMONTH((DATE(LEFT(A$1,4),MONTH(DATEVALUE(A29&" 1"))+1,1)),0)+1-WEEKDAY(EOMONTH((DATE(LEFT(A$1,4),MONTH(DATEVALUE(A29&" 1"))+1,1)),0)+1-4)) -> Jul 26 | L29: 405.41 | M29: =IF(L29<>"",J29-L29,"") -> -114.35705 | N29: =IF(F29="",D29,F29)+N23 -> 2000.0191
A30: =A28+7 -> 42891 | B30: 5,6,7,8,9 | C30: =7.5+7.5+7.5+7.5+5 -> 35
A31: =A30+7 -> 42898
A32: =A31+7 -> 42905
A33: =A32+7 -> 42912
A34: JUL | B34: =(IF(B35<>"",((LEN(B35)-LEN(SUBSTITUTE(B35,",","")))+1)))+(IF(B36<>"",((LEN(B36)-LEN(SUBSTITUTE(B36,",","")))+1)))+(IF(B37<>"",((LEN(B37)-LEN(SUBSTITUTE(B37,",","")))+1)))+(IF(B38<>"",((LEN(B38)-LEN(SUBSTITUTE(B38,",","")))+1))) -> 0 | C34: =ROUND(SUM(C35:C38)/9,2)+SUM(C35:C38) -> 0 | D34: =C34*B41 -> 0 | E34: =8.25*C34-D34 -> 0 | F34: =IF(B42<>0,D34+SUM(E18:E29),0) -> 87.134657 | G34: =IF(F34="",IF((((D34-H34)/4)-155)>0,((((D34-H34)/4)-155)*0.12)*4,0),IF((((F34-H34)/4)-155)>0,((((F34-H34)/4)-155)*0.12)*4,0)) -> 0 | H34: =IF(B$43<>"N",IF(F34="",D34*0.05,F34*0.05),0) -> 4.3567328 | I34: =IF(N34>11000,(D34-(11000-N29))*0.2,0) -> 0 | J34: =IF(F34="",D34-G34-H34-I34,F34-G34-H34-I34) -> 82.777924 | K34: =TEXT(DATE(LEFT(A$1,4),IF(MONTH(DATEVALUE(A34&" 1"))+1>12,1,MONTH(DATEVALUE(A34&" 1"))+1),1),"mmm")&" " &DAY(EOMONTH((DATE(LEFT(A$1,4),MONTH(DATEVALUE(A34&" 1"))+1,1)),0)+1-WEEKDAY(EOMONTH((DATE(LEFT(A$1,4),MONTH(DATEVALUE(A34&" 1"))+1,1)),0)+1-4)) -> Aug 30 | M34: =IF(L34<>"",J34-L34,"") | N34: =IF(F34="",D34,F34)+N29 -> 2087.1538
A35: =A33+7 -> 42919
A36: =A35+7 -> 42926
A37: =A36+7 -> 42933
A38: =A37+7 -> 42940
G39: ="SUM: " & ROUND(SUM(G2:G38),2) -> SUM: 243.2 | H39: ="SUM: " & ROUND(SUM(H2:H38),2) -> SUM: 276.56 | I39: ="SUM: " & ROUND(SUM(I2:I38),2) -> SUM: 0 | J39: ="SUM: " & ROUND(SUM(J2:J38),2) -> SUM: 5011.5 | L39: ="SUM: " & ROUND(SUM(L2:L38),2) -> SUM: 4959.22
A41: Hourly Rate: | B41: 7.8779
A42: Bonus Rate | B42: 8.25
A43: Pension | B43: Y

Sheet Savings 2017
A1: 2017/Month | B1: Amount | D1: monthly
A2: JAN | B2: =IF(ISREF(INDIRECT(CONCATENATE("'",A13,"-",A2," ",RIGHT(YEAR(TODAY())-1,2),"'!B18")))=TRUE,(INDIRECT(CONCATENATE("'Savings ",YEAR(TODAY())-1,"'!B13"))+INDIRECT(CONCATENATE("'",A13,"-",A2," ",RIGHT(YEAR(TODAY())-1,2),"'!B18")))-INDIRECT(CONCATENATE("'",A13,"-",A2," ",RIGHT(YEAR(TODAY())-1,2),"'!B19")),"") -> #REF! | D2: 450
A3: FEB | B3: =IF(ISREF(INDIRECT(CONCATENATE("'",A2,"-",A3," ",RIGHT(YEAR(TODAY()),2),"'!B18")))=TRUE,(B2+INDIRECT(CONCATENATE("'",A2,"-",A3," ",RIGHT(YEAR(TODAY()),2),"'!B18")))-INDIRECT(CONCATENATE("'",A2,"-",A3," ",RIGHT(YEAR(TODAY()),2),"'!B19")),"") -> #REF!
A4: MAR | B4: =IF(ISREF(INDIRECT(CONCATENATE("'",A3,"-",A4," ",RIGHT(YEAR(TODAY()),2),"'!B18")))=TRUE,(B3+INDIRECT(CONCATENATE("'",A3,"-",A4," ",RIGHT(YEAR(TODAY()),2),"'!B18")))-INDIRECT(CONCATENATE("'",A3,"-",A4," ",RIGHT(YEAR(TODAY()),2),"'!B19")),"") -> #REF!
A5: APR | B5: =IF(ISREF(INDIRECT(CONCATENATE("'",A4,"-",A5," ",RIGHT(YEAR(TODAY()),2),"'!B18")))=TRUE,(B4+INDIRECT(CONCATENATE("'",A4,"-",A5," ",RIGHT(YEAR(TODAY()),2),"'!B18")))-INDIRECT(CONCATENATE("'",A4,"-",A5," ",RIGHT(YEAR(TODAY()),2),"'!B19")),"") -> #REF!
A6: MAY | B6: 1072.33
A7: JUN | B7: =IF(ISREF(INDIRECT(CONCATENATE("'",A6,"-",A7," ",LEFT(A$1,4),"'!B32")))=TRUE(),INDIRECT(CONCATENATE("'",A6,"-",A7," ",LEFT(A$1,4),"'!B31"))+B6-INDIRECT(CONCATENATE("'",A6,"-",A7," ",LEFT(A$1,4),"'!B32"))+200,0) -> 1000 | G7: Cash LISA - 0.5% | H7: M&S - 5% to £250 + £185 | I7: First D Saver - 5% to £300 + £100cb | J7: =4605.23 -> 4605.23 | K7: =J7/2 -> 2302.615
A8: JUL | B8: =IF(ISREF(INDIRECT(CONCATENATE("'",A7,"-",A8," ",LEFT(A$1,4),"'!B31")))=TRUE(),INDIRECT(CONCATENATE("'",A7,"-",A8," ",LEFT(A$1,4),"'!B33"))+B7-INDIRECT(CONCATENATE("'",A7,"-",A8," ",LEFT(A$1,4),"'!B34"))+200-301.69,0) -> 2100 | E8: 2017 | F8: Oct | G8: 1 | H8: 1200 | I8: 300 | K8: 2302.62 | L8: 500
A9: AUG | B9: =IF(ISREF(INDIRECT(CONCATENATE("'",A8,"-",A9," ",LEFT(A$1,4),"'!B31")))=TRUE(),INDIRECT(CONCATENATE("'",A8,"-",A9," ",LEFT(A$1,4),"'!B33"))+B8-INDIRECT(CONCATENATE("'",A8,"-",A9," ",LEFT(A$1,4),"'!B34"))+200-301.69,0) -> 0 | F9: Nov | H9: =H8+200 -> 1400 | I9: =I8+300 -> 600 | K9: =K8+L8 -> 2802.62 | L9: 500
A10: SEP | B10: =IF(ISREF(INDIRECT(CONCATENATE("'",A9,"-",A10," ",LEFT(A$1,4),"'!B31")))=TRUE(),INDIRECT(CONCATENATE("'",A9,"-",A10," ",LEFT(A$1,4),"'!B31")))+B19 -> 400 | F10: Dec | H10: =H9+200 -> 1600 | I10: =I9+300 -> 900 | K10: =K9+L9 -> 3302.62 | L10: 500
A11: OCT | E11: 2018 | F11: Jan | H11: =H10+200 -> 1800 | I11: =I10+300 -> 1200 | K11: =K10+L10 -> 3802.62 | L11: 200
A12: NOV | F12: Feb | H12: =H11+200 -> 2000 | I12: =I11+300 -> 1500 | K12: =K11+L11 -> 4002.62 | L12: 500
A13: DEC | F13: Mar | G13: 3999 | H13: =H12+200 -> 2200 | I13: =I12+300 -> 1800 | K13: =K12+L12 -> 4502.62 | L13: 500
E14: NTY | F14: Apr | H14: 200 | I14: 300 | K14: =K13+L13 -> 5002.62 | L14: 500
F15: May | H15: =H14+200 -> 400 | I15: =I14+300 -> 600 | K15: =K14+L14 -> 5502.62 | L15: 500
F16: Jun | H16: =H15+200 -> 600 | I16: =I15+300 -> 900 | K16: =K15+L15 -> 6002.62 | L16: 500
F17: Jul | H17: =H16+200 -> 800 | I17: =I16+300 -> 1200 | K17: =K16+L16 -> 6502.62 | L17: 500
F18: Aug | H18: =H17+200 -> 1000 | I18: =I17+300 -> 1500 | K18: =K17+L17 -> 7002.62 | L18: 500
F19: Sep | H19: =H18+200 -> 1200 | I19: =I18+300 -> 1800 | K19: =K18+L18 -> 7502.62 | L19: 500
F20: Oct | H20: =H19+200 -> 1400 | I20: =I19+300 -> 2100 | K20: =K19+L19 -> 8002.62 | L20: 500
E21: =SUM(G8:G21)+(SUM(G8:G21)*0.25) -> 10000 | F21: Nov | G21: 4000 | H21: =H20+200 -> 1600 | I21: =I20+300 -> 2400 | K21: =K20+L20 -> 8502.62 | L21: 500
F22: Dec | H22: 200 | I22: 300 | K22: =K21+L21 -> 9002.62 | L22: 500
E23: 2019 | F23: Jan | H23: =H22+200 -> 400 | I23: =I22+300 -> 600 | K23: =K22+L22 -> 9502.62 | L23: 500
F24: Feb | H24: =H23+200 -> 600 | I24: =I23+300 -> 900 | K24: =K23+L23 -> 10002.62 | L24: 500
F25: Mar | H25: =H24+200 -> 800 | I25: =I24+300 -> 1200 | K25: =K24+L24 -> 10502.62 | L25: 500
E26: NTY | F26: Apr | H26: =H25+200 -> 1000 | I26: =I25+300 -> 1500 | K26: =K25+L25 -> 11002.62 | L26: 500
F27: May | H27: =H26+200 -> 1200 | I27: =I26+300 -> 1800 | K27: =K26+L26 -> 11502.62 | L27: 500
F28: Jun | H28: =H27+200 -> 1400 | I28: =I27+300 -> 2100 | K28: =K27+L27 -> 12002.62 | L28: 500
E29: =SUM(G8:G29)+(SUM(G8:G29)*0.25) -> 15000 | F29: Jul | G29: 4000 | H29: =H28+200 -> 1600 | I29: =I28+300 -> 2400

Sheet SFE Repayments
A1: Wage | B1: Monthly wage | C1: Weekly wage | D1: UG (9%) | E1: PG (6%) | F1: Total p/m | H1: UG Loan Year | I1: Total Repayment Left
A2: =17*1000 -> 17000 | B2: =A2/12 -> 1416.6667 | C2: =A2/52 -> 326.92308 | D2: =IF(A2>21000,A2-21000,0)*0.09/12 -> 0 | E2: =IF(A2>21000,A2-21000,0)*0.06/12 -> 0 | F2: =D2+E2 -> 0 | H2: Loan year 1 | I2: 10000
A3: 18000 | B3: =A3/12 -> 1500 | C3: =A3/52 -> 346.15385 | D3: =IF(A3>21000,A3-21000,0)*0.09/12 -> 0 | E3: =IF(A3>21000,A3-21000,0)*0.06/12 -> 0 | F3: =D3+E3 -> 0 | H3: Loan year 2 | I3: =(I2-(E$15*12))*1.039 -> 9828.94
A4: 19000 | B4: =A4/12 -> 1583.3333 | C4: =A4/52 -> 365.38462 | D4: =IF(A4>21000,A4-21000,0)*0.09/12 -> 0 | E4: =IF(A4>21000,A4-21000,0)*0.06/12 -> 0 | F4: =D4+E4 -> 0 | H4: Loan year 3 | I4: =(I3-(E$15*12))*1.039 -> 9651.2087
A5: 20000 | B5: =A5/12 -> 1666.6667 | C5: =A5/52 -> 384.61538 | D5: =IF(A5>21000,A5-21000,0)*0.09/12 -> 0 | E5: =IF(A5>21000,A5-21000,0)*0.06/12 -> 0 | F5: =D5+E5 -> 0 | H5: Loan year 4 | I5: =(I4-(E$15*12))*1.039 -> 9466.5458
A6: 21000 | B6: =A6/12 -> 1750 | C6: =A6/52 -> 403.84615 | D6: =IF(A6>21000,A6-21000,0)*0.09/12 -> 0 | E6: =IF(A6>21000,A6-21000,0)*0.06/12 -> 0 | F6: =D6+E6 -> 0 | H6: Loan year 5 | I6: =(I5-(E$15*12))*1.039 -> 9274.6811
A7: 22000 | B7: =A7/12 -> 1833.3333 | C7: =A7/52 -> 423.07692 | D7: =IF(A7>21000,A7-21000,0)*0.09/12 -> 7.5 | E7: =IF(A7>21000,A7-21000,0)*0.06/12 -> 5 | F7: =D7+E7 -> 12.5 | H7: Loan year 6 | I7: =(I6-(E$15*12))*1.039 -> 9075.3336
A8: 23000 | B8: =A8/12 -> 1916.6667 | C8: =A8/52 -> 442.30769 | D8: =IF(A8>21000,A8-21000,0)*0.09/12 -> 15 | E8: =IF(A8>21000,A8-21000,0)*0.06/12 -> 10 | F8: =D8+E8 -> 25 | H8: Loan year 7 | I8: =(I7-(E$15*12))*1.039 -> 8868.2117
A9: 24000 | B9: =A9/12 -> 2000 | C9: =A9/52 -> 461.53846 | D9: =IF(A9>21000,A9-21000,0)*0.09/12 -> 22.5 | E9: =IF(A9>21000,A9-21000,0)*0.06/12 -> 15 | F9: =D9+E9 -> 37.5 | H9: Loan year 8 | I9: =(I8-(E$15*12))*1.039 -> 8653.0119
A10: 25000 | B10: =A10/12 -> 2083.3333 | C10: =A10/52 -> 480.76923 | D10: =IF(A10>21000,A10-21000,0)*0.09/12 -> 30 | E10: =IF(A10>21000,A10-21000,0)*0.06/12 -> 20 | F10: =D10+E10 -> 50 | H10: Loan year 9 | I10: =(I9-(E$15*12))*1.039 -> 8429.4194
A11: 26000 | B11: =A11/12 -> 2166.6667 | C11: =A11/52 -> 500 | D11: =IF(A11>21000,A11-21000,0)*0.09/12 -> 37.5 | E11: =IF(A11>21000,A11-21000,0)*0.06/12 -> 25 | F11: =D11+E11 -> 62.5 | H11: Loan year 10 | I11: =(I10-(E$15*12))*1.039 -> 8197.1067
A12: 27000 | B12: =A12/12 -> 2250 | C12: =A12/52 -> 519.23077 | D12: =IF(A12>21000,A12-21000,0)*0.09/12 -> 45 | E12: =IF(A12>21000,A12-21000,0)*0.06/12 -> 30 | F12: =D12+E12 -> 75 | H12: Loan year 11 | I12: =(I11-(E$15*12))*1.039 -> 7955.7339
A13: 28000 | B13: =A13/12 -> 2333.3333 | C13: =A13/52 -> 538.46154 | D13: =IF(A13>21000,A13-21000,0)*0.09/12 -> 52.5 | E13: =IF(A13>21000,A13-21000,0)*0.06/12 -> 35 | F13: =D13+E13 -> 87.5 | H13: Loan year 12 | I13: =(I12-(E$15*12))*1.039 -> 7704.9475
A14: 29000 | B14: =A14/12 -> 2416.6667 | C14: =A14/52 -> 557.69231 | D14: =IF(A14>21000,A14-21000,0)*0.09/12 -> 60 | E14: =IF(A14>21000,A14-21000,0)*0.06/12 -> 40 | F14: =D14+E14 -> 100 | H14: Loan year 13 | I14: =(I13-(E$15*12))*1.039 -> 7444.3805
A15: 30000 | B15: =A15/12 -> 2500 | C15: =A15/52 -> 576.92308 | D15: =IF(A15>21000,A15-21000,0)*0.09/12 -> 67.5 | E15: =IF(A15>21000,A15-21000,0)*0.06/12 -> 45 | F15: =D15+E15 -> 112.5 | H15: Loan year 14 | I15: =(I14-(E$15*12))*1.039 -> 7173.6513
H16: Loan year 15 | I16: =(I15-(E$15*12))*1.039 -> 6892.3637
H17: Loan year 16 | I17: =(I16-(E$15*12))*1.039 -> 6600.1059
H18: Loan year 17 | I18: =(I17-(E$15*12))*1.039 -> 6296.45
H19: Loan year 18 | I19: =(I18-(E$15*12))*1.039 -> 5980.9516
H20: Loan year 19 | I20: =(I19-(E$15*12))*1.039 -> 5653.1487
H21: Loan year 20 | I21: =(I20-(E$15*12))*1.039 -> 5312.5615
H22: Loan year 21 | I22: =(I21-(E$15*12))*1.039 -> 4958.6914
H23: Loan year 22 | I23: =(I22-(E$15*12))*1.039 -> 4591.0203
H24: Loan year 23 | I24: =(I23-(E$15*12))*1.039 -> 4209.0101
H25: Loan year 24 | I25: =(I24-(E$15*12))*1.039 -> 3812.1015
H26: Loan year 25 | I26: =(I25-(E$15*12))*1.039 -> 3399.7135
H27: Loan year 26 | I27: =(I26-(E$15*12))*1.039 -> 2971.2423
... H33: Loan year 32 | I33: =(I32-(E$15*12))*1.039 -> 25.777063

Sheet Wages 2018
A1: 2018/Month | B1: Days worked | C1: Hours | D1: Gross Pay | E1: Total Bonus | F1: Gross + Bonus | G1: NI (12%) | H1: Pension (5%) | I1: Income Tax (%20) | J1: Net Pay | K1: Payday | L1: Total Paid | M1: Total Missing | N1: Gross sum to date (Tax year)
A2: JAN | B2: =(IF(B3<>"",((LEN(B3)-LEN(SUBSTITUTE(B3,",","")))+1)))+(IF(B4<>"",((LEN(B4)-LEN(SUBSTITUTE(B4,",","")))+1)))+(IF(B5<>"",((LEN(B5)-LEN(SUBSTITUTE(B5,",","")))+1)))+(IF(B6<>"",((LEN(B6)-LEN(SUBSTITUTE(B6,",","")))+1))) -> 0 | C2: =ROUND(SUM(C3:C6)/9,2)+SUM(C3:C6) -> 0 | D2: =C2*B68 -> 0 | E2: =8.25*C2-D2 -> 0 | F2: =IF(ISREF(INDIRECT("'"&"Wages "&LEFT(A1,4)-1&"'!A1"))=TRUE,INDIRECT(CONCATENATE("'Wages ",LEFT(A1,4)-1,"'!G11")) + INDIRECT(CONCATENATE("'Wages ",LEFT(A1,4)-1,"'!G12")) + INDIRECT(CONCATENATE("'Wages ",LEFT(A1,4)-1,"'!G13")) + D2,"") | G2: =IF(F2="",IF((((D2-H2)/4)-155)>0,((((D2-H2)/4)-155)*0.12)*4,0),IF((((F2-H2)/4)-155)>0,((((F2-H2)/4)-155)*0.12)*4,0)) -> 0 | H2: =IF(B$70<>"N",IF(F2="",D2*0.05,F2*0.05),0) -> 0 | I2: =IF(N2>11000,IF(F2="",(D2-11000)*0.2,(F2-11000)*0.2),0) -> 0 | J2: =IF(F2="",D2-G2-H2,F2-G2-H2) -> 0 | K2: =TEXT(DATE(LEFT(A$1,4),IF(MONTH(DATEVALUE(A2&" 1"))+1>12,1,MONTH(DATEVALUE(A2&" 1"))+1),1),"mmm")&" " &DAY(EOMONTH((DATE(LEFT(A$1,4),MONTH(DATEVALUE(A2&" 1"))+1,1)),0)+1-WEEKDAY(EOMONTH((DATE(LEFT(A$1,4),MONTH(DATEVALUE(A2&" 1"))+1,1)),0)+1-4)) -> Feb 28 | N2: =IF(ISREF(INDIRECT("'"&"Wages "&LEFT(A1,4)-1&"'!A1"))=TRUE,INDIRECT(CONCATENATE("'Wages ",LEFT(A1,4)-1,"'!Q13")))+(IF(F2="",D2,F2)) -> 0
A3: =IF(ISREF(INDIRECT("'"&"Wages "&LEFT(A1,4)-1&"'!A1"))=TRUE,INDIRECT(CONCATENATE("'Wages ",LEFT(A1,4)-1,"'!A65"))+7) -> FALSE
A4: =A3+7 -> 7
A5: =A4+7 -> 14
A6: =A5+7 -> 21
A7: FEB | B7: =(IF(B8<>"",((LEN(B8)-LEN(SUBSTITUTE(B8,",","")))+1)))+(IF(B9<>"",((LEN(B9)-LEN(SUBSTITUTE(B9,",","")))+1)))+(IF(B10<>"",((LEN(B10)-LEN(SUBSTITUTE(B10,",","")))+1)))+(IF(B11<>"",((LEN(B11)-LEN(SUBSTITUTE(B11,",","")))+1)))+(IF(B12<>"",((LEN(B12)-LEN(SUBSTITUTE(B12,",","")))+1))) -> 0 | C7: =ROUND(SUM(C8:C12)/9,2)+SUM(C8:C12) -> 0 | D7: =C7*B68 -> 0 | E7: =8.25*C7-D7 -> 0 | G7: =IF(F7="",IF((((D7-H7)/4)-155)>0,((((D7-H7)/4)-155)*0.12)*4,0),IF((((F7-H7)/4)-155)>0,((((F7-H7)/4)-155)*0.12)*4,0)) -> 0 | H7: =IF(B$70<>"N",IF(F7="",D7*0.05,F7*0.05),0) -> 0 | I7: =IF(N7>11000,(D7-(11000-N2))*0.2,0) -> 0 | J7: =IF(F7="",D7-G7-H7,F7-G7-H7) -> 0 | K7: =TEXT(DATE(LEFT(A$1,4),IF(MONTH(DATEVALUE(A7&" 1"))+1>12,1,MONTH(DATEVALUE(A7&" 1"))+1),1),"mmm")&" " &DAY(EOMONTH((DATE(LEFT(A$1,4),MONTH(DATEVALUE(A7&" 1"))+1,1)),0)+1-WEEKDAY(EOMONTH((DATE(LEFT(A$1,4),MONTH(DATEVALUE(A7&" 1"))+1,1)),0)+1-4)) -> Mar 28 | N7: =N2+D7 -> 0
A8: =A6+7 -> 28
A9: =A8+7 -> 35
A10: =A9+7 -> 42
A11: =A10+7 -> 49
A12: =A11+7 -> 56
A13: MAR | B13: =(IF(B14<>"",((LEN(B14)-LEN(SUBSTITUTE(B14,",","")))+1)))+(IF(B15<>"",((LEN(B15)-LEN(SUBSTITUTE(B15,",","")))+1)))+(IF(B16<>"",((LEN(B16)-LEN(SUBSTITUTE(B16,",","")))+1)))+(IF(B17<>"",((LEN(B17)-LEN(SUBSTITUTE(B17,",","")))+1))) -> 0 | C13: =ROUND(SUM(C14:C17)/9,2)+SUM(C14:C17) -> 0 | D13: =C13*B68 -> 0 | E13: =8.25*C13-D13 -> 0 | G13: =IF(F13="",IF((((D13-H13)/4)-155)>0,((((D13-H13)/4)-155)*0.12)*4,0),IF((((F13-H13)/4)-155)>0,((((F13-H13)/4)-155)*0.12)*4,0)) -> 0 | H13: =IF(B$70<>"N",IF(F13="",D13*0.05,F13*0.05),0) -> 0 | I13: =IF(N13>11000,(D13-(11000-N7))*0.2,0) -> 0 | J13: =IF(F13="",D13-G13-H13,F13-G13-H13-I13) -> 0 | K13: =TEXT(DATE(LEFT(A$1,4),IF(MONTH(DATEVALUE(A13&" 1"))+1>12,1,MONTH(DATEVALUE(A13&" 1"))+1),1),"mmm")&" " &DAY(EOMONTH((DATE(LEFT(A$1,4),MONTH(DATEVALUE(A13&" 1"))+1,1)),0)+1-WEEKDAY(EOMONTH((DATE(LEFT(A$1,4),MONTH(DATEVALUE(A13&" 1"))+1,1)),0)+1-4)) -> Apr 25 | N13: =N7+D13 -> 0
A14: =A12+7 -> 63
A15: =A14+7 -> 70
A16: =A15+7 -> 77
A17: =A16+7 -> 84
A18: APR | B18: =(IF(B19<>"",((LEN(B19)-LEN(SUBSTITUTE(B19,",","")))+1)))+(IF(B20<>"",((LEN(B20)-LEN(SUBSTITUTE(B20,",","")))+1)))+(IF(B21<>"",((LEN(B21)-LEN(SUBSTITUTE(B21,",","")))+1)))+(IF(B22<>"",((LEN(B22)-LEN(SUBSTITUTE(B22,",","")))+1))) -> 0 | C18: =ROUND(SUM(C19:C22)/9,2)+SUM(C19:C22) -> 0 | D18: =C18*B68 -> 0 | E18: =8.25*C18-D18 -> 0 | F18: =IF(B69<>0,D18+SUM(E2:E13),0) -> 0 | G18: =IF(F18="",IF((((D18-H18)/4)-155)>0,((((D18-H18)/4)-155)*0.12)*4,0),IF((((F18-H18)/4)-155)>0,((((F18-H18)/4)-155)*0.12)*4,0)) -> 0 | H18: =IF(B$70<>"N",IF(F18="",D18*0.05,F18*0.05),0) -> 0 | I18: =IF(N18>11000,(D18-(11000-N13))*0.2,0) -> 0 | J18: =IF(F18="",D18-G18-H18-I18,F18-G18-H18-I18) -> 0 | K18: =TEXT(DATE(LEFT(A$1,4),IF(MONTH(DATEVALUE(A18&" 1"))+1>12,1,MONTH(DATEVALUE(A18&" 1"))+1),1),"mmm")&" " &DAY(EOMONTH((DATE(LEFT(A$1,4),MONTH(DATEVALUE(A18&" 1"))+1,1)),0)+1-WEEKDAY(EOMONTH((DATE(LEFT(A$1,4),MONTH(DATEVALUE(A18&" 1"))+1,1)),0)+1-4)) -> May 30 | N18: =IF(F18="",D18,F18) -> 0 | O18: New tax year
A19: =A17+7 -> 91
A20: =A19+7 -> 98
A21: =A20+7 -> 105
A22: =A21+7 -> 112
A23: MAY | B23: =(IF(B24<>"",((LEN(B24)-LEN(SUBSTITUTE(B24,",","")))+1)))+(IF(B25<>"",((LEN(B25)-LEN(SUBSTITUTE(B25,",","")))+1)))+(IF(B26<>"",((LEN(B26)-LEN(SUBSTITUTE(B26,",","")))+1)))+(IF(B27<>"",((LEN(B27)-LEN(SUBSTITUTE(B27,",","")))+1)))+(IF(B28<>"",((LEN(B28)-LEN(SUBSTITUTE(B28,",","")))+1))) -> 0 | C23: =ROUND(SUM(C24:C28)/9,2)+SUM(C24:C28) -> 0 | D23: =C23*B68 -> 0 | E23: =8.25*C23-D23 -> 0 | G23: =IF(F23="",IF((((D23-H23)/4)-155)>0,((((D23-H23)/4)-155)*0.12)*4,0),IF((((F23-H23)/4)-155)>0,((((F23-H23)/4)-155)*0.12)*4,0)) -> 0 | H23: =IF(B$70<>"N",IF(F23="",D23*0.05,F23*0.05),0) -> 0 | I23: =IF(N23>11000,(D23-(11000-N18))*0.2,0) -> 0 | J23: =IF(F23="",D23-G23-H23-I23,F23-G23-H23-I23) -> 0 | K23: =TEXT(DATE(LEFT(A$1,4),IF(MONTH(DATEVALUE(A23&" 1"))+1>12,1,MONTH(DATEVALUE(A23&" 1"))+1),1),"mmm")&" " &DAY(EOMONTH((DATE(LEFT(A$1,4),MONTH(DATEVALUE(A23&" 1"))+1,1)),0)+1-WEEKDAY(EOMONTH((DATE(LEFT(A$1,4),MONTH(DATEVALUE(A23&" 1"))+1,1)),0)+1-4)) -> Jun 27 | N23: =IF(F23="",D23,F23)+N18 -> 0
A24: =A22+7 -> 119
A25: =A24+7 -> 126
A26: =A25+7 -> 133
A27: =A26+7 -> 140
A28: =A27+7 -> 147
A29: JUN | B29: =(IF(B30<>"",((LEN(B30)-LEN(SUBSTITUTE(B30,",","")))+1)))+(IF(B31<>"",((LEN(B31)-LEN(SUBSTITUTE(B31,",","")))+1)))+(IF(B32<>"",((LEN(B32)-LEN(SUBSTITUTE(B32,",","")))+1)))+(IF(B33<>"",((LEN(B33)-LEN(SUBSTITUTE(B33,",","")))+1))) -> 0 | C29: =ROUND(SUM(C30:C33)/9,2)+SUM(C30:C33) -> 0 | D29: =C29*B68 -> 0 | E29: =8.25*C29-D29 -> 0 | G29: =IF(F29="",IF((((D29-H29)/4)-155)>0,((((D29-H29)/4)-155)*0.12)*4,0),IF((((F29-H29)/4)-155)>0,((((F29-H29)/4)-155)*0.12)*4,0)) -> 0 | H29: =IF(B$70<>"N",IF(F29="",D29*0.05,F29*0.05),0) -> 0 | I29: =IF(N29>11000,(D29-(11000-N23))*0.2,0) -> 0 | J29: =IF(F29="",D29-G29-H29-I29,F29-G29-H29-I29) -> 0 | K29: =TEXT(DATE(LEFT(A$1,4),IF(MONTH(DATEVALUE(A29&" 1"))+1>12,1,MONTH(DATEVALUE(A29&" 1"))+1),1),"mmm")&" " &DAY(EOMONTH((DATE(LEFT(A$1,4),MONTH(DATEVALUE(A29&" 1"))+1,1)),0)+1-WEEKDAY(EOMONTH((DATE(LEFT(A$1,4),MONTH(DATEVALUE(A29&" 1"))+1,1)),0)+1-4)) -> Jul 25 | N29: =IF(F29="",D29,F29)+N23 -> 0
A30: =A28+7 -> 154
A31: =A30+7 -> 161
A32: =A31+7 -> 168
A33: =A32+7 -> 175
A34: JUL | B34: =(IF(B35<>"",((LEN(B35)-LEN(SUBSTITUTE(B35,",","")))+1)))+(IF(B36<>"",((LEN(B36)-LEN(SUBSTITUTE(B36,",","")))+1)))+(IF(B37<>"",((LEN(B37)-LEN(SUBSTITUTE(B37,",","")))+1)))+(IF(B38<>"",((LEN(B38)-LEN(SUBSTITUTE(B38,",","")))+1))) -> 0 | C34: =ROUND(SUM(C35:C38)/9,2)+SUM(C35:C38) -> 0 | D34: =C34*B68 -> 0 | E34: =8.25*C34-D34 -> 0 | F34: =IF(B69<>0,D34+SUM(E18:E29),0) -> 0 | G34: =IF(F34="",IF((((D34-H34)/4)-155)>0,((((D34-H34)/4)-155)*0.12)*4,0),IF((((F34-H34)/4)-155)>0,((((F34-H34)/4)-155)*0.12)*4,0)) -> 0 | H34: =IF(B$70<>"N",IF(F34="",D34*0.05,F34*0.05),0) -> 0 | I34: =IF(N34>11000,(D34-(11000-N29))*0.2,0) -> 0 | J34: =IF(F34="",D34-G34-H34-I34,F34-G34-H34-I34) -> 0 | K34: =TEXT(DATE(LEFT(A$1,4),IF(MONTH(DATEVALUE(A34&" 1"))+1>12,1,MONTH(DATEVALUE(A34&" 1"))+1),1),"mmm")&" " &DAY(EOMONTH((DATE(LEFT(A$1,4),MONTH(DATEVALUE(A34&" 1"))+1,1)),0)+1-WEEKDAY(EOMONTH((DATE(LEFT(A$1,4),MONTH(DATEVALUE(A34&" 1"))+1,1)),0)+1-4)) -> Aug 29 | N34: =IF(F34="",D34,F34)+N29 -> 0
A35: =A33+7 -> 182
A36: =A35+7 -> 189
A37: =A36+7 -> 196
A38: =A37+7 -> 203
A39: AUG | B39: =(IF(B40<>"",((LEN(B40)-LEN(SUBSTITUTE(B40,",","")))+1)))+(IF(B41<>"",((LEN(B41)-LEN(SUBSTITUTE(B41,",","")))+1)))+(IF(B42<>"",((LEN(B42)-LEN(SUBSTITUTE(B42,",","")))+1)))+(IF(B43<>"",((LEN(B43)-LEN(SUBSTITUTE(B43,",","")))+1)))+(IF(B44<>"",((LEN(B44)-LEN(SUBSTITUTE(B44,",","")))+1))) -> 0 | C39: =ROUND(SUM(C40:C44)/9,2)+SUM(C40:C44) -> 0 | D39: =C39*B68 -> 0 | E39: =8.25*C39-D39 -> 0 | G39: =IF(F39="",IF((((D39-H39)/4)-155)>0,((((D39-H39)/4)-155)*0.12)*4,0),IF((((F39-H39)/4)-155)>0,((((F39-H39)/4)-155)*0.12)*4,0)) -> 0 | H39: =IF(B$70<>"N",IF(F39="",D39*0.05,F39*0.05),0) -> 0 | I39: =IF(N39>11000,(D39-(11000-N34))*0.2,0) -> 0 | J39: =IF(F39="",D39-G39-H39-I39,F39-G39-H39-I39) -> 0 | K39: =TEXT(DATE(LEFT(A$1,4),IF(MONTH(DATEVALUE(A39&" 1"))+1>12,1,MONTH(DATEVALUE(A39&" 1"))+1),1),"mmm")&" " &DAY(EOMONTH((DATE(LEFT(A$1,4),MONTH(DATEVALUE(A39&" 1"))+1,1)),0)+1-WEEKDAY(EOMONTH((DATE(LEFT(A$1,4),MONTH(DATEVALUE(A39&" 1"))+1,1)),0)+1-4)) -> Sep 26 | N39: =IF(F39="",D39,F39)+N34 -> 0
A40: =A38+7 -> 210
A41: =A40+7 -> 217
A42: =A41+7 -> 224
A43: =A42+7 -> 231
A44: =A43+7 -> 238
A45: SEP | B45: =(IF(B46<>"",((LEN(B46)-LEN(SUBSTITUTE(B46,",","")))+1)))+(IF(B47<>"",((LEN(B47)-LEN(SUBSTITUTE(B47,",","")))+1)))+(IF(B48<>"",((LEN(B48)-LEN(SUBSTITUTE(B48,",","")))+1)))+(IF(B49<>"",((LEN(B49)-LEN(SUBSTITUTE(B49,",","")))+1))) -> 0 | C45: =ROUND(SUM(C46:C49)/9,2)+SUM(C46:C49) -> 0 | D45: =C45*B68 -> 0 | E45: =8.25*C45-D45 -> 0 | G45: =IF(F45="",IF((((D45-H45)/4)-155)>0,((((D45-H45)/4)-155)*0.12)*4,0),IF((((F45-H45)/4)-155)>0,((((F45-H45)/4)-155)*0.12)*4,0)) -> 0 | H45: =IF(B$70<>"N",IF(F45="",D45*0.05,F45*0.05),0) -> 0 | I45: =IF(N45>11000,(D45-(11000-N39))*0.2,0) -> 0 | J45: =IF(F45="",D45-G45-H45-I45,F45-G45-H45-I45) -> 0 | K45: =TEXT(DATE(LEFT(A$1,4),IF(MONTH(DATEVALUE(A45&" 1"))+1>12,1,MONTH(DATEVALUE(A45&" 1"))+1),1),"mmm")&" " &DAY(EOMONTH((DATE(LEFT(A$1,4),MONTH(DATEVALUE(A45&" 1"))+1,1)),0)+1-WEEKDAY(EOMONTH((DATE(LEFT(A$1,4),MONTH(DATEVALUE(A45&" 1"))+1,1)),0)+1-4)) -> Oct 31 | N45: =IF(F45="",D45,F45)+N39 -> 0
A46: =A44+7 -> 245
A47: =A46+7 -> 252
A48: =A47+7 -> 259
A49: =A48+7 -> 266
A50: OCT | B50: =(IF(B51<>"",((LEN(B51)-LEN(SUBSTITUTE(B51,",","")))+1)))+(IF(B52<>"",((LEN(B52)-LEN(SUBSTITUTE(B52,",","")))+1)))+(IF(B53<>"",((LEN(B53)-LEN(SUBSTITUTE(B53,",","")))+1)))+(IF(B54<>"",((LEN(B54)-LEN(SUBSTITUTE(B54,",","")))+1))) -> 0 | C50: =ROUND(SUM(C51:C54)/9,2)+SUM(C51:C54) -> 0 | D50: =C50*B68 -> 0 | E50: =8.25*C50-D50 -> 0 | F50: =IF(B69<>0,D50+SUM(E34:E45),0) -> 0 | G50: =IF(F50="",IF((((D50-H50)/4)-155)>0,((((D50-H50)/4)-155)*0.12)*4,0),IF((((F50-H50)/4)-155)>0,((((F50-H50)/4)-155)*0.12)*4,0)) -> 0 | H50: =IF(B$70<>"N",IF(F50="",D50*0.05,F50*0.05),0) -> 0 | I50: =IF(N50>11000,(D50-(11000-N45))*0.2,0) -> 0 | J50: =IF(F50="",D50-G50-H50-I50,F50-G50-H50-I50) -> 0 | K50: =TEXT(DATE(LEFT(A$1,4),IF(MONTH(DATEVALUE(A50&" 1"))+1>12,1,MONTH(DATEVALUE(A50&" 1"))+1),1),"mmm")&" " &DAY(EOMONTH((DATE(LEFT(A$1,4),MONTH(DATEVALUE(A50&" 1"))+1,1)),0)+1-WEEKDAY(EOMONTH((DATE(LEFT(A$1,4),MONTH(DATEVALUE(A50&" 1"))+1,1)),0)+1-4)) -> Nov 28 | N50: =IF(F50="",D50,F50)+N45 -> 0
A51: =A49+7 -> 273
A52: =A51+7 -> 280
A53: =A52+7 -> 287
A54: =A53+7 -> 294
A55: NOV | B55: =(IF(B56<>"",((LEN(B56)-LEN(SUBSTITUTE(B56,",","")))+1)))+(IF(B57<>"",((LEN(B57)-LEN(SUBSTITUTE(B57,",","")))+1)))+(IF(B58<>"",((LEN(B58)-LEN(SUBSTITUTE(B58,",","")))+1)))+(IF(B59<>"",((LEN(B59)-LEN(SUBSTITUTE(B59,",","")))+1)))+(IF(B60<>"",((LEN(B60)-LEN(SUBSTITUTE(B60,",","")))+1))) -> 0 | C55: =ROUND(SUM(C56:C60)/9,2)+SUM(C56:C60) -> 0 | D55: =C55*B68 -> 0 | E55: =8.25*C55-D55 -> 0 | G55: =IF(F55="",IF((((D55-H55)/4)-155)>0,((((D55-H55)/4)-155)*0.12)*4,0),IF((((F55-H55)/4)-155)>0,((((F55-H55)/4)-155)*0.12)*4,0)) -> 0 | H55: =IF(B$70<>"N",IF(F55="",D55*0.05,F55*0.05),0) -> 0 | I55: =IF(N55>11000,(D55-(11000-N50))*0.2,0) -> 0 | J55: =IF(F55="",D55-G55-H55-I55,F55-G55-H55-I55) -> 0 | K55: =TEXT(DATE(LEFT(A$1,4),IF(MONTH(DATEVALUE(A55&" 1"))+1>12,1,MONTH(DATEVALUE(A55&" 1"))+1),1),"mmm")&" " &DAY(EOMONTH((DATE(LEFT(A$1,4),MONTH(DATEVALUE(A55&" 1"))+1,1)),0)+1-WEEKDAY(EOMONTH((DATE(LEFT(A$1,4),MONTH(DATEVALUE(A55&" 1"))+1,1)),0)+1-4)) -> Dec 26 | N55: =IF(F55="",D55,F55)+N50 -> 0
A56: =A54+7 -> 301
A57: =A56+7 -> 308
A58: =A57+7 -> 315
A59: =A58+7 -> 322
A60: =A59+7 -> 329
A61: DEC | B61: =(IF(B62<>"",((LEN(B62)-LEN(SUBSTITUTE(B62,",","")))+1)))+(IF(B63<>"",((LEN(B63)-LEN(SUBSTITUTE(B63,",","")))+1)))+(IF(B64<>"",((LEN(B64)-LEN(SUBSTITUTE(B64,",","")))+1)))+(IF(B65<>"",((LEN(B65)-LEN(SUBSTITUTE(B65,",","")))+1))) -> 0 | C61: =ROUND(SUM(C62:C65)/9,2)+SUM(C62:C65) -> 0 | D61: =C61*B68 -> 0 | E61: =8.25*C61-D61 -> 0 | G61: =IF(F61="",IF((((D61-H61)/4)-155)>0,((((D61-H61)/4)-155)*0.12)*4,0),IF((((F61-H61)/4)-155)>0,((((F61-H61)/4)-155)*0.12)*4,0)) -> 0 | H61: =IF(B$70<>"N",IF(F61="",D61*0.05,F61*0.05),0) -> 0 | I61: =IF(N61>11000,(D61-(11000-N55))*0.2) -> FALSE | J61: =IF(F61="",D61-G61-H61-I61,F61-G61-H61-I61) -> 0 | K61: =TEXT(DATE(LEFT(A$1,4),IF(MONTH(DATEVALUE(A61&" 1"))+1>12,1,MONTH(DATEVALUE(A61&" 1"))+1),1),"mmm")&" " &DAY(EOMONTH((DATE(LEFT(A$1,4),MONTH(DATEVALUE(A61&" 1"))+1,1)),0)+1-WEEKDAY(EOMONTH((DATE(LEFT(A$1,4),MONTH(DATEVALUE(A61&" 1"))+1,1)),0)+1-4)) -> Jan 30 | N61: =IF(F61="",D61,F61)+N55 -> 0
A62: =A60+7 -> 336
A63: =A62+7 -> 343
A64: =A63+7 -> 350
A65: =A64+7 -> 357
G66: ="SUM: " & ROUND(SUM(G2:G61),2) -> SUM: 0 | H66: ="SUM: " & ROUND(SUM(H2:H61),2) -> SUM: 0 | I66: ="SUM: " & ROUND(SUM(I2:I61),2) -> SUM: 0 | J66: ="SUM: " & ROUND(SUM(J2:J61),2) -> SUM: 0 | L66: ="SUM: " & ROUND(SUM(L2:L61),2) -> SUM: 0
A68: Hourly Rate: | B68: 7.7996
A69: Bonus Rate | B69: 8.25
A70: Pension | B70: Y

Sheet LFHA Wages 2017
A1: 2017/Month | B1: Days worked | C1: Sick | D1: Holidays | E1: Hours | F1: Gross Pay | G1: NI (12%) | H1: Pension (1%) | I1: Income Tax (%20) | J1: Net Pay | K1: Payday | L1: Total Paid | M1: Total Missing | N1: Gross sum to date (Tax year)
A2: JAN | B2: =(IF(B3<>"",((LEN(B3)-LEN(SUBSTITUTE(B3,",","")))+1)))+(IF(B4<>"",((LEN(B4)-LEN(SUBSTITUTE(B4,",","")))+1)))+(IF(B5<>"",((LEN(B5)-LEN(SUBSTITUTE(B5,",","")))+1)))+(IF(B6<>"",((LEN(B6)-LEN(SUBSTITUTE(B6,",","")))+1))) -> 0 | E2: =SUM(E3:E6) -> 0 | F2: =E2*B68 -> 0 | G2: =IF((((F2-H2)/4)-155)>0,((((F2-H2)/4)-155)*0.12)*4,0) -> 0 | H2: =IF(B$69<>"N",F2*0.01,0) -> 0 | I2: =IF(N2>11000,(F2-(11000-#REF!))*0.2,0) -> 0 | J2: =IF(F2<>"",F2-G2-H2-I2) -> 0
A3: 42737
A4: =A3+7 -> 42744
A5: =A4+7 -> 42751
A6: =A5+7 -> 42758
A7: FEB | B7: =(IF(B8<>"",((LEN(B8)-LEN(SUBSTITUTE(B8,",","")))+1)))+(IF(B9<>"",((LEN(B9)-LEN(SUBSTITUTE(B9,",","")))+1)))+(IF(B10<>"",((LEN(B10)-LEN(SUBSTITUTE(B10,",","")))+1)))+(IF(B11<>"",((LEN(B11)-LEN(SUBSTITUTE(B11,",","")))+1)))+(IF(B12<>"",((LEN(B12)-LEN(SUBSTITUTE(B12,",","")))+1))) -> 0 | E7: =SUM(E8:E12) -> 0 | F7: =E7*B68 -> 0 | G7: =IF((((F7-H7)/4)-155)>0,((((F7-H7)/4)-155)*0.12)*4,0) -> 0 | H7: =IF(B$69<>"N",F7*0.01,0) -> 0 | I7: =IF(N7>11000,(F7-(11000-N1))*0.2,0) -> 0 | J7: =IF(F7<>"",F7-G7-H7-I7) -> 0 | N7: =IF(F7<>"",F7+N2,0) -> 0
A8: 42765
A9: =A8+7 -> 42772
A10: =A9+7 -> 42779
A11: =A10+7 -> 42786
A12: 42793
A13: MAR | B13: =(IF(B14<>"",((LEN(B14)-LEN(SUBSTITUTE(B14,",","")))+1)))+(IF(B15<>"",((LEN(B15)-LEN(SUBSTITUTE(B15,",","")))+1)))+(IF(B16<>"",((LEN(B16)-LEN(SUBSTITUTE(B16,",","")))+1)))+(IF(B17<>"",((LEN(B17)-LEN(SUBSTITUTE(B17,",","")))+1))) -> 0 | E13: =SUM(E14:E17) -> 0 | F13: =E13*B68 -> 0 | G13: =IF((((F13-H13)/4)-155)>0,((((F13-H13)/4)-155)*0.12)*4,0) -> 0 | H13: =IF(B$69<>"N",F13*0.01,0) -> 0 | I13: =IF(N13>11000,(F13-(11000-N7))*0.2,0) -> 0 | J13: =IF(F13<>"",F13-G13-H13-I13) -> 0 | N13: =IF(F13<>"",F13+N7,0) -> 0
A14: =A12+7 -> 42800
A15: =A14+7 -> 42807
A16: =A15+7 -> 42814
A17: =A16+7 -> 42821
A18: APR | B18: =(IF(B19<>"",((LEN(B19)-LEN(SUBSTITUTE(B19,",","")))+1)))+(IF(B20<>"",((LEN(B20)-LEN(SUBSTITUTE(B20,",","")))+1)))+(IF(B21<>"",((LEN(B21)-LEN(SUBSTITUTE(B21,",","")))+1)))+(IF(B22<>"",((LEN(B22)-LEN(SUBSTITUTE(B22,",","")))+1))) -> 0 | E18: =SUM(E19:E22) -> 0 | F18: =E18*B68 -> 0 | G18: =IF((((F18-H18)/4)-155)>0,((((F18-H18)/4)-155)*0.12)*4,0) -> 0 | H18: =IF(B$69<>"N",F18*0.01,0) -> 0 | I18: =IF(N18>11000,(F18-(11000-N12))*0.2,0) -> 0 | J18: =IF(F18<>"",F18-G18-H18-I18) -> 0 | N18: =IF(F18<>"",F18+N13,0) -> 0 | O18: New tax year
A19: =A17+7 -> 42828
A20: =A19+7 -> 42835
A21: =A20+7 -> 42842
A22: =A21+7 -> 42849
A23: MAY | B23: =(IF(B24<>"",((LEN(B24)-LEN(SUBSTITUTE(B24,",","")))+1)))+(IF(B25<>"",((LEN(B25)-LEN(SUBSTITUTE(B25,",","")))+1)))+(IF(B26<>"",((LEN(B26)-LEN(SUBSTITUTE(B26,",","")))+1)))+(IF(B27<>"",((LEN(B27)-LEN(SUBSTITUTE(B27,",","")))+1)))+(IF(B28<>"",((LEN(B28)-LEN(SUBSTITUTE(B28,",","")))+1))) -> 0 | E23: =SUM(E24:E28) -> 0 | F23: =E23*B68 -> 0 | G23: =IF((((F23-H23)/4)-155)>0,((((F23-H23)/4)-155)*0.12)*4,0) -> 0 | H23: =IF(B$69<>"N",F23*0.01,0) -> 0 | I23: =IF(N23>11000,(F23-(11000-N17))*0.2,0) -> 0 | J23: =IF(F23<>"",F23-G23-H23-I23) -> 0 | N23: =IF(F23<>"",F23+N18,0) -> 0
A24: =A22+7 -> 42856
A25: =A24+7 -> 42863
A26: =A25+7 -> 42870
A27: =A26+7 -> 42877
A28: =A27+7 -> 42884
A29: JUN | B29: =(IF(B30<>"",((LEN(B30)-LEN(SUBSTITUTE(B30,",","")))+1)))+(IF(B31<>"",((LEN(B31)-LEN(SUBSTITUTE(B31,",","")))+1)))+(IF(B32<>"",((LEN(B32)-LEN(SUBSTITUTE(B32,",","")))+1)))+(IF(B33<>"",((LEN(B33)-LEN(SUBSTITUTE(B33,",","")))+1)))-C29-D29 -> 14 | C29: =LEN(B30)-LEN(SUBSTITUTE(UPPER(B30),"S",""))+LEN(B31)-LEN(SUBSTITUTE(UPPER(B31),"S",""))+LEN(B32)-LEN(SUBSTITUTE(UPPER(B32),"S",""))+LEN(B33)-LEN(SUBSTITUTE(UPPER(B33),"S","")) -> 1 | D29: =LEN(B30)-LEN(SUBSTITUTE(UPPER(B30),"H",""))+LEN(B31)-LEN(SUBSTITUTE(UPPER(B31),"H",""))+LEN(B32)-LEN(SUBSTITUTE(UPPER(B32),"H",""))+LEN(B33)-LEN(SUBSTITUTE(UPPER(B33),"H","")) -> 0 | E29: =SUM(E30:E33) -> 112.5 | F29: =E29*B68 -> 1083.375 | G29: =IF((((F29-H29)/4)-155)>0,((((F29-H29)/4)-155)*0.12)*4,0) -> 54.30495 | H29: =IF(B$69<>"N",F29*0.01,0) -> 10.83375 | I29: =IF(N29>11000,(F29-(11000-N23))*0.2,0) -> 0 | J29: ='BRI Wages 2017'!J23 -> 374.20025 | K29: =TEXT(DATE(LEFT(A$1,4),MONTH("1/"&A29),"15"),"dddd") & " 15th " & A29 -> Thursday 15th JUN | N29: =IF(F29<>"",F29+N23,0) -> 1083.375
A30: =A28+7 -> 42891
A31: =A30+7 -> 42898 | B31: 12,13,14,15,16 | E31: =7.5*5 -> 37.5
A32: =A31+7 -> 42905 | B32: S,20,21,22,23 | E32: =7.5*5 -> 37.5
A33: =A32+7 -> 42912 | B33: 26,27,28,29,30 | E33: =7.5*5 -> 37.5
A34: JUL | B34: =(IF(B35<>"",((LEN(B35)-LEN(SUBSTITUTE(B35,",","")))+1)))+(IF(B36<>"",((LEN(B36)-LEN(SUBSTITUTE(B36,",","")))+1)))+(IF(B37<>"",((LEN(B37)-LEN(SUBSTITUTE(B37,",","")))+1)))+(IF(B38<>"",((LEN(B38)-LEN(SUBSTITUTE(B38,",","")))+1)))-C34-D34 -> 18 | C34: =LEN(B35)-LEN(SUBSTITUTE(UPPER(B35),"S",""))+LEN(B36)-LEN(SUBSTITUTE(UPPER(B36),"S",""))+LEN(B37)-LEN(SUBSTITUTE(UPPER(B37),"S",""))+LEN(B38)-LEN(SUBSTITUTE(UPPER(B38),"S","")) -> 0 | D34: =LEN(B35)-LEN(SUBSTITUTE(UPPER(B35),"H",""))+LEN(B36)-LEN(SUBSTITUTE(UPPER(B36),"H",""))+LEN(B37)-LEN(SUBSTITUTE(UPPER(B37),"H",""))+LEN(B38)-LEN(SUBSTITUTE(UPPER(B38),"H","")) -> 2 | E34: =SUM(E35:E38) -> 135 | F34: =E34*B68 -> 1300.05 | G34: =IF((((F34-H34)/4)-155)>0,((((F34-H34)/4)-155)*0.12)*4,0) -> 80.04594 | H34: =IF(B$69<>"N",F34*0.01,0) -> 13.0005 | I34: =IF(N34>11000,(F34-(11000-N28))*0.2,0) -> 0 | J34: =IF(F34<>"",F34-G34-H34-I34)+IF(F29<>"",F29-G29-H29-I29)+'BRI Wages 2017'!J29 -> 2516.2928 | K34: =TEXT(DATE(LEFT(A$1,4),MONTH("1/"&A34),"15"),"dddd") & " 15th " & A34 -> Saturday 15th JUL | N34: =IF(F34<>"",F34+N29,0) -> 2383.425
A35: =A33+7 -> 42919 | B35: 3,4,5,6,7 | E35: =7.5*5 -> 37.5
A36: =A35+7 -> 42926 | B36: 10,11,H,H,14 | E36: =7.5*3 -> 22.5
A37: =A36+7 -> 42933 | B37: 17,18,19,20,21 | E37: =7.5*5 -> 37.5
A38: =A37+7 -> 42940 | B38: 24,25,26,27,28 | E38: =7.5*5 -> 37.5
A39: AUG | B39: =(IF(B40<>"",((LEN(B40)-LEN(SUBSTITUTE(B40,",","")))+1)))+(IF(B41<>"",((LEN(B41)-LEN(SUBSTITUTE(B41,",","")))+1)))+(IF(B42<>"",((LEN(B42)-LEN(SUBSTITUTE(B42,",","")))+1)))+(IF(B43<>"",((LEN(B43)-LEN(SUBSTITUTE(B43,",","")))+1)))+(IF(B44<>"",((LEN(B44)-LEN(SUBSTITUTE(B44,",","")))+1)))-C39-D39 -> 20 | C39: =LEN(B40)-LEN(SUBSTITUTE(UPPER(B40),"S",""))+LEN(B41)-LEN(SUBSTITUTE(UPPER(B41),"S",""))+LEN(B42)-LEN(SUBSTITUTE(UPPER(B42),"S",""))+LEN(B43)-LEN(SUBSTITUTE(UPPER(B43),"S","")) -> 0 | D39: =LEN(B40)-LEN(SUBSTITUTE(UPPER(B40),"H",""))+LEN(B41)-LEN(SUBSTITUTE(UPPER(B41),"H",""))+LEN(B42)-LEN(SUBSTITUTE(UPPER(B42),"H",""))+LEN(B43)-LEN(SUBSTITUTE(UPPER(B43),"H","")) -> 5 | E39: =SUM(E40:E44) -> 150 | F39: =E39*B68 -> 1444.5 | G39: =IF((((F39-H39)/4)-155)>0,((((F39-H39)/4)-155)*0.12)*4,0) -> 97.2066 | H39: =IF(B$69<>"N",F39*0.01,0) -> 14.445 | I39: =IF(N39>11000,(F39-(11000-N34))*0.2,0) -> 0 | J39: =IF(F39<>"",F39-G39-H39-I39)+'BRI Wages 2017'!J34 -> 1415.6263 | K39: =TEXT(DATE(LEFT(A$1,4),MONTH("1/"&A39),"15"),"dddd") & " 15th " & A39 -> Tuesday 15th AUG | N39: =IF(F39<>"",F39+N34,0) -> 3827.925
A40: =A38+7 -> 42947 | B40: 31,1,2,3,4 | E40: =7.5*5 -> 37.5
A41: =A40+7 -> 42954 | B41: 7,8,9,10,11 | E41: =7.5*5 -> 37.5
A42: =A41+7 -> 42961 | B42: 14,15,16,17,18 | E42: =7.5*5 -> 37.5
A43: =A42+7 -> 42968 | B43: H,H,H,H,H
A44: =A43+7 -> 42975 | B44: 28,29,30,31,01 | E44: =7.5*5 -> 37.5
A45: SEP | B45: =(IF(B46<>"",((LEN(B46)-LEN(SUBSTITUTE(B46,",","")))+1)))+(IF(B47<>"",((LEN(B47)-LEN(SUBSTITUTE(B47,",","")))+1)))+(IF(B48<>"",((LEN(B48)-LEN(SUBSTITUTE(B48,",","")))+1)))+(IF(B49<>"",((LEN(B49)-LEN(SUBSTITUTE(B49,",","")))+1))) -> 0 | C45: =LEN(B46)-LEN(SUBSTITUTE(UPPER(B46),"S",""))+LEN(B47)-LEN(SUBSTITUTE(UPPER(B47),"S",""))+LEN(B48)-LEN(SUBSTITUTE(UPPER(B48),"S",""))+LEN(B49)-LEN(SUBSTITUTE(UPPER(B49),"S","")) -> 0 | D45: =LEN(B46)-LEN(SUBSTITUTE(UPPER(B46),"H",""))+LEN(B47)-LEN(SUBSTITUTE(UPPER(B47),"H",""))+LEN(B48)-LEN(SUBSTITUTE(UPPER(B48),"H",""))+LEN(B49)-LEN(SUBSTITUTE(UPPER(B49),"H","")) -> 0 | E45: =SUM(E46:E49) -> 0 | F45: =E45*B68 -> 0 | G45: =IF((((F45-H45)/4)-155)>0,((((F45-H45)/4)-155)*0.12)*4,0) -> 0 | H45: =IF(B$69<>"N",F45*0.01,0) -> 0 | I45: =IF(N45>11000,(F45-(11000-N39))*0.2,0) -> 0 | J45: =IF(F45<>"",F45-G45-H45-I45) -> 0 | K45: =TEXT(DATE(LEFT(A$1,4),MONTH("1/"&A45),"15"),"dddd") & " 15th " & A45 -> Friday 15th SEP | N45: =IF(F45<>"",F45+N39,0) -> 3827.925
A46: =A44+7 -> 42982
A47: =A46+7 -> 42989
A48: =A47+7 -> 42996
A49: =A48+7 -> 43003
A50: OCT | B50: =(IF(B51<>"",((LEN(B51)-LEN(SUBSTITUTE(B51,",","")))+1)))+(IF(B52<>"",((LEN(B52)-LEN(SUBSTITUTE(B52,",","")))+1)))+(IF(B53<>"",((LEN(B53)-LEN(SUBSTITUTE(B53,",","")))+1)))+(IF(B54<>"",((LEN(B54)-LEN(SUBSTITUTE(B54,",","")))+1))) -> 0 | C50: =LEN(B51)-LEN(SUBSTITUTE(UPPER(B51),"S",""))+LEN(B52)-LEN(SUBSTITUTE(UPPER(B52),"S",""))+LEN(B53)-LEN(SUBSTITUTE(UPPER(B53),"S",""))+LEN(B54)-LEN(SUBSTITUTE(UPPER(B54),"S","")) -> 0 | D50: =LEN(B51)-LEN(SUBSTITUTE(UPPER(B51),"H",""))+LEN(B52)-LEN(SUBSTITUTE(UPPER(B52),"H",""))+LEN(B53)-LEN(SUBSTITUTE(UPPER(B53),"H",""))+LEN(B54)-LEN(SUBSTITUTE(UPPER(B54),"H","")) -> 0 | E50: =SUM(E51:E54) -> 0 | F50: =E50*B68 -> 0 | G50: =IF((((F50-H50)/4)-155)>0,((((F50-H50)/4)-155)*0.12)*4,0) -> 0 | H50: =IF(B$69<>"N",F50*0.01,0) -> 0 | I50: =IF(N50>11000,(F50-(11000-N45))*0.2,0) -> 0 | J50: =IF(F50<>"",F50-G50-H50-I50) -> 0 | K50: =TEXT(DATE(LEFT(A$1,4),MONTH("1/"&A50),"15"),"dddd") & " 15th " & A50 -> Sunday 15th OCT | N50: =IF(F50<>"",F50+N45,0) -> 3827.925
A51: =A49+7 -> 43010
A52: =A51+7 -> 43017
A53: =A52+7 -> 43024
A54: =A53+7 -> 43031
A55: NOV | B55: =(IF(B56<>"",((LEN(B56)-LEN(SUBSTITUTE(B56,",","")))+1)))+(IF(B57<>"",((LEN(B57)-LEN(SUBSTITUTE(B57,",","")))+1)))+(IF(B58<>"",((LEN(B58)-LEN(SUBSTITUTE(B58,",","")))+1)))+(IF(B59<>"",((LEN(B59)-LEN(SUBSTITUTE(B59,",","")))+1)))+(IF(B60<>"",((LEN(B60)-LEN(SUBSTITUTE(B60,",","")))+1))) -> 0 | C55: =LEN(B56)-LEN(SUBSTITUTE(UPPER(B56),"S",""))+LEN(B57)-LEN(SUBSTITUTE(UPPER(B57),"S",""))+LEN(B58)-LEN(SUBSTITUTE(UPPER(B58),"S",""))+LEN(B59)-LEN(SUBSTITUTE(UPPER(B59),"S","")) -> 0 | D55: =LEN(B56)-LEN(SUBSTITUTE(UPPER(B56),"H",""))+LEN(B57)-LEN(SUBSTITUTE(UPPER(B57),"H",""))+LEN(B58)-LEN(SUBSTITUTE(UPPER(B58),"H",""))+LEN(B59)-LEN(SUBSTITUTE(UPPER(B59),"H","")) -> 0 | E55: =SUM(E56:E60) -> 0 | F55: =E55*B68 -> 0 | G55: =IF((((F55-H55)/4)-155)>0,((((F55-H55)/4)-155)*0.12)*4,0) -> 0 | H55: =IF(B$69<>"N",F55*0.01,0) -> 0 | I55: =IF(N55>11000,(F55-(11000-N50))*0.2,0) -> 0 | J55: =IF(F55<>"",F55-G55-H55-I55) -> 0 | K55: =TEXT(DATE(LEFT(A$1,4),MONTH("1/"&A55),"15"),"dddd") & " 15th " & A55 -> Wednesday 15th NOV | N55: =IF(F55<>"",F55+N50,0) -> 3827.925
A56: =A54+7 -> 43038
A57: =A56+7 -> 43045
A58: =A57+7 -> 43052
A59: =A58+7 -> 43059
A60: =A59+7 -> 43066
A61: DEC | B61: =(IF(B62<>"",((LEN(B62)-LEN(SUBSTITUTE(B62,",","")))+1)))+(IF(B63<>"",((LEN(B63)-LEN(SUBSTITUTE(B63,",","")))+1)))+(IF(B64<>"",((LEN(B64)-LEN(SUBSTITUTE(B64,",","")))+1)))+(IF(B65<>"",((LEN(B65)-LEN(SUBSTITUTE(B65,",","")))+1))) -> 0 | C61: =LEN(B62)-LEN(SUBSTITUTE(UPPER(B62),"S",""))+LEN(B63)-LEN(SUBSTITUTE(UPPER(B63),"S",""))+LEN(B64)-LEN(SUBSTITUTE(UPPER(B64),"S",""))+LEN(B65)-LEN(SUBSTITUTE(UPPER(B65),"S","")) -> 0 | D61: =LEN(B62)-LEN(SUBSTITUTE(UPPER(B62),"H",""))+LEN(B63)-LEN(SUBSTITUTE(UPPER(B63),"H",""))+LEN(B64)-LEN(SUBSTITUTE(UPPER(B64),"H",""))+LEN(B65)-LEN(SUBSTITUTE(UPPER(B65),"H","")) -> 0 | E61: =SUM(E62:E65) -> 0 | F61: =E61*B68 -> 0 | G61: =IF((((F61-H61)/4)-155)>0,((((F61-H61)/4)-155)*0.12)*4,0) -> 0 | H61: =IF(B$69<>"N",F61*0.01,0) -> 0 | I61: =IF(N61>11000,(F61-(11000-N56))*0.2,0) -> 0 | J61: =IF(F61<>"",F61-G61-H61-I61) -> 0 | K61: =TEXT(DATE(LEFT(A$1,4),MONTH("1/"&A61),"15"),"dddd") & " 15th " & A61 -> Friday 15th DEC | N61: =IF(F61<>"",F61+N55,0) -> 3827.925
A62: =A60+7 -> 43073
A63: =A62+7 -> 43080
A64: =A63+7 -> 43087
A65: =A64+7 -> 43094
G66: ="SUM: " & ROUND(SUM(G2:G61),2) -> SUM: 231.56 | H66: ="SUM: " & ROUND(SUM(H2:H61),2) -> SUM: 38.28 | I66: ="SUM: " & ROUND(SUM(I2:I61),2) -> SUM: 0 | J66: ="SUM: " & ROUND(SUM(J2:J61),2) -> SUM: 4306.12 | L66: ="SUM: " & ROUND(SUM(L2:L61),2) -> SUM: 0
A68: Hourly Rate: | B68: 9.63
A69: Pension | B69: Y
A70: Holiday Days | B70: =30-SUM(D2:D65) -> 23
A71: Sick Days | B71: =30-SUM(C2:C65) -> 29 | D71: Pre tax | E71: =(18772/52)*4 -> 1444 | F71: =(18772/52)*3 -> 1083 | G71: =E71+F71 -> 2527
D72: Post tax | E72: 1337

Sheet Joint Outgoings
B1: Weekly | C1: Monthly | D1: Yearly
A2: Joint | C2: =SUM(C3:C15) -> 1747.99 | D2: =SUM(D3:D15) -> 21216.38 | E2: =A2 -> Joint
A3: Mortgage/Bills | C3: 750 | D3: =C3*12 -> 9000 | E3: =A3 -> Mortgage/Bills
A4: Equity loan | C4: 200 | D4: =C4*12 -> 2400 | E4: =A4 -> Equity loan
A5: Landscape | C5: =ROUND(D5/12,0) -> 8 | D5: 95 | E5: =A5 -> Landscape
A6: Food/Toiletries/Bunnies | B6: 60 | C6: 240 | D6: =B6*52 -> 3120 | E6: =A6 -> Food/Toiletries/Bunnies
A7: Holiday | C7: 225 | D7: =C7*12 -> 2700 | E7: =A7 -> Holiday
A8: Birthday/Christmas Gifts | C8: 125 | D8: =C8*12 -> 1500 | E8: =A8 -> Birthday/Christmas Gifts
A9: Contingency | C9: 100 | D9: =C9*12 -> 1200 | E9: =A9 -> Contingency
A10: Broadband/TV | C10: 35 | D10: =C10*12 -> 420 | E10: =A10 -> Broadband/TV
A11: Home / Content/ life ins. | C11: 40 | D11: =C11*12 -> 480 | E11: =A11 -> Home / Content/ life ins.
A12: TV License | C12: =ROUND(D12/12,0) -> 12 | D12: 145.5 | E12: =A12 -> TV License
A13: NowTV | C13: 0 | D13: =C13*12 -> 0 | E13: =A13 -> NowTV | L13: Spent | O13: Still to come
A14: Onedrive | C14: 7.99 | D14: =C14*12 -> 95.88 | E14: =A14 -> Onedrive | L14: 8703.16 | M14: Completion | O14: 1350 | P14: Door | S14: In
A15: Apple Music | C15: 5 | D15: =C15*12 -> 60 | E15: =A15 -> Apple Music | L15: 230 | M15: Waste disposal | O15: 80 | P15: Aerial | S15: 984.5 | T15: Ins rfd
A16: Kristine | C16: =SUM(C17:C22) -> 88 | D16: =SUM(D17:D22) -> 1056 | E16: =A16 -> Kristine | L16: 320 | M16: Bathroom | O16: 200 | P16: Curtains | S16: 0 | T16: Paul
A17: K Car ins. | C17: =D17/12 -> 0 | D17: 0 | E17: =A17 -> K Car ins.
A18: K car petrol | C18: 0 | D18: 0 | E18: =A18 -> K car petrol
A19: K car vtax. | C19: =D19/12 -> 0 | D19: 0 | E19: =A19 -> K car vtax.
A20: K Other | C20: 60 | D20: =C20*12 -> 720 | E20: =A20 -> K Other | L20: 350 | M20: Jo | O20: 300 | P20: Outdoor | S20: 367.5 | T20: College
A21: Gym | C21: 16 | D21: =C21*12 -> 192 | E21: =A21 -> Gym | L21: 100 | M21: ? | O21: 300 | P21: Chairs | S21: 300 | T21: Wage
A22: K Phone | C22: 12 | D22: =C22*12 -> 144 | E22: =A22 -> K Phone | L22: 50 | M22: ? | O22: 200 | P22: TV unit | S22: 0 | T22: Nectar
A23: Matt | C23: =SUM(C24:C29) -> 351.14 | D23: =SUM(D24:D29) -> 4413.68 | E23: =A23 -> Matt | L23: 150 | M23: ? | P23: Bedside tables | S23: 1000 | T23: Cshbk
A24: M Car ins. | C24: 89.09 | D24: =C24*12 -> 1069.08 | E24: =A24 -> M Car ins. | L24: 273.39 | M24: Coffee table / console | S24: 100 | T24: Cshbk
A25: M Car Petrol | B25: 50 | C25: 200 | D25: =B25*52 -> 2600 | E25: =A25 -> M Car Petrol | L25: 26.62 | M25: ? | S25: 0 | T25: Bonus
A26: M Car service | C26: =D26/12 -> 17.5 | D26: 210 | E26: =A26 -> M Car service | L26: 50 | M26: ? | S26: 0 | T26: Cshbk
A27: M Car v.tax | C27: 27.56 | D27: =C27*12 -> 330.72 | E27: =A27 -> M Car v.tax | L27: 234.99 | M27: Vacuum | S27: =SUM(S15:S26) -> 2752 | T27: Total
A28: Gym | C28: 0 | D28: =C28*12 -> 0 | E28: =A28 -> Gym | L28: 20.99 | M28: Iron
A29: M Phone | C29: 16.99 | D29: =IF(B29<>"",B29*52,C29*12) -> 203.88 | E29: =A29 -> M Phone | L29: 55 | M29: Kettle / toaster | S29: Out
A30: Total costs | C30: =D30/12 -> 2223.8383 | D30: =SUM(D23+D16+D2) -> 26686.06 | E30: =A30 -> Total costs | L30: 38 | M30: Plates / Water jug | S30: =S27-1350 -> 1402 | T30: Door
A31: Total joint Income | C31: =1155+1367 -> 2522 | D31: =C31*12 -> 30264 | E31: =A31 -> Total joint Income | L31: 638 | M31: Couch | S31: =S30-500 -> 902 | T31: Dad
A32: Remaining | C32: =C31-C30 -> 298.16167 | D32: =D31-D30 -> 3577.94 | E32: =A32 -> Remaining | L32: 360 | M32: Floors | S32: =S31-100 -> 802 | T32: Couch
B33: =B1 -> Weekly | C33: =C1 -> Monthly | D33: =D1 -> Yearly | L33: 24.69 | M33: ? | S33: =S32-80 -> 722 | T33: Aerial
L34: 10 | M34: ? | S34: =S33-350 -> 372 | T34: Outdoor set
L35: 16.97 | M35: ? | S35: =S34-200 -> 172 | T35: Curtains
L36: 38 | M36: ? | S36: =S35-300 -> -128 | T36: Chairs
L37: 21.39 | M37: ? | S37: =S36-200 -> -328 | T37: TV unit
L38: 16.25 | M38: ?
L39: 4.08 | M39: ?
L40: 14.97 | M40: ?
L41: 143.78 | M41: Baskets
L42: 44.5 | M42: ?
L43: 35.19 | M43: ?
L44: 90 | M44: ?
L45: 97.95 | M45: Bedding
L46: 29.53 | M46: ?
L47: 468 | M47: Dining table
K48: Net total spend | L48: =SUM(L14:L47) -> 12655.45

Sheet FEB-MAR 2017
A1: MONTH | B1: Monthly Allowance | C1: ="22/02/17" & " - " & "28/02/17" -> 22/02/17 - 28/02/17 | D1: =TEXT(DATEVALUE(RIGHT(C1,8))+1,"dd/mm/yy")& " - "& TEXT(DATEVALUE(RIGHT(C1,8))+7,"dd/mm/yy") -> 01/03/17 - 07/03/17 | E1: =TEXT(DATEVALUE(RIGHT(D1,8))+1,"dd/mm/yy")& " - "& TEXT(DATEVALUE(RIGHT(D1,8))+7,"dd/mm/yy") -> 08/03/17 - 14/03/17 | F1: =TEXT(DATEVALUE(RIGHT(E1,8))+1,"dd/mm/yy")& " - "& TEXT(DATEVALUE(RIGHT(E1,8))+7,"dd/mm/yy") -> 15/03/17 - 21/03/17 | G1: =TEXT(DATEVALUE(RIGHT(F1,8))+1,"dd/mm/yy")& " - "& TEXT(DATEVALUE(RIGHT(F1,8))+7,"dd/mm/yy") -> 22/03/17 - 28/03/17 | H1: Remaining | J1: Overspend
A2: Outgoings | B2: =SUM(B4+B14) -> #REF! | C2: =SUM(C5:C23) -> 281.27 | D2: =SUM(D5:D23) -> 509.79 | E2: =SUM(E5:E23) -> 195.29 | F2: =SUM(F5:F23) -> 123.62 | G2: =SUM(G5:G23) -> 563.23
A4: General | B4: =SUM(B5:B11) -> 392.5 | H4: ="Remaining: £" & SUM(H5:H11) -> Remaining: £-99.77 | J4: =SUM(J5:J11) -> 137.27
A5: Poodini Fund | B5: 95 | C5: 15 | D5: =80+100 -> 180 | H5: =IF(B5<>"",B5-C5-D5-E5-F5-G5,"") -> -100 | I5: =A5 -> Poodini Fund | J5: =IF(H5<0,0-H5,"") -> 100
A6: Car Petrol | B6: =IF(G1="Remaining",17.5*4,17.5*5) -> 87.5 | C6: 30 | D6: 20 | H6: =IF(B6<>"",B6-C6-D6-E6-F6-G6,"") -> 37.5 | I6: =A6 -> Car Petrol | J6: =IF(H6<0,0-H6,"")
A7: Bike petrol | B7: 20 | D7: 20 | H7: =IF(B7<>"",B7-C7-D7-E7-F7-G7,"") -> 0 | I7: =A7 -> Bike petrol | J7: =IF(H7<0,0-H7,"")
A8: House Deposit | B8: 50 | C8: 50 | H8: =IF(B8<>"",B8-C8-D8-E8-F8-G8,"") -> 0 | I8: =A8 -> House Deposit | J8: =IF(H8<0,0-H8,"")
A9: Food | B9: =IF(G1="Remaining",20*4,IF(H1= "Remaining",20* 5,"")) -> 100 | C9: =22.49+6.5 -> 28.99 | D9: =48.4+20 -> 68.4 | E9: 4.09 | F9: 3.3 | G9: =6.06+8.9+12.47+5.06 -> 32.49 | H9: =IF(B9<>"",B9-C9-D9-E9-F9-G9,"") -> -37.27 | I9: =A9 -> Food | J9: =IF(H9<0,0-H9,"") -> 37.27
A10: Gift Fund | B10: 0 | H10: =IF(B10<>"",B10-C10-D10-E10-F10-G10,"") -> 0 | I10: =A10 -> Gift Fund | J10: =IF(H10<0,0-H10,"")
A11: Holiday Fund | B11: 40 | D11: 40 | H11: =IF(B11<>"",B11-C11-D11-E11-F11-G11,"") -> 0 | I11: =A11 -> Holiday Fund | J11: =IF(H11<0,0-H11,"")
A12: Misc | B12: =IF(B28 <> 0,B28-SUM(B5:B11)-B14-B25,0) -> #REF! | C12: =15.99+44.2+16.5+10+39.92 -> 126.61 | D12: =25+11.98+31.5 -> 68.48 | E12: =17.55 -> 17.55 | F12: =18.98+2.7+98.64 -> 120.32 | G12: =450+35.75 -> 485.75 | H12: =IF(B12<>"",B12-C12-D12-E12-F12-G12,"") -> #REF! | I12: Misc | J12: =IF(H12<0,0-H12,"") -> #REF!
J13: =IF(H13<0,0-H13,"")
A14: Direct Debits | B14: =SUM(B15:B23) -> #REF! | H14: ="Remaining: £" & SUM(H15:H23)+J14 -> #REF! | J14: =SUM(J15:J23) -> #REF!
A15: Sky Movies | B15: ='Joint Outgoings'!#REF! -> #REF! | E15: 9.99 | H15: =IF(B15<>"",B15-C15-D15-E15-F15-G15,"") -> #REF! | I15: =A15 -> Sky Movies | J15: =IF(H15<0,0-H15,"") -> #REF!
A16: Spotify | B16: ='Joint Outgoings'!#REF! -> #REF! | E16: 9.99 | H16: =IF(B16<>"",B16-C16-D16-E16-F16-G16,"") -> #REF! | I16: =A16 -> Spotify | J16: =IF(H16<0,0-H16,"") -> #REF!
A17: Phone | B17: ='Joint Outgoings'!C29 -> 16.99 | G17: 44.99 | H17: =IF(B17<>"",B17-C17-D17-E17-F17-G17,"") -> -28 | I17: =A17 -> Phone | J17: =IF(H17<0,0-H17,"") -> 28
A18: Bupa | H18: =IF(B18<>"",B18-C18-D18-E18-F18-G18,"") | I18: =A18 -> Bupa | J18: =IF(H18<0,0-H18,"")
A19: Gym | B19: 17.99 | C19: 17.99 | H19: =IF(B19<>"",B19-C19-D19-E19-F19-G19,"") -> 0 | I19: =A19 -> Gym | J19: =IF(H19<0,0-H19,"")
A20: Onedrive | B20: 7.99 | D20: 7.99 | H20: =IF(B20<>"",B20-C20-D20-E20-F20-G20,"") -> 0 | I20: =A20 -> Onedrive | J20: =IF(H20<0,0-H20,"")
A21: Ring | B21: 104.92 | D21: 104.92 | H21: =IF(B21<>"",B21-C21-D21-E21-F21-G21,"") -> 0 | I21: =A21 -> Ring | J21: =IF(H21<0,0-H21,"")
A22: Car ins. | B22: 153.67 | E22: 153.67 | H22: =IF(B22<>"",B22-C22-D22-E22-F22-G22,"") -> 0 | I22: =A22 -> Car ins. | J22: =IF(H22<0,0-H22,"")
A23: Car v.tax | B23: ='Joint Outgoings'!C25 -> 200 | C23: 12.68 | H23: =IF(B23<>"",B23-C23-D23-E23-F23-G23,"") -> 187.32 | I23: =A23 -> Car v.tax | J23: =IF(H23<0,0-H23,"")
A24: Savings
A25: Savings In | B25: =IF(SUM(C25:G25)<>0,SUM(C25:G25),0) -> 394.08 | G25: 394.08
A26: Savings Out | B26: =IF(SUM(C26:F26)<>0,SUM(C26:G26),0) -> 803.9 | D26: 750 | G26: 53.9
A27: ISA | B27: =IF(SUM(C27:F27)<>0,SUM(C27:F27),0) -> 0
A28: Income | B28: =SUM(C28:G28)+B26 -> 2067.28 | C28: 1115.39 | D28: =40+7.99 -> 47.99 | F28: =100 -> 100 | H28: =ROUND(SUM(H5:H23),2) & " / " & B28 -> #REF!
H29: =IF(ROUND(SUM(H5:H23),2)>0,IF(ROUND(SUM(H5:H23),2)<ROUND(SUMIF(H5:H23,">0"),2),"NOT ENOUGH MONEY",""),"NO MONEY") -> #REF!
A30: Reminders: | B30: =IF(MONTH(TODAY()) = 11, IF(MONTH(A1(RIGHT,3)) = 11, "Bike insurance due",""),"")
B31: =IF(MONTH(TODAY()) = 6, IF(MONTH(A1(RIGHT,3)) = 6, "Bike insurance due",""),"")
A34: Pay after del:

Sheet MAR-APR 2017
A1: MONTH | B1: Monthly Allowance | C1: ="29/03/17" & " - " & "04/04/17" -> 29/03/17 - 04/04/17 | D1: =TEXT(DATEVALUE(RIGHT(C1,8))+1,"dd/mm/yy")& " - "& TEXT(DATEVALUE(RIGHT(C1,8))+7,"dd/mm/yy") -> 05/04/17 - 11/04/17 | E1: =TEXT(DATEVALUE(RIGHT(D1,8))+1,"dd/mm/yy")& " - "& TEXT(DATEVALUE(RIGHT(D1,8))+7,"dd/mm/yy") -> 12/04/17 - 18/04/17 | F1: =TEXT(DATEVALUE(RIGHT(E1,8))+1,"dd/mm/yy")& " - "& TEXT(DATEVALUE(RIGHT(E1,8))+7,"dd/mm/yy") -> 19/04/17 - 25/04/17 | G1: Remaining
A2: Outgoings | C2: =SUM(C5:C21) -> 730.38 | D2: =SUM(D5:D21) -> 68.92 | E2: =SUM(E5:E21) -> 132.27 | F2: =SUM(F5:F21) -> 0
A4: General | B4: =SUM(B5:B10) -> 430 | G4: ="Remaining: £" & ROUND(SUM(G5:G11),2) -> #REF!
A5: Car Petrol | B5: =IF(G1="Remaining",17.5*4,17.5*5) -> 70 | C5: =20+50 -> 70 | G5: =IF(B5<>"",B5-C5-D5-E5-F5,"") -> 0 | H5: =A5 -> Car Petrol
A6: Bike petrol | B6: =IF(G1="Remaining",5*4,5*5) -> 20 | C6: 20 | G6: =IF(B6<>"",B6-C6-D6-E6-F6,"") -> 0 | H6: =A6 -> Bike petrol
A7: Food | B7: 80 | C7: =40+2.31 -> 42.31 | D7: 30 | E7: =3.5+6.81+19 -> 29.31 | G7: =IF(B7<>"",B7-C7-D7-E7-F7,"") -> -21.62 | H7: =A7 -> Food
A8: House Deposit | B8: =100 -> 100 | C8: 100 | G8: =IF(B8<>"",B8-C8-D8-E8-F8,"") -> 0 | H8: =A8 -> House Deposit
A9: Gift Fund | B9: =IF(G1="Remaining",20*4,IF(H1= "Remaining",20* 5,"")) -> 80 | C9: =40+40 -> 80 | E9: =19.99+35 -> 54.99 | G9: =IF(B9<>"",B9-C9-D9-E9-F9,"") -> -54.99 | H9: =A9 -> Gift Fund
A10: Holiday Fund | B10: =IF(G1="Remaining",20*4,IF(H1= "Remaining",20* 5,"")) -> 80 | C10: 80 | G10: =IF(B10<>"",B10-C10-D10-E10-F10,"") -> 0 | H10: =A10 -> Holiday Fund
A11: Misc | B11: =IF(B28 <> 0,B28-B4-B13-B25,0) -> #REF! | C11: =39+10+40+15+50+36+5 -> 195 | D11: 28.93 | E11: =3+24.99+9.99 -> 37.98 | G11: =IF(B11<>"",B11-C11-D11-E11-F11,"") -> #REF! | H11: Misc
A13: Direct debits | B13: =SUM(B14:B22) -> #REF! | G13: ="Remaining: £" & ROUND(SUM(G14:G22),2) -> #REF!
A14: Car ins. | B14: 153.67 | G14: =IF(B14<>"",B14-C14-D14-E14-F14,"") -> 153.67 | H14: =A14 -> Car ins.
A15: Ring | B15: 104.92 | C15: 104.92 | G15: =IF(B15<>"",B15-C15-D15-E15-F15,"") -> 0 | H15: =A15 -> Ring
A16: Phone | B16: ='Joint Outgoings'!C29 -> 16.99 | G16: =IF(B16<>"",B16-C16-D16-E16-F16,"") -> 16.99 | H16: =A16 -> Phone
A17: Gym | B17: 17.99 | C17: 17.99 | G17: =IF(B17<>"",B17-C17-D17-E17-F17,"") -> 0 | H17: =A17 -> Gym
A18: Car v.tax | B18: ='Joint Outgoings'!C25 -> 200 | C18: 12.68 | G18: =IF(B18<>"",B18-C18-D18-E18-F18,"") -> 187.32 | H18: =A18 -> Car v.tax
A19: Sky Movies | B19: ='Joint Outgoings'!#REF! -> #REF! | E19: 9.99 | G19: =IF(B19<>"",B19-C19-D19-E19-F19,"") -> #REF! | H19: =A19 -> Sky Movies
A20: Spotify | B20: ='Joint Outgoings'!#REF! -> #REF! | D20: 9.99 | G20: =IF(B20<>"",B20-C20-D20-E20-F20,"") -> #REF! | H20: =A20 -> Spotify
A21: Onedrive | B21: 7.48 | C21: 7.48 | G21: =IF(B21<>"",B21-C21-D21-E21-F21,"") -> 0 | H21: =A21 -> Onedrive
A22: Amazon Prime | B22: 7.99 | D22: 7.99 | G22: =IF(B22<>"",B22-C22-D22-E22-F22,"") -> 0 | H22: =A22 -> Amazon Prime
A24: Savings
A25: Savings In | B25: =SUM(C25:F25) -> 0
A26: Savings Out | B26: =SUM(C26:F26) -> 0
A27: ISA | B27: =SUM(C27:F27) -> 0
A28: Income Main | B28: =SUM(C28:F28)+B29 -> 1052.36 | C28: =945.16+0.14+55+5 -> 1005.3 | E28: 40 | G28: =SUM(G14:G22)+SUM(G5:G11)& " / " & B28 -> #REF!
A29: MoreThan | B29: 7.06 | G29: =IF(ROUND(SUM(G5:G21),2)>0,IF(ROUND(SUM(G5:G21),2)<ROUND(SUMIF(G5:G21,">0"),2),"NOT ENOUGH MONEY",""),"NO MONEY") -> #REF!
A30: Reminders: | B30: =IF(MONTH(TODAY()) = 11, IF(MONTH(A1(RIGHT,3)) = 11, "Bike insurance due",""),"")
B31: =IF(MONTH(TODAY()) = 6, IF(MONTH(A1(RIGHT,3)) = 6, "Bike insurance due",""),"")
A33: Pay after del:
A36: Owed: | B36: By:
A37: 40 | B37: Mum
A38: 30 | B38: Auntie Jo
A39: =SUM(A37:A38) -> 70

Sheet APR-MAY 2017
A1: MONTH | B1: Monthly Allowance | C1: ="26/04/17" & " - " & "02/05/17" -> 26/04/17 - 02/05/17 | D1: =TEXT(DATEVALUE(RIGHT(C1,8))+1,"dd/mm/yy")& " - "& TEXT(DATEVALUE(RIGHT(C1,8))+7,"dd/mm/yy") -> 03/05/17 - 09/05/17 | E1: =TEXT(DATEVALUE(RIGHT(D1,8))+1,"dd/mm/yy")& " - "& TEXT(DATEVALUE(RIGHT(D1,8))+7,"dd/mm/yy") -> 10/05/17 - 16/05/17 | F1: =TEXT(DATEVALUE(RIGHT(E1,8))+1,"dd/mm/yy")& " - "& TEXT(DATEVALUE(RIGHT(E1,8))+7,"dd/mm/yy") -> 17/05/17 - 23/05/17 | G1: =TEXT(DATEVALUE(RIGHT(F1,8))+1,"dd/mm/yy")& " - "& TEXT(DATEVALUE(RIGHT(F1,8))+7,"dd/mm/yy") -> 24/05/17 - 30/05/17 | H1: Remaining
A2: Outgoings | C2: =SUM(C5:C22) -> 989.81 | D2: =SUM(D5:D22) -> 346.06 | E2: =SUM(E5:E22) -> 0 | F2: =SUM(F5:F22) -> 203.03 | G2: =SUM(G5:G22) -> 113.76
A4: General | B4: =SUM(B5:B10) -> 110 | H4: ="Remaining: £" & SUM(H5:H10) -> Remaining: £-23.04
A5: Car Petrol | B5: 30 | C5: 34.58 | H5: =IF(B5<>"",B5-C5-D5-E5-F5-G5,"") -> -4.58 | I5: =A5 -> Car Petrol | J5: =IF(H5<0,H5*-1) -> 4.58
A6: Bike petrol | B6: 0 | H6: =IF(B6<>"",B6-C6-D6-E6-F6-G6,"") -> 0 | I6: =A6 -> Bike petrol | J6: =IF(H6<0,H6*-1) -> FALSE
A7: House Deposit | B7: 0 | H7: =IF(B7<>"",B7-C7-D7-E7-F7-G7,"") -> 0 | I7: =A7 -> House Deposit | J7: =IF(H7<0,H7*-1) -> FALSE
A8: Food | B8: 40 | C8: =1+6+3.45+5.9+5.3+2 -> 23.65 | D8: =14.08+4.79+7.93 -> 26.8 | H8: =IF(B8<>"",B8-C8-D8-E8-F8-G8,"") -> -10.45 | I8: =A8 -> Food | J8: =IF(H8<0,H8*-1) -> 10.45
A9: Gift Fund | B9: 40 | C9: =10+12.79 -> 22.79 | D9: =4.99+5+15.23 -> 25.22 | H9: =IF(B9<>"",B9-C9-D9-E9-F9-G9,"") -> -8.01 | I9: =A9 -> Gift Fund | J9: =IF(H9<0,H9*-1) -> 8.01
A10: Holiday Fund | B10: 0 | H10: =IF(B10<>"",B10-C10-D10-E10-F10-G10,"") -> 0 | I10: =A10 -> Holiday Fund | J10: =IF(H10<0,H10*-1) -> FALSE
A11: Misc | B11: =IF(B29 <> 0,B29-SUM(B5:B10)-B13-B27-J11,0) -> 1004.99 | C11: =300+70+35.22+14.78+15+82.94+(23.77-12.79)+8.99+4.72+22.98+79.53+35.59 -> 680.73 | D11: =6+19.98+80.74+6.34+(13.03-4.99)+13.99+2.78+2.5 -> 140.37 | F11: =99.99+34.8 -> 134.79 | G11: =17.14+1.25+9.49+1.25+11.59+1.25+28.27+1.99+11.8+29.73 -> 113.76 | H11: =IF(B11<>"",B11-C11-D11-E11-F11-G11,"") -> -64.66 | I11: Misc | J11: =SUM(J5:J9) -> 23.04
A13: Direct Debits | B13: =SUM(B14:B23) -> 590.03 | H13: ="Remaining: £" & SUM(H14:H23) -> Remaining: £140.06
A14: Car ins. | B14: =153.67 -> 153.67 | D14: 153.67 | H14: =IF(B14<>"",B14-C14-D14-E14-F14-G14,"") -> 0 | I14: =A14 -> Car ins.
A15: Ring | B15: 104.92 | C15: 104.92 | H15: =IF(B15<>"",B15-C15-D15-E15-F15-G15,"") -> 0 | I15: =A15 -> Ring
A16: Travel Ins. | B16: 84.48 | C16: 84.48 | H16: =IF(B16<>"",B16-C16-D16-E16-F16-G16,"") -> 0 | I16: =A16 -> Travel Ins.
A17: Phone | B17: ='Joint Outgoings'!C29 -> 16.99 | F17: 46.26 | H17: =IF(B17<>"",B17-C17-D17-E17-F17-G17,"") -> -29.27 | I17: =A17 -> Phone
A18: Gadget Ins. | B18: =IF(MONTH(TODAY())=5,17.99,0) -> 0 | F18: 17.99 | H18: =IF(B18<>"",B18-C18-D18-E18-F18-G18,"") -> -17.99 | I18: =A18 -> Gadget Ins.
A19: Gym | B19: 17.99 | C19: 17.99 | H19: =IF(B19<>"",B19-C19-D19-E19-F19-G19,"") -> 0 | I19: =A19 -> Gym
A20: Car v.tax | B20: ='Joint Outgoings'!C25 -> 200 | C20: 12.68 | H20: =IF(B20<>"",B20-C20-D20-E20-F20-G20,"") -> 187.32 | I20: =A20 -> Car v.tax
A21: Sky Movies | B21: 3.99 | F21: 3.99 | H21: =IF(B21<>"",B21-C21-D21-E21-F21-G21,"") -> 0 | I21: =A21 -> Sky Movies
A22: Onedrive | B22: 7.99 | C22: 7.99 | H22: =IF(B22<>"",B22-C22-D22-E22-F22-G22,"") -> 0 | I22: =A22 -> Onedrive
A23: Amazon Prime | B23: 0 | H23: =IF(B23<>"",B23-C23-D23-E23-F23-G23,"") -> 0 | I23: =A23 -> Amazon Prime
A24: Xbox live | I24: =A24 -> Xbox live
A26: Savings
A27: Savings In | B27: =IF(SUM(C27:G27)<>0,SUM(C27:G27),0) -> 255.91 | G27: =250+5.91 -> 255.91
A28: Savings Out | B28: =IF(SUM(C28:G28)<>0,SUM(C28:G28),0) -> 855 | C28: =255+100 -> 355 | D28: 500
A29: Income | B29: =SUM(C29:G29)+B28 -> 1983.97 | C29: =1042.21+8.45+12.99+20.78+12.49 -> 1096.92 | D29: 7.99 | E29: 14.61 | G29: 9.45 | H29: =ROUND(SUMIF(H5:H28,">0"),2) & " / " & B29 -> 187.32 / 1983.97
A30: Reminders: | B30: =IF(MONTH(TODAY()) = 11, IF(MONTH(A1(RIGHT,3)) = 11, "Bike insurance due",""),"")
B31: =IF(MONTH(TODAY()) = 6, IF(MONTH(A1(RIGHT,3)) = 6, "Bike insurance due",""),"")
A34: Pay after del:

Sheet MAY-JUN 2017
A1: 2017/JUN | B1: Monthly Allowance | C1: ="31/05/17" & " - " & "06/06/17" -> 31/05/17 - 06/06/17 | D1: =TEXT(DATEVALUE(RIGHT(C1,8))+1,"dd/mm/yy")& " - "& TEXT(DATEVALUE(RIGHT(C1,8))+7,"dd/mm/yy") -> 07/06/17 - 13/06/17 | E1: =TEXT(DATEVALUE(RIGHT(D1,8))+1,"dd/mm/yy")& " - "& TEXT(DATEVALUE(RIGHT(D1,8))+7,"dd/mm/yy") -> 14/06/17 - 20/06/17 | F1: =TEXT(DATEVALUE(RIGHT(E1,8))+1,"dd/mm/yy")& " - "& TEXT(DATEVALUE(RIGHT(E1,8))+7,"dd/mm/yy") -> 21/06/17 - 27/06/17 | G1: Remaining
A2: Outgoings | C2: =SUM(C5:C21) -> 517.49 | D2: =SUM(D5:D21) -> 174.45 | E2: =SUM(E5:E21) -> 416.53 | F2: =SUM(F5:F21) -> 243.61
A4: General | B4: =SUM(B5:B10) -> 504.61 | G4: ="Remaining: £" & ROUND(SUM(G5:G11),2) -> Remaining: £194.24
A5: Car Petrol | B5: =IF(G1="Remaining",25*4,25*5) -> 100 | C5: 5 | D5: 50.64 | E5: =25+35 -> 60 | F5: 50 | G5: =IF(B5<>"",B5-C5-D5-E5-F5,"") -> -65.64 | H5: =A5 -> Car Petrol
A6: Bike petrol | B6: 10 | G6: =IF(B6<>"",B6-C6-D6-E6-F6,"") -> 10 | H6: =A6 -> Bike petrol
A7: Food | B7: =IF(G1="Remaining",40*4,IF(H1= "Remaining",40* 5,""))+34.61 -> 194.61 | C7: =38.99+30 -> 68.99 | D7: =5.3+2.31+10.14+0.9+12.62+18.35 -> 49.62 | E7: =10+9.48+5.88+4.2 -> 29.56 | F7: =16 -> 16 | G7: =IF(B7<>"",B7-C7-D7-E7-F7,"") -> 30.44 | H7: =A7 -> Food
A8: Gift Fund | B8: =IF(G1="Remaining",20*4,IF(H1= "Remaining",20* 5,"")) -> 80 | C8: =17.99+12 -> 29.99 | E8: 50 | G8: =IF(B8<>"",B8-C8-D8-E8-F8,"") -> 0.01 | H8: =A8 -> Gift Fund
A9: Holiday Fund | B9: 80 | E9: 80 | G9: =IF(B9<>"",B9-C9-D9-E9-F9,"") -> 0 | H9: =A9 -> Holiday Fund
A10: Horse riding | B10: =IF(G1="Remaining",10*4,IF(H1= "Remaining",10* 5,"")) -> 40 | D10: 40 | G10: =IF(B10<>"",B10-C10-D10-E10-F10,"") -> 0 | H10: =A10 -> Horse riding
A11: Misc | B11: =IF(B33 <> 0,B33-B4-B13-B23-B31,0) -> 829.55 | C11: =19.99+160+0.98+54.99+2.49+10+3.99+6.99 -> 259.43 | D11: =2.4+16.5+7.3 -> 26.2 | E11: =153.67+30+8.06+1.25 -> 192.98 | F11: =16.01+10.5+105 -> 131.51 | G11: =IF(B11<>"",B11-C11-D11-E11-F11,"") -> 219.43 | H11: Misc
A13: Monthly Debits | B13: =SUM(B14:B21) -> 212.32 | G13: ="Remaining: £" & ROUND(SUM(G14:G21),2) -> Remaining: £0.16
A14: House | B14: 0 | G14: =IF(B14<>"",B14-C14-D14-E14-F14,"") -> 0 | H14: =A14 -> House
A15: Ring | B15: 104.92 | C15: 104.92 | G15: =IF(B15<>"",B15-C15-D15-E15-F15,"") -> 0 | H15: =A15 -> Ring
A16: Phone | B16: =46.26 -> 46.26 | F16: 46.1 | G16: =IF(B16<>"",B16-C16-D16-E16-F16,"") -> 0.16 | H16: =A16 -> Phone
A17: Gym | B17: 17.99 | C17: 17.99 | G17: =IF(B17<>"",B17-C17-D17-E17-F17,"") -> 0 | H17: =A17 -> Gym
A18: Gadget Ins. | B18: 17.99 | C18: 17.99 | G18: =IF(B18<>"",B18-C18-D18-E18-F18,"") -> 0 | H18: =A18 -> Gadget Ins.
A19: Car v.tax | B19: 13.18 | C19: 13.18 | G19: =IF(B19<>"",B19-C19-D19-E19-F19,"") -> 0 | H19: =A19 -> Car v.tax
A20: Sky Movies | B20: 3.99 | E20: 3.99 | G20: =IF(B20<>"",B20-C20-D20-E20-F20,"") -> 0 | H20: =A20 -> Sky Movies
A21: Onedrive | B21: 7.99 | D21: 7.99 | G21: =IF(B21<>"",B21-C21-D21-E21-F21,"") -> 0 | H21: =A21 -> Onedrive
A23: Yearly Debits | B23: =SUM(B24:B28) -> 189 | G23: ="Remaining: £" & ROUND(SUM(G24:G28),2) -> Remaining: £-155
A24: Amazon Prime | B24: =IF(MONTH(TODAY())<>6,ROUND(80/12,0),39) -> 7 | C24: 39 | G24: =IF(B24<>"",B24-C24-D24-E24-F24,"") -> -32 | H24: =A24 -> Amazon Prime
A25: Travel Ins. | B25: =IF(MONTH(TODAY())<>5,ROUND(85/12,0),85) -> 7 | G25: =IF(B25<>"",B25-C25-D25-E25-F25,"") -> 7 | H25: =A25 -> Travel Ins.
A26: Car Ins. | B26: =IF(MONTH(TODAY())<>6,ROUND(1500/12,0),0) -> 125 | G26: =IF(B26<>"",B26-C26-D26-E26-F26,"") -> 125 | H26: =A26 -> Car Ins.
A27: Car v.tax | B27: =IF(MONTH(TODAY())<>6,ROUND(305/12,0),305) -> 25 | D27: 305 | G27: =IF(B27<>"",B27-C27-D27-E27-F27,"") -> -280 | H27: =A27 -> Car v.tax
A28: Bike Ins. | B28: =IF(MONTH(TODAY())<>11,ROUND(300/12,0),300) -> 25 | G28: =IF(B28<>"",B28-C28-D28-E28-F28,"") -> 25 | H28: =A28 -> Bike Ins.
A30: Savings | B30: ="£"& B31 & " / " & "£" &B32 -> £0 / £272.33
A31: Savings In | B31: =SUM(C31:F31) -> 0
A32: Savings Out | B32: =SUM(C32:F32) -> 272.33 | E32: =50+36.04+86.29 -> 172.33 | F32: 100
A33: Income | B33: =SUM(C33:F33)+B32-B31 -> 1735.48 | C33: =1385.55+17.99 -> 1403.54 | D33: 25 | E33: =34.61 -> 34.61 | G33: =ROUND(SUM(G5:G28),2) & " / " & B33 -> 39.4 / 1735.48
G34: =IF(ROUND(SUM(G5:G21),2)>0,IF(ROUND(SUM(G5:G21),2)<ROUND(SUMIF(G5:G21,">0"),2),"NOT ENOUGH MONEY",""),"NO MONEY") -> NOT ENOUGH MONEY
A35: Reminders: | B35: =IF(MONTH(TODAY()) = 11, IF(MONTH(DATEVALUE(RIGHT(A1,3)&" 1"))=11, "Bike insurance due",""),"")
B36: =IF(MONTH(TODAY()) = 6, IF(MONTH(DATEVALUE(RIGHT(A1,3)&" 1"))=6, "Car insurance due",""),"")
B37: =IF(MONTH(TODAY()) = 5, IF(MONTH(DATEVALUE(RIGHT(A1,3)&" 1"))=5, "Travel insurance due",""),"")
B38: =IF(MONTH(TODAY()) = 6, IF(MONTH(DATEVALUE(RIGHT(A1,3)&" 1"))=6, "Amazon Prime",""),"")
B39: =IF(MONTH(TODAY()) = 6, IF(MONTH(DATEVALUE(RIGHT(A1,3)&" 1"))=6, "Car vehicle tax",""),"")

Sheet JAN-FEB 2017
A1: MONTH | B1: Monthly Allowance | C1: ="25/01/17" & " - " & "31/01/17" -> 25/01/17 - 31/01/17 | D1: =TEXT(DATEVALUE(RIGHT(C1,8))+1,"dd/mm/yy")& " - "& TEXT(DATEVALUE(RIGHT(C1,8))+7,"dd/mm/yy") -> 01/02/17 - 07/02/17 | E1: =TEXT(DATEVALUE(RIGHT(D1,8))+1,"dd/mm/yy")& " - "& TEXT(DATEVALUE(RIGHT(D1,8))+7,"dd/mm/yy") -> 08/02/17 - 14/02/17 | F1: =TEXT(DATEVALUE(RIGHT(E1,8))+1,"dd/mm/yy")& " - "& TEXT(DATEVALUE(RIGHT(E1,8))+7,"dd/mm/yy") -> 15/02/17 - 21/02/17 | G1: Remaining
A2: Outgoings | C2: =SUM(C5:C23) -> 682 | D2: =SUM(D5:D23) -> 474.11 | E2: =SUM(E5:E23) -> 118.66 | F2: =SUM(F5:F23) -> 119.33
A4: General | B4: =SUM(B5:B11) -> #REF! | G4: ="Remaining: £" & ROUND(SUM(G5:G12),2) -> #REF!
A5: Poodini Fund | B5: =IF(G1="Remaining",'Joint Outgoings'!B3*4,IF(H1= "Remaining",'Joint Outgoings'!B3* 5,"")) -> 0 | C5: 300 | D5: 20 | G5: =IF(B5<>"",B5-C5-D5-E5-F5,"") -> -320 | H5: =A5 -> Poodini Fund
A6: Car Petrol | B6: =IF(G1="Remaining",'Joint Outgoings'!B24*4,IF(H1= "Remaining",'Joint Outgoings'!B24* 5,"")) -> 0 | C6: 30.5 | E6: 33.19 | G6: =IF(B6<>"",B6-C6-D6-E6-F6,"") -> -63.69 | H6: =A6 -> Car Petrol
A7: Bike petrol | B7: =IF(G1="Remaining",'Joint Outgoings'!#REF!*2,IF(H1= "Remaining",'Joint Outgoings'!#REF!* 2,"")) -> #REF! | C7: 9.2 | G7: =IF(B7<>"",B7-C7-D7-E7-F7,"") -> #REF! | H7: =A7 -> Bike petrol
A8: Food | B8: =IF(G1="Remaining",20*4,IF(H1= "Remaining",20* 5,"")) -> 80 | C8: =16.27+2.65+3.85+4.51+17.6+6.65 -> 51.53 | D8: =1.21+2+0.8 -> 4.01 | E8: =2.7+2.55+2+16.5+9.98 -> 33.73 | F8: 9.47 | G8: =IF(B8<>"",B8-C8-D8-E8-F8,"") -> -18.74 | H8: =A8 -> Food
A9: House Deposit | G9: =IF(B9<>"",B9-C9-D9-E9-F9,"") | H9: =A9 -> House Deposit
A10: Gift Fund | B10: 0 | G10: =IF(B10<>"",B10-C10-D10-E10-F10,"") -> 0 | H10: =A10 -> Gift Fund
A11: Holiday Fund | B11: 0 | D11: =0.78+37.97+22.05+52.14 -> 112.94 | G11: =IF(B11<>"",B11-C11-D11-E11-F11,"") -> -112.94 | H11: =A11 -> Holiday Fund
A12: Misc | B12: =IF(B29 <> 0,B29-B4-B14-B26,0) -> #REF! | C12: =88+88.3+29.98+27.95+35.56+2.99 -> 272.78 | D12: =15+16+29.9 -> 60.9 | E12: =10+41.74 -> 51.74 | F12: =22.96+11.05+7.75+6.82+3+12 -> 63.58 | G12: =IF(B12<>"",B12-C12-D12-E12-F12,"") -> #REF! | H12: Misc
A14: Direct debits | B14: =SUM(B15:B23) -> #REF! | G14: ="Remaining: £" & ROUND(SUM(G15:G23),2) -> #REF!
A15: Sky Movies | B15: ='Joint Outgoings'!#REF! -> #REF! | F15: 9.99 | G15: =IF(B15<>"",B15-C15-D15-E15-F15,"") -> #REF! | H15: =A15 -> Sky Movies
A16: Spotify | B16: ='Joint Outgoings'!#REF! -> #REF! | D16: 4.99 | G16: =IF(B16<>"",B16-C16-D16-E16-F16,"") -> #REF! | H16: =A16 -> Spotify
A17: Phone | B17: ='Joint Outgoings'!C29 -> 16.99 | G17: =IF(B17<>"",B17-C17-D17-E17-F17,"") -> 16.99 | H17: =A17 -> Phone
A18: Bupa | B18: ='Joint Outgoings'!#REF! -> #REF! | F18: 36.29 | G18: =IF(B18<>"",B18-C18-D18-E18-F18,"") -> #REF! | H18: =A18 -> Bupa
A19: Gym | B19: 17.99 | C19: 17.99 | G19: =IF(B19<>"",B19-C19-D19-E19-F19,"") -> 0 | H19: =A19 -> Gym
A20: Onedrive | B20: 7.99 | G20: =IF(B20<>"",B20-C20-D20-E20-F20,"") -> 7.99 | H20: =A20 -> Onedrive
A21: Ring | B21: 104.92 | D21: 104.92 | G21: =IF(B21<>"",B21-C21-D21-E21-F21,"") -> 0 | H21: =A21 -> Ring
A22: Car ins. | B22: 153.67 | D22: 153.67 | G22: =IF(B22<>"",B22-C22-D22-E22-F22,"") -> 0 | H22: =A22 -> Car ins.
A23: Car v.tax | B23: ='Joint Outgoings'!C25 -> 200 | D23: 12.68 | G23: =IF(B23<>"",B23-C23-D23-E23-F23,"") -> 187.32 | H23: =A23 -> Car v.tax
A25: Savings
A26: Savings In | B26: =SUM(C26:F26) -> 3000 | C26: 3000
A27: Savings Out | B27: =SUM(C27:F27) -> 0
A28: ISA | B28: =SUM(C28:F28) -> 0
A29: Income | B29: =SUM(C29:F29) -> 4372.05 | C29: =132.49+3300+798.12 -> 4230.61 | D29: =33.5+15.43+26.52 -> 75.45 | E29: =14.43+9.98+41.58 -> 65.99 | G29: =SUM(G5:G23) & " / " & B29 -> #REF!
G30: =IF(ROUND(SUM(G5:G23),2)>0,IF(ROUND(SUM(G5:G23),2)<ROUND(SUMIF(G5:G23,">0"),2),"NOT ENOUGH MONEY",""),"NO MONEY") -> #REF!
A31: Reminders: | B31: =IF(MONTH(TODAY()) = 11, IF(MONTH(A1(RIGHT,3)) = 11, "Bike insurance due",""),"")
B32: =IF(MONTH(TODAY()) = 6, IF(MONTH(A1(RIGHT,3)) = 6, "Bike insurance due",""),"")
A34: Pay after del:

Sheet Birthdays 2016
A1: Birthdays / Card 2016 | B1: Date | D1: Age | E1: Gift Value | F1: Ideas | G1: Done? | H1: Spent | I1: Remaining | J1: Time
A3: Auntie Helen | B3: 22573 | C3: =TEXT(B3,"MMDD") -> 1019 | D3: =DATEDIF(B3,NOW(),"y") -> 64 | E3: 10 | F3: Choc,glut.free | G3: Y | H3: 5 | I3: =IF(E3<>"/",E3-H3,"") -> 5 | J3: =IF(TEXT(TODAY(),"YYYY")=RIGHT(A$1,4), IF(ISERROR(DATEDIF(TEXT(TODAY(),"dd/mm/yyyy"),TEXT(B3,"dd/mm/")&RIGHT(A$1,4),"d")),IF(G3="Y","DONE","MISSED"), IF(DATEDIF(TEXT(TODAY(),"dd/mm/yyyy"),TEXT(B3,"dd/mm/")&RIGHT(A$1,4),"d") = 0,"TODAY!!!", IF(DATEDIF(TEXT(TODAY(),"dd/mm/yyyy"),TEXT(B3,"dd/mm/")&RIGHT(A$1,4),"d") > 0, DATEDIF(TEXT(TODAY(),"dd/mm/yyyy"), TEXT(B3,"dd/mm/")&RIGHT(A$1,4),"d")&" Days to go!",""))),"")
A4: Grandma | B4: 11252 | C4: =TEXT(B4,"MMDD") -> 1021 | D4: =DATEDIF(B4,NOW(),"y") -> 95 | E4: 20 | F4: Cup and saucer | G4: Y | H4: 15 | I4: =IF(E4<>"/",E4-H4,"") -> 5 | J4: =IF(TEXT(TODAY(),"YYYY")=RIGHT(A$1,4), IF(ISERROR(DATEDIF(TEXT(TODAY(),"dd/mm/yyyy"),TEXT(B4,"dd/mm/")&RIGHT(A$1,4),"d")),IF(G4="Y","DONE","MISSED"), IF(DATEDIF(TEXT(TODAY(),"dd/mm/yyyy"),TEXT(B4,"dd/mm/")&RIGHT(A$1,4),"d") = 0,"TODAY!!!", IF(DATEDIF(TEXT(TODAY(),"dd/mm/yyyy"),TEXT(B4,"dd/mm/")&RIGHT(A$1,4),"d") > 0, DATEDIF(TEXT(TODAY(),"dd/mm/yyyy"), TEXT(B4,"dd/mm/")&RIGHT(A$1,4),"d")&" Days to go!",""))),"")
A5: Daniel | B5: 33172 | C5: =TEXT(B5,"MMDD") -> 1026 | D5: =DATEDIF(B5,NOW(),"y") -> 35 | E5: / | I5: =IF(E5<>"/",E5-H5,"") | J5: =IF(TEXT(TODAY(),"YYYY")=RIGHT(A$1,4), IF(ISERROR(DATEDIF(TEXT(TODAY(),"dd/mm/yyyy"),TEXT(B5,"dd/mm/")&RIGHT(A$1,4),"d")),IF(G5="Y","DONE","MISSED"), IF(DATEDIF(TEXT(TODAY(),"dd/mm/yyyy"),TEXT(B5,"dd/mm/")&RIGHT(A$1,4),"d") = 0,"TODAY!!!", IF(DATEDIF(TEXT(TODAY(),"dd/mm/yyyy"),TEXT(B5,"dd/mm/")&RIGHT(A$1,4),"d") > 0, DATEDIF(TEXT(TODAY(),"dd/mm/yyyy"), TEXT(B5,"dd/mm/")&RIGHT(A$1,4),"d")&" Days to go!",""))),"")
A6: Philippa | B6: 34280 | C6: =TEXT(B6,"MMDD") -> 1107 | D6: =DATEDIF(B6,NOW(),"y") -> 32 | E6: / | G6: y | I6: =IF(E6<>"/",E6-H6,"") | J6: =IF(TEXT(TODAY(),"YYYY")=RIGHT(A$1,4), IF(ISERROR(DATEDIF(TEXT(TODAY(),"dd/mm/yyyy"),TEXT(B6,"dd/mm/")&RIGHT(A$1,4),"d")),IF(G6="Y","DONE","MISSED"), IF(DATEDIF(TEXT(TODAY(),"dd/mm/yyyy"),TEXT(B6,"dd/mm/")&RIGHT(A$1,4),"d") = 0,"TODAY!!!", IF(DATEDIF(TEXT(TODAY(),"dd/mm/yyyy"),TEXT(B6,"dd/mm/")&RIGHT(A$1,4),"d") > 0, DATEDIF(TEXT(TODAY(),"dd/mm/yyyy"), TEXT(B6,"dd/mm/")&RIGHT(A$1,4),"d")&" Days to go!",""))),"")
A7: Wayne | B7: 42684 | C7: =TEXT(B7,"MMDD") -> 1110 | D7: =DATEDIF(B7,NOW(),"y") -> 9 | E7: / | I7: =IF(E7<>"/",E7-H7,"") | J7: =IF(TEXT(TODAY(),"YYYY")=RIGHT(A$1,4), IF(ISERROR(DATEDIF(TEXT(TODAY(),"dd/mm/yyyy"),TEXT(B7,"dd/mm/")&RIGHT(A$1,4),"d")),IF(G7="Y","DONE","MISSED"), IF(DATEDIF(TEXT(TODAY(),"dd/mm/yyyy"),TEXT(B7,"dd/mm/")&RIGHT(A$1,4),"d") = 0,"TODAY!!!", IF(DATEDIF(TEXT(TODAY(),"dd/mm/yyyy"),TEXT(B7,"dd/mm/")&RIGHT(A$1,4),"d") > 0, DATEDIF(TEXT(TODAY(),"dd/mm/yyyy"), TEXT(B7,"dd/mm/")&RIGHT(A$1,4),"d")&" Days to go!",""))),"")
A8: Harry | B8: 42696 | C8: =TEXT(B8,"MMDD") -> 1122 | D8: =DATEDIF(B8,NOW(),"y") -> 9 | E8: 5 | F8: Cash. | G8: Y | I8: =IF(E8<>"/",E8-H8,"") -> 5 | J8: =IF(TEXT(TODAY(),"YYYY")=RIGHT(A$1,4), IF(ISERROR(DATEDIF(TEXT(TODAY(),"dd/mm/yyyy"),TEXT(B8,"dd/mm/")&RIGHT(A$1,4),"d")),IF(G8="Y","DONE","MISSED"), IF(DATEDIF(TEXT(TODAY(),"dd/mm/yyyy"),TEXT(B8,"dd/mm/")&RIGHT(A$1,4),"d") = 0,"TODAY!!!", IF(DATEDIF(TEXT(TODAY(),"dd/mm/yyyy"),TEXT(B8,"dd/mm/")&RIGHT(A$1,4),"d") > 0, DATEDIF(TEXT(TODAY(),"dd/mm/yyyy"), TEXT(B8,"dd/mm/")&RIGHT(A$1,4),"d")&" Days to go!",""))),"")
A9: JJ | B9: 33221 | C9: =TEXT(B9,"MMDD") -> 1214 | D9: =DATEDIF(B9,NOW(),"y") -> 35 | E9: / | I9: =IF(E9<>"/",E9-H9,"") | J9: =IF(TEXT(TODAY(),"YYYY")=RIGHT(A$1,4), IF(ISERROR(DATEDIF(TEXT(TODAY(),"dd/mm/yyyy"),TEXT(B9,"dd/mm/")&RIGHT(A$1,4),"d")),IF(G9="Y","DONE","MISSED"), IF(DATEDIF(TEXT(TODAY(),"dd/mm/yyyy"),TEXT(B9,"dd/mm/")&RIGHT(A$1,4),"d") = 0,"TODAY!!!", IF(DATEDIF(TEXT(TODAY(),"dd/mm/yyyy"),TEXT(B9,"dd/mm/")&RIGHT(A$1,4),"d") > 0, DATEDIF(TEXT(TODAY(),"dd/mm/yyyy"), TEXT(B9,"dd/mm/")&RIGHT(A$1,4),"d")&" Days to go!",""))),"")
A10: Robert | B10: 34317 | C10: =TEXT(B10,"MMDD") -> 1214 | D10: =DATEDIF(B10,NOW(),"y") -> 32 | E10: 15 | F10: Becks and stein | G10: Y | H10: 12.5 | I10: =IF(E10<>"/",E10-H10,"") -> 2.5 | J10: =IF(TEXT(TODAY(),"YYYY")=RIGHT(A$1,4), IF(ISERROR(DATEDIF(TEXT(TODAY(),"dd/mm/yyyy"),TEXT(B10,"dd/mm/")&RIGHT(A$1,4),"d")),IF(G10="Y","DONE","MISSED"), IF(DATEDIF(TEXT(TODAY(),"dd/mm/yyyy"),TEXT(B10,"dd/mm/")&RIGHT(A$1,4),"d") = 0,"TODAY!!!", IF(DATEDIF(TEXT(TODAY(),"dd/mm/yyyy"),TEXT(B10,"dd/mm/")&RIGHT(A$1,4),"d") > 0, DATEDIF(TEXT(TODAY(),"dd/mm/yyyy"), TEXT(B10,"dd/mm/")&RIGHT(A$1,4),"d")&" Days to go!",""))),"")
A11: Andrew | B11: 42720 | C11: =TEXT(B11,"MMDD") -> 1216 | D11: =DATEDIF(B11,NOW(),"y") -> 9 | E11: / | I11: =IF(E11<>"/",E11-H11,"") | J11: =IF(TEXT(TODAY(),"YYYY")=RIGHT(A$1,4), IF(ISERROR(DATEDIF(TEXT(TODAY(),"dd/mm/yyyy"),TEXT(B11,"dd/mm/")&RIGHT(A$1,4),"d")),IF(G11="Y","DONE","MISSED"), IF(DATEDIF(TEXT(TODAY(),"dd/mm/yyyy"),TEXT(B11,"dd/mm/")&RIGHT(A$1,4),"d") = 0,"TODAY!!!", IF(DATEDIF(TEXT(TODAY(),"dd/mm/yyyy"),TEXT(B11,"dd/mm/")&RIGHT(A$1,4),"d") > 0, DATEDIF(TEXT(TODAY(),"dd/mm/yyyy"), TEXT(B11,"dd/mm/")&RIGHT(A$1,4),"d")&" Days to go!",""))),"")
A12: Kristine | B12: 34327 | C12: =TEXT(B12,"MMDD") -> 1224 | D12: =DATEDIF(B12,NOW(),"y") -> 32 | E12: 100 | G12: Y | H12: 100 | J12: =IF(TEXT(TODAY(),"YYYY")=RIGHT(A$1,4), IF(ISERROR(DATEDIF(TEXT(TODAY(),"dd/mm/yyyy"),TEXT(B12,"dd/mm/")&RIGHT(A$1,4),"d")),IF(G12="Y","DONE","MISSED"), IF(DATEDIF(TEXT(TODAY(),"dd/mm/yyyy"),TEXT(B12,"dd/mm/")&RIGHT(A$1,4),"d") = 0,"TODAY!!!", IF(DATEDIF(TEXT(TODAY(),"dd/mm/yyyy"),TEXT(B12,"dd/mm/")&RIGHT(A$1,4),"d") > 0, DATEDIF(TEXT(TODAY(),"dd/mm/yyyy"), TEXT(B12,"dd/mm/")&RIGHT(A$1,4),"d")&" Days to go!",""))),"")
A13: Mark | B13: 32138 | C13: =TEXT(B13,"MMDD") -> 1227 | D13: =DATEDIF(B13,NOW(),"y") -> 38 | E13: / | I13: =IF(E13<>"/",E13-H13,"") | J13: =IF(TEXT(TODAY(),"YYYY")=RIGHT(A$1,4), IF(ISERROR(DATEDIF(TEXT(TODAY(),"dd/mm/yyyy"),TEXT(B13,"dd/mm/")&RIGHT(A$1,4),"d")),IF(G13="Y","DONE","MISSED"), IF(DATEDIF(TEXT(TODAY(),"dd/mm/yyyy"),TEXT(B13,"dd/mm/")&RIGHT(A$1,4),"d") = 0,"TODAY!!!", IF(DATEDIF(TEXT(TODAY(),"dd/mm/yyyy"),TEXT(B13,"dd/mm/")&RIGHT(A$1,4),"d") > 0, DATEDIF(TEXT(TODAY(),"dd/mm/yyyy"), TEXT(B13,"dd/mm/")&RIGHT(A$1,4),"d")&" Days to go!",""))),"")
A14: Auntie Julie | B14: 23740 | C14: =TEXT(B14,"MMDD") -> 1229 | D14: =DATEDIF(B14,NOW(),"y") -> 61 | E14: 10 | I14: =IF(E14<>"/",E14-H14,"") -> 10 | J14: =IF(TEXT(TODAY(),"YYYY")=RIGHT(A$1,4), IF(ISERROR(DATEDIF(TEXT(TODAY(),"dd/mm/yyyy"),TEXT(B14,"dd/mm/")&RIGHT(A$1,4),"d")),IF(G14="Y","DONE","MISSED"), IF(DATEDIF(TEXT(TODAY(),"dd/mm/yyyy"),TEXT(B14,"dd/mm/")&RIGHT(A$1,4),"d") = 0,"TODAY!!!", IF(DATEDIF(TEXT(TODAY(),"dd/mm/yyyy"),TEXT(B14,"dd/mm/")&RIGHT(A$1,4),"d") > 0, DATEDIF(TEXT(TODAY(),"dd/mm/yyyy"), TEXT(B14,"dd/mm/")&RIGHT(A$1,4),"d")&" Days to go!",""))),"")
A16: Total: | E16: =SUMIF(E3:E10,">0") -> 50 | H16: =SUM(H3:H10) -> 32.5 | I16: =SUM(I3:I10) -> 17.5

Sheet Jury 2016
B1: Full days | C1: Half Days
B2: 42458
B3: 42459
B4: 42460
B5: 42464
B6: 42465
B7: 42466
B8: 42467
B9: 42468
B10: 42471
A12: Total Days: | B12: =COUNT(B2:B10) -> 9
A13: Total Wage: | B13: =B12*64.33 -> 578.97
A14: Total Substinance: | B14: =B12*5.71 -> 51.39
A15: Total repayment: | B15: =SUM(B13,B14) -> 630.36

Sheet MAR-APR 2016
B1: Monthly Allowance | C1: 30/03/16 - 06/04/2016 | D1: 07/04/16 - 13/04/2016 | E1: 14/03/16 - 20/04/2016 | F1: 21/03/16 - 27/04/2016 | G1: Remaining
A2: Outgoings | C2: =SUM(C3:C16) -> #REF! | D2: =SUM(D3:D16) -> 2181.97 | E2: =SUM(E3:E16) -> 212.35 | F2: =SUM(F3:F16) -> 171.27
A3: Bike petrol | B3: ='Joint Outgoings'!#REF! -> #REF! | C3: 0 | D3: 0 | E3: 0 | F3: 7.75 | G3: =IF(B3<>"",B3-C3-D3-E3-F3,"") -> #REF! | H3: =A3 -> Bike petrol
A4: Food | B4: ='Joint Outgoings'!C3 -> 750 | C4: =6+23.16+9+17.55+3+3 -> 61.71 | D4: =14.15+9.3+3.5+3.27 -> 30.22 | E4: =7.45+4.4+30.05+5+3.29+5.45+15+3.29 -> 73.93 | F4: =9.96+5.54+23.65+7.9 -> 47.05 | G4: =IF(B4<>"",B4-C4-D4-E4-F4,"") -> 537.09 | H4: =A4 -> Food
A5: Car Petrol | G5: =IF(B5<>"",B5-C5-D5-E5-F5,"") | H5: =A5 -> Car Petrol
A6: Netflix | B6: =6.99 -> 6.99 | C6: 6.99 | D6: 0 | E6: 0 | F6: 0 | G6: =IF(B6<>"",B6-C6-D6-E6-F6,"") -> 0 | H6: =A6 -> Netflix
A7: Sky Movies | B7: ='Joint Outgoings'!#REF! -> #REF! | C7: 0 | D7: 0 | E7: 9.99 | F7: 0 | G7: =IF(B7<>"",B7-C7-D7-E7-F7,"") -> #REF! | H7: =A7 -> Sky Movies
A8: Spotify | B8: ='Joint Outgoings'!#REF! -> #REF! | C8: 0 | D8: 4.99 | E8: 0 | F8: 0 | G8: =IF(B8<>"",B8-C8-D8-E8-F8,"") -> #REF! | H8: =A8 -> Spotify
A9: Phone | B9: ='Joint Outgoings'!C29 -> 16.99 | C9: 0 | D9: 0 | E9: 0 | F9: 44.99 | G9: =IF(B9<>"",B9-C9-D9-E9-F9,"") -> -28 | H9: =A9 -> Phone
A10: Bupa | B10: ='Joint Outgoings'!#REF! -> #REF! | C10: 0 | D10: 0 | E10: 0 | G10: =IF(B10<>"",B10-C10-D10-E10-F10,"") -> #REF! | H10: =A10 -> Bupa
A11: Bike ins. | G11: =IF(B11<>"",B11-C11-D11-E11-F11,"") | H11: =A11 -> Bike ins.
A12: Car ins. | G12: =IF(B12<>"",B12-C12-D12-E12-F12,"") | H12: =A12 -> Car ins.
A13: Bike v.tax | G13: =IF(B13<>"",B13-C13-D13-E13-F13,"") | H13: =A13 -> Bike v.tax
A14: Xbox live | G14: =IF(B14<>"",B14-C14-D14-E14-F14,"") | H14: =A14 -> Xbox live
A15: Misc | B15: =B18-SUM(B3:B14)-SUM(C16:F16) -> #REF! | C15: =6.4+9 -> 15.4 | D15: =95+73+101+149.99+20 -> 438.99 | E15: =4.5+4.99+9.99+13.65+4.7+37.85+22.97+2.8+3.98+23 -> 128.43 | F15: =11.99+12.99+31.5+15 -> 71.48 | G15: =IF(B15<>"",B15-C15-D15-E15-F15,"") -> #REF! | H15: Misc
A16: Savings In | B16: =IF(SUM(C16:F16)<>0,SUM(C16:F16),"") -> #REF! | C16: =IF((C18-SUM(B3:B14))>500,(C18-SUM(B3:B14)-500),IF(((C18-SUM(B3:B14))/2)>0,((C18-SUM(B3:B14))/2),0)) -> #REF! | D16: =1850-142.23 -> 1707.77 | H16: Savings
A17: Savings Out | B17: =IF(SUM(C17:F17)<>0,SUM(C17:F17),0) -> 0
A18: Income | B18: =SUM(C18:F18) -> 3299.86 | C18: 643.51 | D18: =1129+945.88 -> 2074.88 | E18: 570.48 | F18: 10.99 | G18: =SUM(G3:G15) -> #REF!

Sheet APR-MAY 2016
B1: Monthly Allowance | C1: 27/04/16 - 03/05/2016 | D1: 04/05/16 - 10/05/2016 | E1: 11/05/16 - 17/05/2016 | F1: 18/05/16 - 24/05/2016 | G1: Remaining
A2: Outgoings | C2: =SUM(C3:C16) -> 924.27 | D2: =SUM(D3:D16) -> 313.79 | E2: =SUM(E3:E16) -> 504.69 | F2: =SUM(F3:F16) -> 186.01
A3: Bike petrol | B3: ='Joint Outgoings'!#REF! -> #REF! | C3: 0 | D3: 0 | E3: 7.87 | F3: 8.32 | G3: =IF(B3<>"",B3-C3-D3-E3-F3,"") -> #REF! | H3: =A3 -> Bike petrol
A4: Car Petrol | G4: =IF(B4<>"",B4-C4-D4-E4-F4,"") | H4: =A4 -> Car Petrol
A5: Netflix | B5: =6.99 -> 6.99 | C5: 6.99 | G5: =IF(B5<>"",B5-C5-D5-E5-F5,"") -> 0 | H5: =A5 -> Netflix
A6: Food | B6: ='Joint Outgoings'!C3 -> 750 | C6: =2.9+11+6.6+39.96+11.5+17 -> 88.96 | D6: =20+49.61+22 -> 91.61 | E6: =14.63 -> 14.63 | F6: =6+25.7 -> 31.7 | G6: =IF(B6<>"",B6-C6-D6-E6-F6,"") -> 523.1 | H6: =A6 -> Food
A7: Sky Movies | B7: ='Joint Outgoings'!#REF! -> #REF! | E7: 9.99 | G7: =IF(B7<>"",B7-C7-D7-E7-F7,"") -> #REF! | H7: =A7 -> Sky Movies
A8: Spotify | B8: ='Joint Outgoings'!#REF! -> #REF! | D8: 4.99 | G8: =IF(B8<>"",B8-C8-D8-E8-F8,"") -> #REF! | H8: =A8 -> Spotify
A9: Phone | B9: ='Joint Outgoings'!C29 -> 16.99 | F9: 44.99 | G9: =IF(B9<>"",B9-C9-D9-E9-F9,"") -> -28 | H9: =A9 -> Phone
A10: Bupa | B10: ='Joint Outgoings'!#REF! -> #REF! | E10: 36.29 | G10: =IF(B10<>"",B10-C10-D10-E10-F10,"") -> #REF! | H10: =A10 -> Bupa
A11: Xbox live | B11: 39.99 | G11: =IF(B11<>"",B11-C11-D11-E11-F11,"") -> 39.99 | H11: =A11 -> Xbox live
A12: Bike ins. | D12: 176.71 | G12: =IF(B12<>"",B12-C12-D12-E12-F12,"") | H12: =A12 -> Bike ins.
A13: Car ins. | G13: =IF(B13<>"",B13-C13-D13-E13-F13,"") | H13: =A13 -> Car ins.
A14: Bike v.tax | B14: 39 | F14: 39 | G14: =IF(B14<>"",B14-C14-D14-E14-F14,"") -> 0 | H14: =A14 -> Bike v.tax
A15: Misc | B15: =IF(B19 <> 0,B19-SUM(B3:B14)-SUM(C16:F16)+SUM(C17:F17)-SUM(C18:F18),"") -> #REF! | C15: =9.4+25.1+31.25+17.57+245 -> 328.32 | D15: =40.48 -> 40.48 | E15: =12.98+12.39+25+37.9+30+7.99+(545.91-308.8)+11.99+59.95+0.6 -> 435.91 | F15: =62 -> 62 | G15: =IF(B15<>"",B15-C15-D15-E15-F15,"") -> #REF! | H15: Misc
A16: Savings In | B16: =IF(SUM(C16:F16)<>0,SUM(C16:F16),"") -> 500 | C16: 500 | D16: =IF(D19 <> "",IF((D19-SUM(C3:C14))>500,(D19-SUM(C3:C14)-500),IF(((D19-SUM(C3:C14))/2)>0,((D19-SUM(C3:C14))/2),0)),"") | E16: =IF(E19 <> "",IF((E19-SUM(D3:D14))>500,(E19-SUM(D3:D14)-500),IF(((E19-SUM(D3:D14))/2)>0,((E19-SUM(D3:D14))/2),0)),"") | H16: Savings
A17: Savings Out | B17: =IF(SUM(C17:F17)<>0,SUM(C17:F17),"") -> 500 | D17: 500
A18: ISA | B18: =IF(SUM(C18:F18)<>0,SUM(C18:F18),0) -> 0
A19: Income | B19: =SUM(C19:F19) -> 1377.68 | C19: =80+579.76+547.49+70.43 -> 1277.68 | F19: 100 | G19: =SUM(G3:G15) -> #REF!

Sheet MAY-JUN 2016
B1: Monthly Allowance | C1: 25/05/16 - 31/05/2016 | D1: 01/05/16 - 07/05/2016 | E1: 08/05/16 - 14/05/2016 | F1: 15/05/16 - 21/05/2016 | G1: 22/05/2016 - 28/05/2016 | H1: Remaining
A2: Outgoings | C2: =SUM(C3:C16) -> 817.11 | D2: =SUM(D3:D16) -> 323.65 | E2: =SUM(E3:E16) -> 1085.57 | F2: =SUM(F3:F16) -> 9.2 | G2: =SUM(G3:G16) -> 0
A3: Bike petrol | B3: 20 | C3: 8.32 | F3: 9.2 | H3: =IF(B3<>"",B3-C3-D3-E3-F3-G3,"") -> 2.48 | I3: =A3 -> Bike petrol
A4: Car Petrol | B4: 100 | D4: =37.84 -> 37.84 | E4: 39.9 | H4: =IF(B4<>"",B4-C4-D4-E4-F4,"") -> 22.26 | I4: =A4 -> Car Petrol
A5: Netflix | B5: =6.99 -> 6.99 | C5: 6.99 | H5: =IF(B5<>"",B5-C5-D5-E5-F5,"") -> 0 | I5: =A5 -> Netflix
A6: Food | B6: ='Joint Outgoings'!C3 -> 750 | C6: =20.3+4 -> 24.3 | D6: =40+10.15 -> 50.15 | E6: =20.1+3+3.83+19.27 -> 46.2 | H6: =IF(B6<>"",B6-C6-D6-E6-F6,"") -> 629.35 | I6: =A6 -> Food
A7: Sky Movies | B7: ='Joint Outgoings'!#REF! -> #REF! | E7: 9.99 | H7: =IF(B7<>"",B7-C7-D7-E7-F7,"") -> #REF! | I7: =A7 -> Sky Movies
A8: Spotify | B8: ='Joint Outgoings'!#REF! -> #REF! | E8: 4.99 | H8: =IF(B8<>"",B8-C8-D8-E8-F8,"") -> #REF! | I8: =A8 -> Spotify
A9: Phone | B9: ='Joint Outgoings'!C29 -> 16.99 | H9: =IF(B9<>"",B9-C9-D9-E9-F9,"") -> 16.99 | I9: =A9 -> Phone
A10: Bupa | B10: ='Joint Outgoings'!#REF! -> #REF! | E10: 36.29 | H10: =IF(B10<>"",B10-C10-D10-E10-F10,"") -> #REF! | I10: =A10 -> Bupa
A11: Xbox live | B11: 39.99 | D11: 39.99 | H11: =IF(B11<>"",B11-C11-D11-E11-F11,"") -> 0 | I11: =A11 -> Xbox live
A12: Bike ins. | H12: =IF(B12<>"",B12-C12-D12-E12-F12,"") | I12: =A12 -> Bike ins.
A13: Car ins. | H13: =IF(B13<>"",B13-C13-D13-E13-F13,"") | I13: =A13 -> Car ins.
A14: Car v.tax | B14: 12.68 | E14: 12.77 | H14: =IF(B14<>"",B14-C14-D14-E14-F14,"") -> -0.09 | I14: =A14 -> Car v.tax
A15: Bike v.tax | H15: =IF(B15<>"",B15-C15-D15-E15-F15,"") | I15: =A15 -> Bike v.tax
A16: Misc | B16: =IF(B20 <> 0,B20-SUM(B3:B15)-SUM(C17:G17)+SUM(C18:G18)-SUM(C19:G19),"") -> #REF! | C16: =20+24+695+18+18+2.5 -> 777.5 | D16: =28+24+111.17+2.5+30 -> 195.67 | E16: =5.23+18+10.98+7.35+20+873.87 -> 935.43 | H16: =IF(B16<>"",B16-C16-D16-E16-F16-G16,"") -> #REF! | I16: Misc
A17: Savings In | B17: =IF(SUM(C17:G17)<>0,SUM(C17:G17),0) -> 0 | I17: Savings
A18: Savings Out | B18: =IF(SUM(C18:G18)<>0,SUM(C18:G18),0) -> 1935.86 | C18: 695 | D18: 111.37 | E18: =100+50+879.49+100 -> 1129.49
A19: ISA | B19: =IF(SUM(C19:G19)<>0,SUM(C19:G19),0) -> 0
A20: Income | B20: =SUM(C20:G20) -> 425.52 | C20: 372.14 | E20: =7.08+46.3 -> 53.38 | H20: =SUM(H3:H16) -> #REF!

Sheet JUN-JUL 2016
B1: Monthly Allowance | C1: ="29/06/16" & " - " & "05/7/16" -> 29/06/16 - 05/7/16 | D1: =TEXT(DATEVALUE(RIGHT(C1,8))+1,"dd/mm/yy")& " - "& TEXT(DATEVALUE(RIGHT(C1,8))+7,"dd/mm/yy") -> 06/07/16 - 12/07/16 | E1: =TEXT(DATEVALUE(RIGHT(D1,8))+1,"dd/mm/yy")& " - "& TEXT(DATEVALUE(RIGHT(D1,8))+7,"dd/mm/yy") -> 13/07/16 - 19/07/16 | F1: =TEXT(DATEVALUE(RIGHT(E1,8))+1,"dd/mm/yy")& " - "& TEXT(DATEVALUE(RIGHT(E1,8))+7,"dd/mm/yy") -> 20/07/16 - 26/07/16 | G1: Remaining
A2: Outgoings | C2: =SUM(C3:C14) -> 95.81 | D2: =SUM(D3:D14) -> 179.69 | E2: =SUM(E3:E14) -> 277.26 | F2: =SUM(F3:F14) -> 84.99
A3: Bike petrol | B3: ='Joint Outgoings'!#REF! -> #REF! | G3: =IF(B3<>"",B3-C3-D3-E3-F3,"") -> #REF! | H3: =A3 -> Bike petrol
A4: Food | B4: ='Joint Outgoings'!C3 -> 750 | C4: =9.14 -> 9.14 | D4: =10 -> 10 | E4: 40 | F4: 40 | G4: =IF(B4<>"",B4-C4-D4-E4-F4,"") -> 650.86 | H4: =A4 -> Food
A5: Car Petrol | B5: 80 | E5: 27 | G5: =IF(B5<>"",B5-C5-D5-E5-F5,"") -> 53 | H5: =A5 -> Car Petrol
A6: Sky Movies | B6: ='Joint Outgoings'!#REF! -> #REF! | E6: 9.99 | G6: =IF(B6<>"",B6-C6-D6-E6-F6,"") -> #REF! | H6: =A6 -> Sky Movies
A7: Spotify | B7: ='Joint Outgoings'!#REF! -> #REF! | D7: 4.99 | G7: =IF(B7<>"",B7-C7-D7-E7-F7,"") -> #REF! | H7: =A7 -> Spotify
A8: Phone | B8: ='Joint Outgoings'!C29 -> 16.99 | F8: 44.99 | G8: =IF(B8<>"",B8-C8-D8-E8-F8,"") -> -28 | H8: =A8 -> Phone
A9: Bupa | B9: ='Joint Outgoings'!#REF! -> #REF! | E9: 36.29 | G9: =IF(B9<>"",B9-C9-D9-E9-F9,"") -> #REF! | H9: =A9 -> Bupa
A10: Gym | B10: 17.99 | C10: 17.99 | G10: =IF(B10<>"",B10-C10-D10-E10-F10,"") -> 0 | H10: =A10 -> Gym
A11: House Deposit | B11: ='Joint Outgoings'!#REF! -> #REF! | G11: =IF(B11<>"",B11-C11-D11-E11-F11,"") -> #REF! | H11: =A11 -> House Deposit
A12: Car ins. | B12: 158 | D12: 153.7 | G12: =IF(B12<>"",B12-C12-D12-E12-F12,"") -> 4.3 | H12: =A12 -> Car ins.
A13: Car v.tax | B13: ='Joint Outgoings'!C25 -> 200 | C13: 12.68 | G13: =IF(B13<>"",B13-C13-D13-E13-F13,"") -> 187.32 | H13: =A13 -> Car v.tax
A14: Misc | B14: =IF(B18 <> 0,B18-SUM(B3:B13)-SUM(C15:F15),"") -> #REF! | C14: 56 | D14: =11 -> 11 | E14: =31.5+20+17.5+16+40.98+38 -> 163.98 | G14: =IF(B14<>"",B14-C14-D14-E14-F14,"") -> #REF! | H14: Misc
A15: Savings In | B15: =IF(SUM(C15:F15)<>0,SUM(C15:F15),0) -> 0 | H15: Savings
A16: Savings Out | B16: =IF(SUM(C16:F16)<>0,SUM(C16:F16),"") -> 56 | C16: 56
A17: ISA
A18: Income | B18: =SUM(C18:F18) -> 719.86 | C18: =389.86+305 -> 694.86 | E18: 25 | G18: =SUM(G3:G14) & " / " & SUM(B3:B13) -> #REF!
D19: =TEXT(DATEVALUE(RIGHT('MAY-JUN 2016'!G1,10))+1,"dd/mm/yy") & " - " & TEXT(DATEVALUE(RIGHT('MAY-JUN 2016'!G1,10))+8,"dd/mm/yy") -> 29/05/16 - 05/06/16

Sheet JUL-AUG 2016
B1: Monthly Allowance | C1: ="27/07/16" & " - " & "02/08/16" -> 27/07/16 - 02/08/16 | D1: =TEXT(DATEVALUE(RIGHT(C1,8))+1,"dd/mm/yy")& " - "& TEXT(DATEVALUE(RIGHT(C1,8))+7,"dd/mm/yy") -> 03/08/16 - 09/08/16 | E1: =TEXT(DATEVALUE(RIGHT(D1,8))+1,"dd/mm/yy")& " - "& TEXT(DATEVALUE(RIGHT(D1,8))+7,"dd/mm/yy") -> 10/08/16 - 16/08/16 | F1: =TEXT(DATEVALUE(RIGHT(E1,8))+1,"dd/mm/yy")& " - "& TEXT(DATEVALUE(RIGHT(E1,8))+7,"dd/mm/yy") -> 17/08/16 - 23/08/16 | G1: =TEXT(DATEVALUE(RIGHT(F1,8))+1,"dd/mm/yy")& " - "& TEXT(DATEVALUE(RIGHT(F1,8))+7,"dd/mm/yy") -> 24/08/16 - 30/08/16 | H1: Remaining
A2: Outgoings | C2: =SUM(C3:C14) -> 336.88 | D2: =SUM(D3:D14) -> 381.11 | E2: =SUM(E3:E14) -> 277.79 | F2: =SUM(F3:F14) -> 46.35 | G2: =SUM(G3:G14) -> 0
A3: Food | B3: =IF(G1="Remaining",'Joint Outgoings'!B3*4,IF(H1= "Remaining",'Joint Outgoings'!B3* 5,"")) -> 0 | C3: =3.35+12.87+1.32+25 -> 42.54 | D3: =40+4.11+25.68 -> 69.79 | E3: =40+3.88+3.62 -> 47.5 | F3: =43.85+2.5 -> 46.35 | H3: =IF(B3<>"",B3-C3-D3-E3-F3-G3,"") -> -206.18 | I3: =A3 -> Food
A4: Car Petrol | B4: =IF(G1="Remaining",'Joint Outgoings'!B24*4,IF(H1= "Remaining",'Joint Outgoings'!B24* 5,"")) -> 0 | C4: 26.42 | D4: 29.82 | E4: =20.36 -> 20.36 | H4: =IF(B4<>"",B4-C4-D4-E4-F4-G4,"") -> -76.6 | I4: =A4 -> Car Petrol
A5: Bike petrol | B5: =IF(G1="Remaining",'Joint Outgoings'!#REF!*4,IF(H1= "Remaining",'Joint Outgoings'!#REF!* 5,"")) -> #REF! | D5: 6.68 | H5: =IF(B5<>"",B5-C5-D5-E5-F5-G5,"") -> #REF! | I5: =A5 -> Bike petrol
A6: Sky Movies | B6: ='Joint Outgoings'!#REF! -> #REF! | E6: =9.99 -> 9.99 | H6: =IF(B6<>"",B6-C6-D6-E6-F6-G6,"") -> #REF! | I6: =A6 -> Sky Movies
A7: Spotify | B7: ='Joint Outgoings'!#REF! -> #REF! | D7: 4.99 | H7: =IF(B7<>"",B7-C7-D7-E7-F7-G7,"") -> #REF! | I7: =A7 -> Spotify
A8: Phone | B8: ='Joint Outgoings'!C29 -> 16.99 | H8: =IF(B8<>"",B8-C8-D8-E8-F8-G8,"") -> 16.99 | I8: =A8 -> Phone
A9: Bupa | B9: ='Joint Outgoings'!#REF! -> #REF! | E9: 36.29 | H9: =IF(B9<>"",B9-C9-D9-E9-F9-G9,"") -> #REF! | I9: =A9 -> Bupa
A10: Gym | B10: 17.99 | C10: 17.99 | H10: =IF(B10<>"",B10-C10-D10-E10-F10-G10,"") -> 0 | I10: =A10 -> Gym
A11: House Deposit | B11: ='Joint Outgoings'!#REF! -> #REF! | H11: =IF(B11<>"",B11-C11-D11-E11-F11-G11,"") -> #REF! | I11: =A11 -> House Deposit
A12: Car ins. | B12: 158 | D12: 153.67 | H12: =IF(B12<>"",B12-C12-D12-E12-F12-G12,"") -> 4.33 | I12: =A12 -> Car ins.
A13: Car v.tax | B13: ='Joint Outgoings'!C25 -> 200 | C13: 12.68 | H13: =IF(B13<>"",B13-C13-D13-E13-F13-G13,"") -> 187.32 | I13: =A13 -> Car v.tax
A14: Misc | B14: =IF(B18 <> 0,B18-SUM(B3:B13)-SUM(C15:F15),"") -> #REF! | C14: =40+159+22+3.25+13 -> 237.25 | D14: =55+20+21.16+20 -> 116.16 | E14: =59.95+103.7 -> 163.65 | H14: =IF(B14<>"",B14-C14-D14-E14-F14-G14,"") -> #REF! | I14: Misc
A15: Savings In | B15: =IF(SUM(C15:F15)<>0,SUM(C15:F15),0) -> 0 | I15: Savings
A16: Savings Out | B16: =IF(SUM(C16:F16)<>0,SUM(C16:F16),"")
A17: ISA
A18: Income | B18: =SUM(C18:F18) -> 1338.79 | C18: 1023.79 | D18: 10 | E18: =55+250 -> 305 | H18: =SUMIF(H3:H14,">0") & " / " & SUM(B3:B14) -> #REF!
H20: =SUM(H3:H13)-H12-H5 -> #REF!

Sheet AUG-SEP 2016
B1: Monthly Allowance | C1: ="29/08/16" & " - " & "06/09/16" -> 29/08/16 - 06/09/16 | D1: =TEXT(DATEVALUE(RIGHT(C1,8))+1,"dd/mm/yy")& " - "& TEXT(DATEVALUE(RIGHT(C1,8))+7,"dd/mm/yy") -> 07/09/16 - 13/09/16 | E1: =TEXT(DATEVALUE(RIGHT(D1,8))+1,"dd/mm/yy")& " - "& TEXT(DATEVALUE(RIGHT(D1,8))+7,"dd/mm/yy") -> 14/09/16 - 20/09/16 | F1: =TEXT(DATEVALUE(RIGHT(E1,8))+1,"dd/mm/yy")& " - "& TEXT(DATEVALUE(RIGHT(E1,8))+7,"dd/mm/yy") -> 21/09/16 - 27/09/16 | G1: Remaining
A2: Outgoings | C2: =SUM(C3:C14) -> 370.18 | D2: =SUM(D3:D14) -> 270.46 | E2: =SUM(E3:E14) -> 310.45 | F2: =SUM(F3:F14) -> 0
A3: Food | B3: =IF(G1="Remaining",'Joint Outgoings'!B3*4,IF(H1= "Remaining",'Joint Outgoings'!B3* 5,"")) -> 0 | C3: =18.9+10.9+2.5+5.3 -> 37.6 | D3: =20+3+3.85+3.1 -> 29.95 | E3: =38.56+4.44+2.3 -> 45.3 | G3: =IF(B3<>"",B3-C3-D3-E3-F3,"") -> -112.85 | H3: =A3 -> Food
A4: Car Petrol | B4: =IF(G1="Remaining",'Joint Outgoings'!B24*4,IF(H1= "Remaining",'Joint Outgoings'!B24* 5,"")) -> 0 | C4: 30.73 | E4: 31.5 | G4: =IF(B4<>"",B4-C4-D4-E4-F4,"") -> -62.23 | H4: =A4 -> Car Petrol
A5: Bike petrol | B5: =IF(G1="Remaining",'Joint Outgoings'!#REF!*4,IF(H1= "Remaining",'Joint Outgoings'!#REF!* 5,"")) -> #REF! | D5: =9.16 -> 9.16 | G5: =IF(B5<>"",B5-C5-D5-E5-F5,"") -> #REF! | H5: =A5 -> Bike petrol
A6: Sky Movies | B6: ='Joint Outgoings'!#REF! -> #REF! | E6: 9.99 | G6: =IF(B6<>"",B6-C6-D6-E6-F6,"") -> #REF! | H6: =A6 -> Sky Movies
A7: Spotify | B7: ='Joint Outgoings'!#REF! -> #REF! | D7: 4.99 | G7: =IF(B7<>"",B7-C7-D7-E7-F7,"") -> #REF! | H7: =A7 -> Spotify
A8: Phone | B8: ='Joint Outgoings'!C29 -> 16.99 | E8: 44.99 | G8: =IF(B8<>"",B8-C8-D8-E8-F8,"") -> -28 | H8: =A8 -> Phone
A9: Bupa | B9: ='Joint Outgoings'!#REF! -> #REF! | E9: 36.29 | G9: =IF(B9<>"",B9-C9-D9-E9-F9,"") -> #REF! | H9: =A9 -> Bupa
A10: Gym | B10: 17.99 | C10: 17.99 | G10: =IF(B10<>"",B10-C10-D10-E10-F10,"") -> 0 | H10: =A10 -> Gym
A11: House Deposit | B11: ='Joint Outgoings'!#REF! -> #REF! | G11: =IF(B11<>"",B11-C11-D11-E11-F11,"") -> #REF! | H11: =A11 -> House Deposit
A12: Car ins. | B12: 153.67 | D12: 153.67 | G12: =IF(B12<>"",B12-C12-D12-E12-F12,"") -> 0 | H12: =A12 -> Car ins.
A13: Car v.tax | B13: ='Joint Outgoings'!C25 -> 200 | C13: 12.68 | G13: =IF(B13<>"",B13-C13-D13-E13-F13,"") -> 187.32 | H13: =A13 -> Car v.tax
A14: Misc | B14: =IF(B18 <> 0,B18-SUM(B3:B13)-SUM(C15:F15),"") -> #REF! | C14: =100+44.94+9.39+10+46.25+39+21.6 -> 271.18 | D14: =39.45+24.25+8.99 -> 72.69 | E14: =3.5+17.2+12.48+30.85+40+5.5+32.85 -> 142.38 | G14: =IF(B14<>"",B14-C14-D14-E14-F14,"") -> #REF! | H14: Misc
A15: Savings In | B15: =IF(SUM(C15:F15)<>0,SUM(C15:F15),0) -> 0 | H15: Savings
A16: Savings Out | B16: =IF(SUM(C16:F16)<>0,SUM(C16:F16),"")
A17: ISA
A18: Income | B18: =SUM(C18:F18) -> 961.54 | C18: =935.56+17.99 -> 953.55 | E18: =7.99 -> 7.99 | G18: =SUM(G3:G14) & " / " & SUM(B3:B14) -> #REF!
G19: =SUM(G3:G14) -> #REF!
A20: =IF(SUM(B3:B13)>B18,"You will have insufficient funds for this month!","") -> #REF!

Sheet Birthdays 2017
A1: Birthdays / Card 2017 | B1: Date | D1: Age | E1: Gift Value | F1: Ideas | G1: Done? | H1: Spent | I1: Remaining | J1: Time
A3: Lena | B3: 42655 | C3: =TEXT(B3,"MMDD") -> 1012 | D3: =DATEDIF(B3,NOW(),"y") -> 9 | E3: 10 | I3: =IF(E3<>"/",E3-H3,0) -> 10 | J3: =IF(TEXT(TODAY(),"YYYY")=RIGHT(A$1,4), IF(ISERROR(DATEDIF(TEXT(TODAY(),"dd/mm/yyyy"),TEXT(B3,"dd/mm/")&RIGHT(A$1,4),"d")),IF(G3="Y","DONE","MISSED"), IF(DATEDIF(TEXT(TODAY(),"dd/mm/yyyy"),TEXT(B3,"dd/mm/")&RIGHT(A$1,4),"d") = 0,"TODAY!!!", IF(DATEDIF(TEXT(TODAY(),"dd/mm/yyyy"),TEXT(B3,"dd/mm/")&RIGHT(A$1,4),"d") > 0, DATEDIF(TEXT(TODAY(),"dd/mm/yyyy"), TEXT(B3,"dd/mm/")&RIGHT(A$1,4),"d")&" Days to go!",""))),"")
A4: Jasmine | C4: =TEXT(B4,"MMDD") -> 0100 | D4: =DATEDIF(B4,NOW(),"y") -> 126 | E4: 5 | F4: Cash. | I4: =IF(E4<>"/",E4-H4,0) -> 5 | J4: =IF(TEXT(TODAY(),"YYYY")=RIGHT(A$1,4), IF(ISERROR(DATEDIF(TEXT(TODAY(),"dd/mm/yyyy"),TEXT(B4,"dd/mm/")&RIGHT(A$1,4),"d")),IF(G4="Y","DONE","MISSED"), IF(DATEDIF(TEXT(TODAY(),"dd/mm/yyyy"),TEXT(B4,"dd/mm/")&RIGHT(A$1,4),"d") = 0,"TODAY!!!", IF(DATEDIF(TEXT(TODAY(),"dd/mm/yyyy"),TEXT(B4,"dd/mm/")&RIGHT(A$1,4),"d") > 0, DATEDIF(TEXT(TODAY(),"dd/mm/yyyy"), TEXT(B4,"dd/mm/")&RIGHT(A$1,4),"d")&" Days to go!",""))),"")
A5: Leo | C5: =TEXT(B5,"MMDD") -> 0100 | D5: =DATEDIF(B5,NOW(),"y") -> 126 | E5: 5 | F5: Cash. | I5: =IF(E5<>"/",E5-H5,0) -> 5 | J5: =IF(TEXT(TODAY(),"YYYY")=RIGHT(A$1,4), IF(ISERROR(DATEDIF(TEXT(TODAY(),"dd/mm/yyyy"),TEXT(B5,"dd/mm/")&RIGHT(A$1,4),"d")),IF(G5="Y","DONE","MISSED"), IF(DATEDIF(TEXT(TODAY(),"dd/mm/yyyy"),TEXT(B5,"dd/mm/")&RIGHT(A$1,4),"d") = 0,"TODAY!!!", IF(DATEDIF(TEXT(TODAY(),"dd/mm/yyyy"),TEXT(B5,"dd/mm/")&RIGHT(A$1,4),"d") > 0, DATEDIF(TEXT(TODAY(),"dd/mm/yyyy"), TEXT(B5,"dd/mm/")&RIGHT(A$1,4),"d")&" Days to go!",""))),"")
A6: Jamie | B6: =DATE(1990,1,6) -> 32879 | C6: =TEXT(B6,"MMDD") -> 0106 | D6: =DATEDIF(B6,NOW(),"y") -> 36 | E6: / | I6: =IF(E6<>"/",E6-H6,0) -> 0 | J6: =IF(TEXT(TODAY(),"YYYY")=RIGHT(A$1,4), IF(ISERROR(DATEDIF(TEXT(TODAY(),"dd/mm/yyyy"),TEXT(B6,"dd/mm/")&RIGHT(A$1,4),"d")),IF(G6="Y","DONE","MISSED"), IF(DATEDIF(TEXT(TODAY(),"dd/mm/yyyy"),TEXT(B6,"dd/mm/")&RIGHT(A$1,4),"d") = 0,"TODAY!!!", IF(DATEDIF(TEXT(TODAY(),"dd/mm/yyyy"),TEXT(B6,"dd/mm/")&RIGHT(A$1,4),"d") > 0, DATEDIF(TEXT(TODAY(),"dd/mm/yyyy"), TEXT(B6,"dd/mm/")&RIGHT(A$1,4),"d")&" Days to go!",""))),"")
A7: Sam | B7: 42375 | C7: =TEXT(B7,"MMDD") -> 0106 | D7: =DATEDIF(B7,NOW(),"y") -> 10 | E7: 5 | F7: Cash. | G7: Y | I7: =IF(E7<>"/",E7-H7,0) -> 5 | J7: =IF(TEXT(TODAY(),"YYYY")=RIGHT(A$1,4), IF(ISERROR(DATEDIF(TEXT(TODAY(),"dd/mm/yyyy"),TEXT(B7,"dd/mm/")&RIGHT(A$1,4),"d")),IF(G7="Y","DONE","MISSED"), IF(DATEDIF(TEXT(TODAY(),"dd/mm/yyyy"),TEXT(B7,"dd/mm/")&RIGHT(A$1,4),"d") = 0,"TODAY!!!", IF(DATEDIF(TEXT(TODAY(),"dd/mm/yyyy"),TEXT(B7,"dd/mm/")&RIGHT(A$1,4),"d") > 0, DATEDIF(TEXT(TODAY(),"dd/mm/yyyy"), TEXT(B7,"dd/mm/")&RIGHT(A$1,4),"d")&" Days to go!",""))),"")
A8: Amanda | B8: 42376 | C8: =TEXT(B8,"MMDD") -> 0107 | D8: =DATEDIF(B8,NOW(),"y") -> 10 | E8: / | G8: Y | I8: =IF(E8<>"/",E8-H8,0) -> 0 | J8: =IF(TEXT(TODAY(),"YYYY")=RIGHT(A$1,4), IF(ISERROR(DATEDIF(TEXT(TODAY(),"dd/mm/yyyy"),TEXT(B8,"dd/mm/")&RIGHT(A$1,4),"d")),IF(G8="Y","DONE","MISSED"), IF(DATEDIF(TEXT(TODAY(),"dd/mm/yyyy"),TEXT(B8,"dd/mm/")&RIGHT(A$1,4),"d") = 0,"TODAY!!!", IF(DATEDIF(TEXT(TODAY(),"dd/mm/yyyy"),TEXT(B8,"dd/mm/")&RIGHT(A$1,4),"d") > 0, DATEDIF(TEXT(TODAY(),"dd/mm/yyyy"), TEXT(B8,"dd/mm/")&RIGHT(A$1,4),"d")&" Days to go!",""))),"")
A9: Uncle Andrew (Auntie Julie) | B9: 42378 | C9: =TEXT(B9,"MMDD") -> 0109 | D9: =DATEDIF(B9,NOW(),"y") -> 10 | E9: 10 | I9: =IF(E9<>"/",E9-H9,0) -> 10 | J9: =IF(TEXT(TODAY(),"YYYY")=RIGHT(A$1,4), IF(ISERROR(DATEDIF(TEXT(TODAY(),"dd/mm/yyyy"),TEXT(B9,"dd/mm/")&RIGHT(A$1,4),"d")),IF(G9="Y","DONE","MISSED"), IF(DATEDIF(TEXT(TODAY(),"dd/mm/yyyy"),TEXT(B9,"dd/mm/")&RIGHT(A$1,4),"d") = 0,"TODAY!!!", IF(DATEDIF(TEXT(TODAY(),"dd/mm/yyyy"),TEXT(B9,"dd/mm/")&RIGHT(A$1,4),"d") > 0, DATEDIF(TEXT(TODAY(),"dd/mm/yyyy"), TEXT(B9,"dd/mm/")&RIGHT(A$1,4),"d")&" Days to go!",""))),"")
A10: Uncle Andrew (Jamie / JJ) | B10: 42382 | C10: =TEXT(B10,"MMDD") -> 0113 | D10: =DATEDIF(B10,NOW(),"y") -> 10 | E10: 10 | I10: =IF(E10<>"/",E10-H10,0) -> 10 | J10: =IF(TEXT(TODAY(),"YYYY")=RIGHT(A$1,4), IF(ISERROR(DATEDIF(TEXT(TODAY(),"dd/mm/yyyy"),TEXT(B10,"dd/mm/")&RIGHT(A$1,4),"d")),IF(G10="Y","DONE","MISSED"), IF(DATEDIF(TEXT(TODAY(),"dd/mm/yyyy"),TEXT(B10,"dd/mm/")&RIGHT(A$1,4),"d") = 0,"TODAY!!!", IF(DATEDIF(TEXT(TODAY(),"dd/mm/yyyy"),TEXT(B10,"dd/mm/")&RIGHT(A$1,4),"d") > 0, DATEDIF(TEXT(TODAY(),"dd/mm/yyyy"), TEXT(B10,"dd/mm/")&RIGHT(A$1,4),"d")&" Days to go!",""))),"")
A11: Rachel | B11: 42383 | C11: =TEXT(B11,"MMDD") -> 0114 | D11: =DATEDIF(B11,NOW(),"y") -> 10 | E11: 10 | I11: =IF(E11<>"/",E11-H11,0) -> 10 | J11: =IF(TEXT(TODAY(),"YYYY")=RIGHT(A$1,4), IF(ISERROR(DATEDIF(TEXT(TODAY(),"dd/mm/yyyy"),TEXT(B11,"dd/mm/")&RIGHT(A$1,4),"d")),IF(G11="Y","DONE","MISSED"), IF(DATEDIF(TEXT(TODAY(),"dd/mm/yyyy"),TEXT(B11,"dd/mm/")&RIGHT(A$1,4),"d") = 0,"TODAY!!!", IF(DATEDIF(TEXT(TODAY(),"dd/mm/yyyy"),TEXT(B11,"dd/mm/")&RIGHT(A$1,4),"d") > 0, DATEDIF(TEXT(TODAY(),"dd/mm/yyyy"), TEXT(B11,"dd/mm/")&RIGHT(A$1,4),"d")&" Days to go!",""))),"")
A12: Auntie Susan | B12: 20115 | C12: =TEXT(B12,"MMDD") -> 0126 | D12: =DATEDIF(B12,NOW(),"y") -> 71 | E12: 10 | G12: Y | I12: =IF(E12<>"/",E12-H12,0) -> 10 | J12: =IF(TEXT(TODAY(),"YYYY")=RIGHT(A$1,4), IF(ISERROR(DATEDIF(TEXT(TODAY(),"dd/mm/yyyy"),TEXT(B12,"dd/mm/")&RIGHT(A$1,4),"d")),IF(G12="Y","DONE","MISSED"), IF(DATEDIF(TEXT(TODAY(),"dd/mm/yyyy"),TEXT(B12,"dd/mm/")&RIGHT(A$1,4),"d") = 0,"TODAY!!!", IF(DATEDIF(TEXT(TODAY(),"dd/mm/yyyy"),TEXT(B12,"dd/mm/")&RIGHT(A$1,4),"d") > 0, DATEDIF(TEXT(TODAY(),"dd/mm/yyyy"), TEXT(B12,"dd/mm/")&RIGHT(A$1,4),"d")&" Days to go!",""))),"")
A13: Malcolm | B13: 42396 | C13: =TEXT(B13,"MMDD") -> 0127 | D13: =DATEDIF(B13,NOW(),"y") -> 10 | E13: / | I13: =IF(E13<>"/",E13-H13,0) -> 0 | J13: =IF(TEXT(TODAY(),"YYYY")=RIGHT(A$1,4), IF(ISERROR(DATEDIF(TEXT(TODAY(),"dd/mm/yyyy"),TEXT(B13,"dd/mm/")&RIGHT(A$1,4),"d")),IF(G13="Y","DONE","MISSED"), IF(DATEDIF(TEXT(TODAY(),"dd/mm/yyyy"),TEXT(B13,"dd/mm/")&RIGHT(A$1,4),"d") = 0,"TODAY!!!", IF(DATEDIF(TEXT(TODAY(),"dd/mm/yyyy"),TEXT(B13,"dd/mm/")&RIGHT(A$1,4),"d") > 0, DATEDIF(TEXT(TODAY(),"dd/mm/yyyy"), TEXT(B13,"dd/mm/")&RIGHT(A$1,4),"d")&" Days to go!",""))),"")
A14: Uncle Keith | B14: 42401 | C14: =TEXT(B14,"MMDD") -> 0201 | D14: =DATEDIF(B14,NOW(),"y") -> 10 | E14: 10 | G14: Y | I14: =IF(E14<>"/",E14-H14,0) -> 10 | J14: =IF(TEXT(TODAY(),"YYYY")=RIGHT(A$1,4), IF(ISERROR(DATEDIF(TEXT(TODAY(),"dd/mm/yyyy"),TEXT(B14,"dd/mm/")&RIGHT(A$1,4),"d")),IF(G14="Y","DONE","MISSED"), IF(DATEDIF(TEXT(TODAY(),"dd/mm/yyyy"),TEXT(B14,"dd/mm/")&RIGHT(A$1,4),"d") = 0,"TODAY!!!", IF(DATEDIF(TEXT(TODAY(),"dd/mm/yyyy"),TEXT(B14,"dd/mm/")&RIGHT(A$1,4),"d") > 0, DATEDIF(TEXT(TODAY(),"dd/mm/yyyy"), TEXT(B14,"dd/mm/")&RIGHT(A$1,4),"d")&" Days to go!",""))),"")
A15: Jordan | B15: 34368 | C15: =TEXT(B15,"MMDD") -> 0203 | D15: =DATEDIF(B15,NOW(),"y") -> 32 | E15: 15 | G15: Y | I15: =IF(E15<>"/",E15-H15,0) -> 15 | J15: =IF(TEXT(TODAY(),"YYYY")=RIGHT(A$1,4), IF(ISERROR(DATEDIF(TEXT(TODAY(),"dd/mm/yyyy"),TEXT(B15,"dd/mm/")&RIGHT(A$1,4),"d")),IF(G15="Y","DONE","MISSED"), IF(DATEDIF(TEXT(TODAY(),"dd/mm/yyyy"),TEXT(B15,"dd/mm/")&RIGHT(A$1,4),"d") = 0,"TODAY!!!", IF(DATEDIF(TEXT(TODAY(),"dd/mm/yyyy"),TEXT(B15,"dd/mm/")&RIGHT(A$1,4),"d") > 0, DATEDIF(TEXT(TODAY(),"dd/mm/yyyy"), TEXT(B15,"dd/mm/")&RIGHT(A$1,4),"d")&" Days to go!",""))),"")
A16: Auntie Jo | B16: 42404 | C16: =TEXT(B16,"MMDD") -> 0204 | D16: =DATEDIF(B16,NOW(),"y") -> 10 | E16: 10 | G16: Y | I16: =IF(E16<>"/",E16-H16,0) -> 10 | J16: =IF(TEXT(TODAY(),"YYYY")=RIGHT(A$1,4), IF(ISERROR(DATEDIF(TEXT(TODAY(),"dd/mm/yyyy"),TEXT(B16,"dd/mm/")&RIGHT(A$1,4),"d")),IF(G16="Y","DONE","MISSED"), IF(DATEDIF(TEXT(TODAY(),"dd/mm/yyyy"),TEXT(B16,"dd/mm/")&RIGHT(A$1,4),"d") = 0,"TODAY!!!", IF(DATEDIF(TEXT(TODAY(),"dd/mm/yyyy"),TEXT(B16,"dd/mm/")&RIGHT(A$1,4),"d") > 0, DATEDIF(TEXT(TODAY(),"dd/mm/yyyy"), TEXT(B16,"dd/mm/")&RIGHT(A$1,4),"d")&" Days to go!",""))),"")
A17: William | B17: 42406 | C17: =TEXT(B17,"MMDD") -> 0206 | D17: =DATEDIF(B17,NOW(),"y") -> 10 | E17: 5 | F17: Cash. | G17: Y | I17: =IF(E17<>"/",E17-H17,0) -> 5 | J17: =IF(TEXT(TODAY(),"YYYY")=RIGHT(A$1,4), IF(ISERROR(DATEDIF(TEXT(TODAY(),"dd/mm/yyyy"),TEXT(B17,"dd/mm/")&RIGHT(A$1,4),"d")),IF(G17="Y","DONE","MISSED"), IF(DATEDIF(TEXT(TODAY(),"dd/mm/yyyy"),TEXT(B17,"dd/mm/")&RIGHT(A$1,4),"d") = 0,"TODAY!!!", IF(DATEDIF(TEXT(TODAY(),"dd/mm/yyyy"),TEXT(B17,"dd/mm/")&RIGHT(A$1,4),"d") > 0, DATEDIF(TEXT(TODAY(),"dd/mm/yyyy"), TEXT(B17,"dd/mm/")&RIGHT(A$1,4),"d")&" Days to go!",""))),"")
A18: Lea | B18: 37694 | C18: =TEXT(B18,"MMDD") -> 0314 | D18: =DATEDIF(B18,NOW(),"y") -> 23 | E18: 5 | F18: Cash. | G18: y | I18: =IF(E18<>"/",E18-H18,0) -> 5 | J18: =IF(TEXT(TODAY(),"YYYY")=RIGHT(A$1,4), IF(ISERROR(DATEDIF(TEXT(TODAY(),"dd/mm/yyyy"),TEXT(B18,"dd/mm/")&RIGHT(A$1,4),"d")),IF(G18="Y","DONE","MISSED"), IF(DATEDIF(TEXT(TODAY(),"dd/mm/yyyy"),TEXT(B18,"dd/mm/")&RIGHT(A$1,4),"d") = 0,"TODAY!!!", IF(DATEDIF(TEXT(TODAY(),"dd/mm/yyyy"),TEXT(B18,"dd/mm/")&RIGHT(A$1,4),"d") > 0, DATEDIF(TEXT(TODAY(),"dd/mm/yyyy"), TEXT(B18,"dd/mm/")&RIGHT(A$1,4),"d")&" Days to go!",""))),"")
A19: Morgan | B19: 37694 | C19: =TEXT(B19,"MMDD") -> 0314 | D19: =DATEDIF(B19,NOW(),"y") -> 23 | E19: 5 | F19: Cash. | G19: y | I19: =IF(E19<>"/",E19-H19,0) -> 5 | J19: =IF(TEXT(TODAY(),"YYYY")=RIGHT(A$1,4), IF(ISERROR(DATEDIF(TEXT(TODAY(),"dd/mm/yyyy"),TEXT(B19,"dd/mm/")&RIGHT(A$1,4),"d")),IF(G19="Y","DONE","MISSED"), IF(DATEDIF(TEXT(TODAY(),"dd/mm/yyyy"),TEXT(B19,"dd/mm/")&RIGHT(A$1,4),"d") = 0,"TODAY!!!", IF(DATEDIF(TEXT(TODAY(),"dd/mm/yyyy"),TEXT(B19,"dd/mm/")&RIGHT(A$1,4),"d") > 0, DATEDIF(TEXT(TODAY(),"dd/mm/yyyy"), TEXT(B19,"dd/mm/")&RIGHT(A$1,4),"d")&" Days to go!",""))),"")
A20: Dave | B20: 35145 | C20: =TEXT(B20,"MMDD") -> 0321 | D20: =DATEDIF(B20,NOW(),"y") -> 30 | E20: / | G20: y | I20: =IF(E20<>"/",E20-H20,0) -> 0 | J20: =IF(TEXT(TODAY(),"YYYY")=RIGHT(A$1,4), IF(ISERROR(DATEDIF(TEXT(TODAY(),"dd/mm/yyyy"),TEXT(B20,"dd/mm/")&RIGHT(A$1,4),"d")),IF(G20="Y","DONE","MISSED"), IF(DATEDIF(TEXT(TODAY(),"dd/mm/yyyy"),TEXT(B20,"dd/mm/")&RIGHT(A$1,4),"d") = 0,"TODAY!!!", IF(DATEDIF(TEXT(TODAY(),"dd/mm/yyyy"),TEXT(B20,"dd/mm/")&RIGHT(A$1,4),"d") > 0, DATEDIF(TEXT(TODAY(),"dd/mm/yyyy"), TEXT(B20,"dd/mm/")&RIGHT(A$1,4),"d")&" Days to go!",""))),"")
A21: Auntie Jean | B21: 42453 | C21: =TEXT(B21,"MMDD") -> 0324 | D21: =DATEDIF(B21,NOW(),"y") -> 10 | E21: 10 | G21: y | I21: =IF(E21<>"/",E21-H21,0) -> 10 | J21: =IF(TEXT(TODAY(),"YYYY")=RIGHT(A$1,4), IF(ISERROR(DATEDIF(TEXT(TODAY(),"dd/mm/yyyy"),TEXT(B21,"dd/mm/")&RIGHT(A$1,4),"d")),IF(G21="Y","DONE","MISSED"), IF(DATEDIF(TEXT(TODAY(),"dd/mm/yyyy"),TEXT(B21,"dd/mm/")&RIGHT(A$1,4),"d") = 0,"TODAY!!!", IF(DATEDIF(TEXT(TODAY(),"dd/mm/yyyy"),TEXT(B21,"dd/mm/")&RIGHT(A$1,4),"d") > 0, DATEDIF(TEXT(TODAY(),"dd/mm/yyyy"), TEXT(B21,"dd/mm/")&RIGHT(A$1,4),"d")&" Days to go!",""))),"")
A22: Uncle Chris | B22: 42458 | C22: =TEXT(B22,"MMDD") -> 0329 | D22: =DATEDIF(B22,NOW(),"y") -> 10 | E22: 10 | G22: y | I22: =IF(E22<>"/",E22-H22,0) -> 10 | J22: =IF(TEXT(TODAY(),"YYYY")=RIGHT(A$1,4), IF(ISERROR(DATEDIF(TEXT(TODAY(),"dd/mm/yyyy"),TEXT(B22,"dd/mm/")&RIGHT(A$1,4),"d")),IF(G22="Y","DONE","MISSED"), IF(DATEDIF(TEXT(TODAY(),"dd/mm/yyyy"),TEXT(B22,"dd/mm/")&RIGHT(A$1,4),"d") = 0,"TODAY!!!", IF(DATEDIF(TEXT(TODAY(),"dd/mm/yyyy"),TEXT(B22,"dd/mm/")&RIGHT(A$1,4),"d") > 0, DATEDIF(TEXT(TODAY(),"dd/mm/yyyy"), TEXT(B22,"dd/mm/")&RIGHT(A$1,4),"d")&" Days to go!",""))),"")
A23: Dad | B23: 18733 | C23: =TEXT(B23,"MMDD") -> 0415 | D23: =DATEDIF(B23,NOW(),"y") -> 75 | E23: 50 | G23: y | I23: =IF(E23<>"/",E23-H23,0) -> 50 | J23: =IF(TEXT(TODAY(),"YYYY")=RIGHT(A$1,4), IF(ISERROR(DATEDIF(TEXT(TODAY(),"dd/mm/yyyy"),TEXT(B23,"dd/mm/")&RIGHT(A$1,4),"d")),IF(G23="Y","DONE","MISSED"), IF(DATEDIF(TEXT(TODAY(),"dd/mm/yyyy"),TEXT(B23,"dd/mm/")&RIGHT(A$1,4),"d") = 0,"TODAY!!!", IF(DATEDIF(TEXT(TODAY(),"dd/mm/yyyy"),TEXT(B23,"dd/mm/")&RIGHT(A$1,4),"d") > 0, DATEDIF(TEXT(TODAY(),"dd/mm/yyyy"), TEXT(B23,"dd/mm/")&RIGHT(A$1,4),"d")&" Days to go!",""))),"")
A24: Grandad | B24: 12162 | C24: =TEXT(B24,"MMDD") -> 0418 | D24: =DATEDIF(B24,NOW(),"y") -> 93 | E24: 20 | G24: y | I24: =IF(E24<>"/",E24-H24,0) -> 20 | J24: =IF(TEXT(TODAY(),"YYYY")=RIGHT(A$1,4), IF(ISERROR(DATEDIF(TEXT(TODAY(),"dd/mm/yyyy"),TEXT(B24,"dd/mm/")&RIGHT(A$1,4),"d")),IF(G24="Y","DONE","MISSED"), IF(DATEDIF(TEXT(TODAY(),"dd/mm/yyyy"),TEXT(B24,"dd/mm/")&RIGHT(A$1,4),"d") = 0,"TODAY!!!", IF(DATEDIF(TEXT(TODAY(),"dd/mm/yyyy"),TEXT(B24,"dd/mm/")&RIGHT(A$1,4),"d") > 0, DATEDIF(TEXT(TODAY(),"dd/mm/yyyy"), TEXT(B24,"dd/mm/")&RIGHT(A$1,4),"d")&" Days to go!",""))),"")
A25: Andrew | B25: 42495 | C25: =TEXT(B25,"MMDD") -> 0505 | D25: =DATEDIF(B25,NOW(),"y") -> 10 | E25: 10 | I25: =IF(E25<>"/",E25-H25,0) -> 10 | J25: =IF(TEXT(TODAY(),"YYYY")=RIGHT(A$1,4), IF(ISERROR(DATEDIF(TEXT(TODAY(),"dd/mm/yyyy"),TEXT(B25,"dd/mm/")&RIGHT(A$1,4),"d")),IF(G25="Y","DONE","MISSED"), IF(DATEDIF(TEXT(TODAY(),"dd/mm/yyyy"),TEXT(B25,"dd/mm/")&RIGHT(A$1,4),"d") = 0,"TODAY!!!", IF(DATEDIF(TEXT(TODAY(),"dd/mm/yyyy"),TEXT(B25,"dd/mm/")&RIGHT(A$1,4),"d") > 0, DATEDIF(TEXT(TODAY(),"dd/mm/yyyy"), TEXT(B25,"dd/mm/")&RIGHT(A$1,4),"d")&" Days to go!",""))),"")
A26: Christian | B26: 33730 | C26: =TEXT(B26,"MMDD") -> 0506 | D26: =DATEDIF(B26,NOW(),"y") -> 34 | E26: / | I26: =IF(E26<>"/",E26-H26,0) -> 0 | J26: =IF(TEXT(TODAY(),"YYYY")=RIGHT(A$1,4), IF(ISERROR(DATEDIF(TEXT(TODAY(),"dd/mm/yyyy"),TEXT(B26,"dd/mm/")&RIGHT(A$1,4),"d")),IF(G26="Y","DONE","MISSED"), IF(DATEDIF(TEXT(TODAY(),"dd/mm/yyyy"),TEXT(B26,"dd/mm/")&RIGHT(A$1,4),"d") = 0,"TODAY!!!", IF(DATEDIF(TEXT(TODAY(),"dd/mm/yyyy"),TEXT(B26,"dd/mm/")&RIGHT(A$1,4),"d") > 0, DATEDIF(TEXT(TODAY(),"dd/mm/yyyy"), TEXT(B26,"dd/mm/")&RIGHT(A$1,4),"d")&" Days to go!",""))),"")
A27: Lee | B27: 27895 | C27: =TEXT(B27,"MMDD") -> 0515 | D27: =DATEDIF(B27,NOW(),"y") -> 50 | E27: 10 | G27: y | I27: =IF(E27<>"/",E27-H27,0) -> 10 | J27: =IF(TEXT(TODAY(),"YYYY")=RIGHT(A$1,4), IF(ISERROR(DATEDIF(TEXT(TODAY(),"dd/mm/yyyy"),TEXT(B27,"dd/mm/")&RIGHT(A$1,4),"d")),IF(G27="Y","DONE","MISSED"), IF(DATEDIF(TEXT(TODAY(),"dd/mm/yyyy"),TEXT(B27,"dd/mm/")&RIGHT(A$1,4),"d") = 0,"TODAY!!!", IF(DATEDIF(TEXT(TODAY(),"dd/mm/yyyy"),TEXT(B27,"dd/mm/")&RIGHT(A$1,4),"d") > 0, DATEDIF(TEXT(TODAY(),"dd/mm/yyyy"), TEXT(B27,"dd/mm/")&RIGHT(A$1,4),"d")&" Days to go!",""))),"")
A28: Craig | B28: 27895 | C28: =TEXT(B28,"MMDD") -> 0515 | D28: =DATEDIF(B28,NOW(),"y") -> 50 | E28: 10 | G28: y | I28: =IF(E28<>"/",E28-H28,0) -> 10 | J28: =IF(TEXT(TODAY(),"YYYY")=RIGHT(A$1,4), IF(ISERROR(DATEDIF(TEXT(TODAY(),"dd/mm/yyyy"),TEXT(B28,"dd/mm/")&RIGHT(A$1,4),"d")),IF(G28="Y","DONE","MISSED"), IF(DATEDIF(TEXT(TODAY(),"dd/mm/yyyy"),TEXT(B28,"dd/mm/")&RIGHT(A$1,4),"d") = 0,"TODAY!!!", IF(DATEDIF(TEXT(TODAY(),"dd/mm/yyyy"),TEXT(B28,"dd/mm/")&RIGHT(A$1,4),"d") > 0, DATEDIF(TEXT(TODAY(),"dd/mm/yyyy"), TEXT(B28,"dd/mm/")&RIGHT(A$1,4),"d")&" Days to go!",""))),"")
A29: Uncle Mick | B29: 16942 | C29: =TEXT(B29,"MMDD") -> 0520 | D29: =DATEDIF(B29,NOW(),"y") -> 80 | E29: / | G29: y | I29: =IF(E29<>"/",E29-H29,0) -> 0 | J29: =IF(TEXT(TODAY(),"YYYY")=RIGHT(A$1,4), IF(ISERROR(DATEDIF(TEXT(TODAY(),"dd/mm/yyyy"),TEXT(B29,"dd/mm/")&RIGHT(A$1,4),"d")),IF(G29="Y","DONE","MISSED"), IF(DATEDIF(TEXT(TODAY(),"dd/mm/yyyy"),TEXT(B29,"dd/mm/")&RIGHT(A$1,4),"d") = 0,"TODAY!!!", IF(DATEDIF(TEXT(TODAY(),"dd/mm/yyyy"),TEXT(B29,"dd/mm/")&RIGHT(A$1,4),"d") > 0, DATEDIF(TEXT(TODAY(),"dd/mm/yyyy"), TEXT(B29,"dd/mm/")&RIGHT(A$1,4),"d")&" Days to go!",""))),"")
A30: Adam | B30: 42512 | C30: =TEXT(B30,"MMDD") -> 0522 | D30: =DATEDIF(B30,NOW(),"y") -> 10 | E30: 5 | F30: Cash. | G30: y | I30: =IF(E30<>"/",E30-H30,0) -> 5 | J30: =IF(TEXT(TODAY(),"YYYY")=RIGHT(A$1,4), IF(ISERROR(DATEDIF(TEXT(TODAY(),"dd/mm/yyyy"),TEXT(B30,"dd/mm/")&RIGHT(A$1,4),"d")),IF(G30="Y","DONE","MISSED"), IF(DATEDIF(TEXT(TODAY(),"dd/mm/yyyy"),TEXT(B30,"dd/mm/")&RIGHT(A$1,4),"d") = 0,"TODAY!!!", IF(DATEDIF(TEXT(TODAY(),"dd/mm/yyyy"),TEXT(B30,"dd/mm/")&RIGHT(A$1,4),"d") > 0, DATEDIF(TEXT(TODAY(),"dd/mm/yyyy"), TEXT(B30,"dd/mm/")&RIGHT(A$1,4),"d")&" Days to go!",""))),"")
A31: Alex | B31: 42513 | C31: =TEXT(B31,"MMDD") -> 0523 | D31: =DATEDIF(B31,NOW(),"y") -> 10 | E31: 10 | G31: y | I31: =IF(E31<>"/",E31-H31,0) -> 10 | J31: =IF(TEXT(TODAY(),"YYYY")=RIGHT(A$1,4), IF(ISERROR(DATEDIF(TEXT(TODAY(),"dd/mm/yyyy"),TEXT(B31,"dd/mm/")&RIGHT(A$1,4),"d")),IF(G31="Y","DONE","MISSED"), IF(DATEDIF(TEXT(TODAY(),"dd/mm/yyyy"),TEXT(B31,"dd/mm/")&RIGHT(A$1,4),"d") = 0,"TODAY!!!", IF(DATEDIF(TEXT(TODAY(),"dd/mm/yyyy"),TEXT(B31,"dd/mm/")&RIGHT(A$1,4),"d") > 0, DATEDIF(TEXT(TODAY(),"dd/mm/yyyy"), TEXT(B31,"dd/mm/")&RIGHT(A$1,4),"d")&" Days to go!",""))),"")
A32: Steve | B32: 26451 | C32: =TEXT(B32,"MMDD") -> 0601 | D32: =DATEDIF(B32,NOW(),"y") -> 54 | E32: 10 | G32: Y | I32: =IF(E32<>"/",E32-H32,0) -> 10 | J32: =IF(TEXT(TODAY(),"YYYY")=RIGHT(A$1,4), IF(ISERROR(DATEDIF(TEXT(TODAY(),"dd/mm/yyyy"),TEXT(B32,"dd/mm/")&RIGHT(A$1,4),"d")),IF(G32="Y","DONE","MISSED"), IF(DATEDIF(TEXT(TODAY(),"dd/mm/yyyy"),TEXT(B32,"dd/mm/")&RIGHT(A$1,4),"d") = 0,"TODAY!!!", IF(DATEDIF(TEXT(TODAY(),"dd/mm/yyyy"),TEXT(B32,"dd/mm/")&RIGHT(A$1,4),"d") > 0, DATEDIF(TEXT(TODAY(),"dd/mm/yyyy"), TEXT(B32,"dd/mm/")&RIGHT(A$1,4),"d")&" Days to go!",""))),"")
A33: Kat | B33: 29376 | C33: =TEXT(B33,"MMDD") -> 0604 | D33: =DATEDIF(B33,NOW(),"y") -> 46 | E33: 10 | G33: y | I33: =IF(E33<>"/",E33-H33,0) -> 10 | J33: =IF(TEXT(TODAY(),"YYYY")=RIGHT(A$1,4), IF(ISERROR(DATEDIF(TEXT(TODAY(),"dd/mm/yyyy"),TEXT(B33,"dd/mm/")&RIGHT(A$1,4),"d")),IF(G33="Y","DONE","MISSED"), IF(DATEDIF(TEXT(TODAY(),"dd/mm/yyyy"),TEXT(B33,"dd/mm/")&RIGHT(A$1,4),"d") = 0,"TODAY!!!", IF(DATEDIF(TEXT(TODAY(),"dd/mm/yyyy"),TEXT(B33,"dd/mm/")&RIGHT(A$1,4),"d") > 0, DATEDIF(TEXT(TODAY(),"dd/mm/yyyy"), TEXT(B33,"dd/mm/")&RIGHT(A$1,4),"d")&" Days to go!",""))),"")
A34: Charlotte (Niece) | B34: 35953 | C34: =TEXT(B34,"MMDD") -> 0607 | D34: =DATEDIF(B34,NOW(),"y") -> 28 | E34: 5 | F34: Cash. | G34: y | I34: =IF(E34<>"/",E34-H34,0) -> 5 | J34: =IF(TEXT(TODAY(),"YYYY")=RIGHT(A$1,4), IF(ISERROR(DATEDIF(TEXT(TODAY(),"dd/mm/yyyy"),TEXT(B34,"dd/mm/")&RIGHT(A$1,4),"d")),IF(G34="Y","DONE","MISSED"), IF(DATEDIF(TEXT(TODAY(),"dd/mm/yyyy"),TEXT(B34,"dd/mm/")&RIGHT(A$1,4),"d") = 0,"TODAY!!!", IF(DATEDIF(TEXT(TODAY(),"dd/mm/yyyy"),TEXT(B34,"dd/mm/")&RIGHT(A$1,4),"d") > 0, DATEDIF(TEXT(TODAY(),"dd/mm/yyyy"), TEXT(B34,"dd/mm/")&RIGHT(A$1,4),"d")&" Days to go!",""))),"")
A35: Emma | B35: 27928 | C35: =TEXT(B35,"MMDD") -> 0617 | D35: =DATEDIF(B35,NOW(),"y") -> 50 | E35: 10 | G35: y | I35: =IF(E35<>"/",E35-H35,0) -> 10 | J35: =IF(TEXT(TODAY(),"YYYY")=RIGHT(A$1,4), IF(ISERROR(DATEDIF(TEXT(TODAY(),"dd/mm/yyyy"),TEXT(B35,"dd/mm/")&RIGHT(A$1,4),"d")),IF(G35="Y","DONE","MISSED"), IF(DATEDIF(TEXT(TODAY(),"dd/mm/yyyy"),TEXT(B35,"dd/mm/")&RIGHT(A$1,4),"d") = 0,"TODAY!!!", IF(DATEDIF(TEXT(TODAY(),"dd/mm/yyyy"),TEXT(B35,"dd/mm/")&RIGHT(A$1,4),"d") > 0, DATEDIF(TEXT(TODAY(),"dd/mm/yyyy"), TEXT(B35,"dd/mm/")&RIGHT(A$1,4),"d")&" Days to go!",""))),"")
A36: Louise | B36: 42562 | C36: =TEXT(B36,"MMDD") -> 0711 | D36: =DATEDIF(B36,NOW(),"y") -> 10 | E36: / | G36: y | I36: =IF(E36<>"/",E36-H36,0) -> 0 | J36: =IF(TEXT(TODAY(),"YYYY")=RIGHT(A$1,4), IF(ISERROR(DATEDIF(TEXT(TODAY(),"dd/mm/yyyy"),TEXT(B36,"dd/mm/")&RIGHT(A$1,4),"d")),IF(G36="Y","DONE","MISSED"), IF(DATEDIF(TEXT(TODAY(),"dd/mm/yyyy"),TEXT(B36,"dd/mm/")&RIGHT(A$1,4),"d") = 0,"TODAY!!!", IF(DATEDIF(TEXT(TODAY(),"dd/mm/yyyy"),TEXT(B36,"dd/mm/")&RIGHT(A$1,4),"d") > 0, DATEDIF(TEXT(TODAY(),"dd/mm/yyyy"), TEXT(B36,"dd/mm/")&RIGHT(A$1,4),"d")&" Days to go!",""))),"")
A37: Keiran | B37: 42563 | C37: =TEXT(B37,"MMDD") -> 0712 | D37: =DATEDIF(B37,NOW(),"y") -> 10 | E37: 5 | F37: Cash. | G37: y | I37: =IF(E37<>"/",E37-H37,0) -> 5 | J37: =IF(TEXT(TODAY(),"YYYY")=RIGHT(A$1,4), IF(ISERROR(DATEDIF(TEXT(TODAY(),"dd/mm/yyyy"),TEXT(B37,"dd/mm/")&RIGHT(A$1,4),"d")),IF(G37="Y","DONE","MISSED"), IF(DATEDIF(TEXT(TODAY(),"dd/mm/yyyy"),TEXT(B37,"dd/mm/")&RIGHT(A$1,4),"d") = 0,"TODAY!!!", IF(DATEDIF(TEXT(TODAY(),"dd/mm/yyyy"),TEXT(B37,"dd/mm/")&RIGHT(A$1,4),"d") > 0, DATEDIF(TEXT(TODAY(),"dd/mm/yyyy"), TEXT(B37,"dd/mm/")&RIGHT(A$1,4),"d")&" Days to go!",""))),"")
A38: Charlotte | B38: 31995 | C38: =TEXT(B38,"MMDD") -> 0806 | D38: =DATEDIF(B38,NOW(),"y") -> 39 | E38: / | I38: =IF(E38<>"/",E38-H38,0) -> 0 | J38: =IF(TEXT(TODAY(),"YYYY")=RIGHT(A$1,4), IF(ISERROR(DATEDIF(TEXT(TODAY(),"dd/mm/yyyy"),TEXT(B38,"dd/mm/")&RIGHT(A$1,4),"d")),IF(G38="Y","DONE","MISSED"), IF(DATEDIF(TEXT(TODAY(),"dd/mm/yyyy"),TEXT(B38,"dd/mm/")&RIGHT(A$1,4),"d") = 0,"TODAY!!!", IF(DATEDIF(TEXT(TODAY(),"dd/mm/yyyy"),TEXT(B38,"dd/mm/")&RIGHT(A$1,4),"d") > 0, DATEDIF(TEXT(TODAY(),"dd/mm/yyyy"), TEXT(B38,"dd/mm/")&RIGHT(A$1,4),"d")&" Days to go!",""))),"")
